Workbook

Sheet WACC
B2: Weighted Average Cost Of Capital
B4: All figures are INR unless stated otherwise
B6: Peer Comps
H7: Debt/ | I7: Debt/ | J7: Levered | K7: Unlevered
B8: Name of the Company | D8: Country | E8: Total Debt | F8: Total Equity | G8: Tax Rate 1 | H8: Equity | I8: Capital | J8: Beta 2 | K8: Beta 3
B9: Hind. Unilever | D9: India | E9: ='Beta Comps'!F5 -> 1478 | F9: ='Beta Comps'!E5 -> 511505.98 | G9: 0.3 | H9: =IFERROR(E9/F9,0) -> 0.0028895068 | I9: =IFERROR(E9/SUM(E9:F9),0) -> 0.0028811816 | J9: ='Data - Hind. Unilever'!J6 -> 0.56045174 | K9: =IFERROR(J9/(1+H9*(1-G9)),0) -> 0.55932043
B10: Nestle India | D10: India | E10: ='Beta Comps'!F6 -> 444.16 | F10: ='Beta Comps'!E6 -> 276905.89 | G10: 0.3 | H10: =IFERROR(E10/F10,0) -> 0.0016040107 | I10: =IFERROR(E10/SUM(E10:F10),0) -> 0.0016014419 | J10: ='Data - Nestle India'!J6 -> 0.77963166 | K10: =IFERROR(J10/(1+H10*(1-G10)),0) -> 0.77875727
B11: Britannia Inds. | D11: India | E11: ='Beta Comps'!F7 -> 1380.28 | F11: ='Beta Comps'!E7 -> 129103.03 | G11: 0.3 | H11: =IFERROR(E11/F11,0) -> 0.010691306 | I11: =IFERROR(E11/SUM(E11:F11),0) -> 0.010578211 | J11: ='Data - Britannia Inds.'!J6 -> 0.51192831 | K11: =IFERROR(J11/(1+H11*(1-G11)),0) -> 0.50812555
B12: Godrej Consumer | D12: India | E12: ='Beta Comps'!F8 -> 4420.52 | F12: ='Beta Comps'!E8 -> 109595.96 | G12: 0.3 | H12: =IFERROR(E12/F12,0) -> 0.040334698 | I12: =IFERROR(E12/SUM(E12:F12),0) -> 0.038770886 | J12: ='Data - Godrej Consumer'!J6 -> 0.92476014 | K12: =IFERROR(J12/(1+H12*(1-G12)),0) -> 0.89936715
B13: Dabur India | D13: India | E13: ='Beta Comps'!F9 -> 1287.32 | F13: ='Beta Comps'!E9 -> 75703.42 | G13: 0.3 | H13: =IFERROR(E13/F13,0) -> 0.01700478 | I13: =IFERROR(E13/SUM(E13:F13),0) -> 0.016720452 | J13: ='Data - Dabur India'!J6 -> 0.87404026 | K13: =IFERROR(J13/(1+H13*(1-G13)),0) -> 0.86375864
F15: Average | G15: =IFERROR(AVERAGE(G9:G13),0) -> 0.3 | H15: =IFERROR(AVERAGE(H9:H13),0) -> 0.01450486 | I15: =IFERROR(AVERAGE(I9:I13),0) -> 0.014110435 | J15: =IFERROR(AVERAGE(J9:J13),0) -> 0.73016242 | K15: =IFERROR(AVERAGE(K9:K13),0) -> 0.72186581
F16: Median | G16: =IFERROR(MEDIAN(G9:G13),0) -> 0.3 | H16: =IFERROR(MEDIAN(H9:H13),0) -> 0.010691306 | I16: =IFERROR(MEDIAN(I9:I13),0) -> 0.010578211 | J16: =IFERROR(MEDIAN(J9:J13),0) -> 0.77963166 | K16: =IFERROR(MEDIAN(K9:K13),0) -> 0.77875727
B19: Cost of Debt | G19: Cost of Equity
B21: Pre tax cost of debt | E21: =410/1478 -> 0.27740189 | G21: Risk free rate | K21: 0.06769
B22: Tax rate | E22: 0.3 | G22: Equity Risk Premium | K22: ='DCF>'!F6-WACC!K21 -> 0.096802308
B23: Post Tax cost of debt | E23: =IFERROR(E21*(1-E22),0) -> 0.19418133 | G23: Levered Beta 4 | K23: =K32 -> 0.78458542
G24: Cost of Equity | K24: =K21+(K22*K23) -> 0.14363968
B27: Capital Structure | G27: Levered Beta
D29: Current | E29: Target | G29: Comps Median Unlevered Beta | K29: =K16 -> 0.77875727
B30: Total Debt | C30: =E9 -> 1478 | D30: =IFERROR(C30/$C$32,0) -> 0.0028811816 | E30: =I16 -> 0.010578211 | G30: Target Debt / Equity | K30: =E34 -> 0.010691306
B31: Market Capitalization | C31: =F9 -> 511505.98 | D31: =IFERROR(C31/$C$32,0) -> 0.99711882 | E31: =E32-E30 -> 0.98942179 | G31: Tax Rate | K31: =E22 -> 0.3
B32: Total Capital | C32: =IFERROR(SUM(C30:C31),0) -> 512983.98 | D32: =IFERROR(C32/$C$32,0) -> 1 | E32: =D32 -> 1 | G32: Levered Beta | K32: =K29*(1+(K30*(1-K31))) -> 0.78458542
B34: Debt / Equity | D34: =IFERROR(D30/D31,0) -> 0.0028895068 | E34: =IFERROR(E30/E31,0) -> 0.010691306 | G34: Weighted Average Cost of Capital
J36: Total Cost | K36: Total Weight
G37: Debt | J37: =E23 -> 0.19418133 | K37: =E30 -> 0.010578211
G38: Equity | J38: =K24 -> 0.14363968 | K38: =E31 -> 0.98942179
G39: Weighted Average Cost of Capital | K39: =SUMPRODUCT(J37:J38,K37:K38) -> 0.14417432
B41: Notes
B42: 1. Tax rate considered as mariginal tax rate of country
B43: 2. Levered Beta is based on 5 year montly data
B44: 3.Unlevered Beta = Levered Beta / (1+(Debt /Equity *(1- Tax rate )
B45: 4.Levered Beta = Unlevered Beta * (1+(Debt /Equity *(1- Tax rate )

Sheet Data - Hind. Unilever
B2: Regression Beta - 2 Years Weekly
B4: Hindustan Unilever Weekly Returns | F4: Nifty Returns | I4: Beta Drifting | L4: SUMMARY OUTPUT
B6: Date | C6: Adj Closing Price | D6: Return | F6: Adj Closing Price | G6: Return | I6: Levered Raw Beta | J6: =M21 -> 0.56045174 | L6: Regression Statistics
B7: 45495 | C7: 2604.8 | F7: 24834.85 | I7: Beta Weight | J7: 0.75 | L7: Multiple R | M7: 0.38284712
B8: 45502 | C8: 2587.0249 | D8: =IFERROR(C8/C7-1,0) -> -0.0068239965 | F8: 24717.699 | G8: =IFERROR(F8/F7-1,0) -> -0.0047171774 | L8: R Square | M8: 0.14657192
B9: 45509 | C9: 2639.5332 | D9: =IFERROR(C9/C8-1,0) -> 0.02029679 | F9: 24367.5 | G9: =IFERROR(F9/F8-1,0) -> -0.014167954 | L9: Adjusted R Square | M9: 0.13820497
B10: 45516 | C10: 2640.542 | D10: =IFERROR(C10/C9-1,0) -> 0.00038218465 | F10: 24541.15 | G10: =IFERROR(F10/F9-1,0) -> 0.0071263113 | I10: Market Beta | J10: 1 | L10: Standard Error | M10: 0.025047411
B11: 45523 | C11: 2705.2527 | D11: =IFERROR(C11/C10-1,0) -> 0.024506595 | F11: 24823.15 | G11: =IFERROR(F11/F10-1,0) -> 0.011490904 | I11: Market Beta Weight | J11: 0.25 | L11: Observations | M11: 104
B12: 45530 | C12: 2669.126 | D12: =IFERROR(C12/C11-1,0) -> -0.013354283 | F12: 25235.9 | G12: =IFERROR(F12/F11-1,0) -> 0.016627624
B13: 45537 | C13: 2727.6873 | D13: =IFERROR(C13/C12-1,0) -> 0.021940246 | F13: 24852.15 | G13: =IFERROR(F13/F12-1,0) -> -0.015206511 | I13: Adjusted Beta | J13: =IFERROR((J6*J7)+(J10*J11),0) -> 0.67033881 | L13: ANOVA
B14: 45544 | C14: 2818.0034 | D14: =IFERROR(C14/C13-1,0) -> 0.033110893 | F14: 25356.5 | G14: =IFERROR(F14/F13-1,0) -> 0.020294003 | M14: df | N14: SS | O14: MS | P14: F | Q14: Significance F
B15: 45551 | C15: 2860.9036 | D15: =IFERROR(C15/C14-1,0) -> 0.015223596 | F15: 25790.949 | G15: =IFERROR(F15/F14-1,0) -> 0.017133643 | L15: Regression | M15: 1 | N15: 0.010990304 | O15: 0.010990304 | P15: 17.517979 | Q15: 6.0453759e-05
B16: 45558 | C16: 2849.9983 | D16: =IFERROR(C16/C15-1,0) -> -0.0038118284 | F16: 26178.949 | G16: =IFERROR(F16/F15-1,0) -> 0.015044037 | L16: Residual | M16: 102 | N16: 0.063992027 | O16: 0.00062737282
B17: 45565 | C17: 2737.1035 | D17: =IFERROR(C17/C16-1,0) -> -0.039612226 | F17: 25014.6 | G17: =IFERROR(F17/F16-1,0) -> -0.04447656 | L17: Total | M17: 103 | N17: 0.074982331
B18: 45572 | C18: 2674.1223 | D18: =IFERROR(C18/C17-1,0) -> -0.023010164 | F18: 24964.25 | G18: =IFERROR(F18/F17-1,0) -> -0.0020128089
B19: 45579 | C19: 2610.6128 | D19: =IFERROR(C19/C18-1,0) -> -0.02374967 | F19: 24854.051 | G19: =IFERROR(F19/F18-1,0) -> -0.0044142812 | M19: Coefficients | N19: Standard Error | O19: t Stat | P19: P-value | Q19: Lower 95% | R19: Upper 95% | S19: Lower 95.0% | T19: Upper 95.0%
B20: 45586 | C20: 2428.9717 | D20: =IFERROR(C20/C19-1,0) -> -0.06957796 | F20: 24180.801 | G20: =IFERROR(F20/F19-1,0) -> -0.02708814 | L20: Intercept | M20: -0.0013115825 | N20: 0.0024562661 | O20: -0.5339741 | P20: 0.59452129 | Q20: -0.0061835746 | R20: 0.0035604097 | S20: -0.0061835746 | T20: 0.0035604097
B21: 45593 | C21: 2438.0515 | D21: =IFERROR(C21/C20-1,0) -> 0.0037381391 | F21: 24304.35 | G21: =IFERROR(F21/F20-1,0) -> 0.005109377 | L21: X Variable 1 | M21: 0.56045174 | N21: 0.13390482 | O21: 4.1854485 | P21: 6.0453759e-05 | Q21: 0.29485216 | R21: 0.82605132 | S21: 0.29485216 | T21: 0.82605132
B22: 45600 | C22: 2437.4546 | D22: =IFERROR(C22/C21-1,0) -> -0.00024483643 | F22: 24148.199 | G22: =IFERROR(F22/F21-1,0) -> -0.006424792 | M22: =SLOPE(D8:D111,G8:G111) -> 0.56045174
B23: 45607 | C23: 2322.2739 | D23: =IFERROR(C23/C22-1,0) -> -0.047254486 | F23: 23532.699 | G23: =IFERROR(F23/F22-1,0) -> -0.025488443
B24: 45614 | C24: 2376.7539 | D24: =IFERROR(C24/C23-1,0) -> 0.023459756 | F24: 23907.25 | G24: =IFERROR(F24/F23-1,0) -> 0.015916184
B25: 45621 | C25: 2426.2283 | D25: =IFERROR(C25/C24-1,0) -> 0.020815939 | F25: 24131.1 | G25: =IFERROR(F25/F24-1,0) -> 0.0093632521
B26: 45628 | C26: 2414.2241 | D26: =IFERROR(C26/C25-1,0) -> -0.0049476591 | F26: 24677.801 | G26: =IFERROR(F26/F25-1,0) -> 0.02265546
B27: 45635 | C27: 2323.1489 | D27: =IFERROR(C27/C26-1,0) -> -0.037724416 | F27: 24768.301 | G27: =IFERROR(F27/F26-1,0) -> 0.0036672636
B28: 45642 | C28: 2268.5232 | D28: =IFERROR(C28/C27-1,0) -> -0.023513659 | F28: 23587.5 | G28: =IFERROR(F28/F27-1,0) -> -0.047673871
B29: 45649 | C29: 2275.6672 | D29: =IFERROR(C29/C28-1,0) -> 0.0031492043 | F29: 23813.4 | G29: =IFERROR(F29/F28-1,0) -> 0.0095771231
B30: 45656 | C30: 2338.8464 | D30: =IFERROR(C30/C29-1,0) -> 0.027762934 | F30: 24004.75 | G30: =IFERROR(F30/F29-1,0) -> 0.0080353753
B31: 45663 | C31: 2373.6436 | D31: =IFERROR(C31/C30-1,0) -> 0.014877898 | F31: 23431.5 | G31: =IFERROR(F31/F30-1,0) -> -0.02388069
B32: 45670 | C32: 2288.0603 | D32: =IFERROR(C32/C31-1,0) -> -0.036055646 | F32: 23203.199 | G32: =IFERROR(F32/F31-1,0) -> -0.0097433276
B33: 45677 | C33: 2301.7651 | D33: =IFERROR(C33/C32-1,0) -> 0.0059897171 | F33: 23092.199 | G33: =IFERROR(F33/F32-1,0) -> -0.0047838231
B34: 45684 | C34: 2435.8511 | D34: =IFERROR(C34/C33-1,0) -> 0.058253527 | F34: 23482.15 | G34: =IFERROR(F34/F33-1,0) -> 0.016886706
... B111: 46223 | C111: 2161.8 | D111: =IFERROR(C111/C110-1,0) -> 0.0083963054 | F111: 23869.6 | G111: =IFERROR(F111/F110-1,0) -> -0.019096549

Sheet Data - Nestle India
B2: ='Data - Hind. Unilever'!B2 -> Regression Beta - 2 Years Weekly
B4: Nestle India Weekly Returns | F4: Nifty Returns | I4: Beta Drifting | L4: SUMMARY OUTPUT
B6: Date | C6: Adj Closing Price | D6: Return | F6: Adj Closing Price | G6: Return | I6: Levered Raw Beta | J6: =M21 -> 0.77963166 | L6: Regression Statistics
B7: 45495 | C7: 1213.0056 | F7: ='Data - Hind. Unilever'!F7 -> 24834.85 | I7: Beta Weight | J7: 0.75 | L7: Multiple R | M7: 0.50410626
B8: 45502 | C8: 1221.9187 | D8: =IFERROR(C8/C7-1,0) -> 0.0073479346 | F8: ='Data - Hind. Unilever'!F8 -> 24717.699 | G8: =IFERROR(F8/F7-1,0) -> -0.0047171774 | L8: R Square | M8: 0.25412312
B9: 45509 | C9: 1226.62 | D9: =IFERROR(C9/C8-1,0) -> 0.0038474687 | F9: ='Data - Hind. Unilever'!F9 -> 24367.5 | G9: =IFERROR(F9/F8-1,0) -> -0.014167954 | L9: Adjusted R Square | M9: 0.2468106
B10: 45516 | C10: 1236.7819 | D10: =IFERROR(C10/C9-1,0) -> 0.0082844445 | F10: ='Data - Hind. Unilever'!F10 -> 24541.15 | G10: =IFERROR(F10/F9-1,0) -> 0.0071263113 | I10: Market Beta | J10: 1 | L10: Standard Error | M10: 0.024738166
B11: 45523 | C11: 1238.6183 | D11: =IFERROR(C11/C10-1,0) -> 0.0014848421 | F11: ='Data - Hind. Unilever'!F11 -> 24823.15 | G11: =IFERROR(F11/F10-1,0) -> 0.011490904 | I11: Market Beta Weight | J11: 0.25 | L11: Observations | M11: 104
B12: 45530 | C12: 1224.6857 | D12: =IFERROR(C12/C11-1,0) -> -0.011248516 | F12: ='Data - Hind. Unilever'!F12 -> 25235.9 | G12: =IFERROR(F12/F11-1,0) -> 0.016627624
B13: 45537 | C13: 1225.8855 | D13: =IFERROR(C13/C12-1,0) -> 0.00097970372 | F13: ='Data - Hind. Unilever'!F13 -> 24852.15 | G13: =IFERROR(F13/F12-1,0) -> -0.015206511 | I13: Adjusted Beta | J13: =IFERROR((J6*J7)+(J10*J11),0) -> 0.83472375 | L13: ANOVA
B14: 45544 | C14: 1239.6957 | D14: =IFERROR(C14/C13-1,0) -> 0.011265474 | F14: ='Data - Hind. Unilever'!F14 -> 25356.5 | G14: =IFERROR(F14/F13-1,0) -> 0.020294003 | M14: df | N14: SS | O14: MS | P14: F | Q14: Significance F
B15: 45551 | C15: 1322.0433 | D15: =IFERROR(C15/C14-1,0) -> 0.066425702 | F15: ='Data - Hind. Unilever'!F15 -> 25790.949 | G15: =IFERROR(F15/F14-1,0) -> 0.017133643 | L15: Regression | M15: 1 | N15: 0.021267292 | O15: 0.021267292 | P15: 34.751792 | Q15: 4.8816986e-08
B16: 45558 | C16: 1344.6444 | D16: =IFERROR(C16/C15-1,0) -> 0.017095562 | F16: ='Data - Hind. Unilever'!F16 -> 26178.949 | G16: =IFERROR(F16/F15-1,0) -> 0.015044037 | L16: Residual | M16: 102 | N16: 0.062421638 | O16: 0.00061197685
B17: 45565 | C17: 1272.3851 | D17: =IFERROR(C17/C16-1,0) -> -0.053738577 | F17: ='Data - Hind. Unilever'!F17 -> 25014.6 | G17: =IFERROR(F17/F16-1,0) -> -0.04447656 | L17: Total | M17: 103 | N17: 0.08368893
B18: 45572 | C18: 1230.0972 | D18: =IFERROR(C18/C17-1,0) -> -0.033235192 | F18: ='Data - Hind. Unilever'!F18 -> 24964.25 | G18: =IFERROR(F18/F17-1,0) -> -0.0020128089
B19: 45579 | C19: 1150.9817 | D19: =IFERROR(C19/C18-1,0) -> -0.064316446 | F19: ='Data - Hind. Unilever'!F19 -> 24854.051 | G19: =IFERROR(F19/F18-1,0) -> -0.0044142812 | M19: Coefficients | N19: Standard Error | O19: t Stat | P19: P-value | Q19: Lower 95% | R19: Upper 95% | S19: Lower 95.0% | T19: Upper 95.0%
B20: 45586 | C20: 1107.1266 | D20: =IFERROR(C20/C19-1,0) -> -0.038102346 | F20: ='Data - Hind. Unilever'!F20 -> 24180.801 | G20: =IFERROR(F20/F19-1,0) -> -0.02708814 | L20: Intercept | M20: 0.0022390716 | N20: 0.00242594 | O20: 0.92297072 | P20: 0.35820062 | Q20: -0.0025727689 | R20: 0.0070509122 | S20: -0.0025727689 | T20: 0.0070509122
B21: 45593 | C21: 1117.7046 | D21: =IFERROR(C21/C20-1,0) -> 0.0095544656 | F21: ='Data - Hind. Unilever'!F21 -> 24304.35 | G21: =IFERROR(F21/F20-1,0) -> 0.005109377 | L21: X Variable 1 | M21: 0.77963166 | N21: 0.13225158 | O21: 5.895065 | P21: 4.8816986e-08 | Q21: 0.51731128 | R21: 1.041952 | S21: 0.51731128 | T21: 1.041952
B22: 45600 | C22: 1124.2424 | D22: =IFERROR(C22/C21-1,0) -> 0.0058493468 | F22: ='Data - Hind. Unilever'!F22 -> 24148.199 | G22: =IFERROR(F22/F21-1,0) -> -0.006424792 | M22: =SLOPE(D8:D111,G8:G111) -> 0.77963166
B23: 45607 | C23: 1068.9768 | D23: =IFERROR(C23/C22-1,0) -> -0.049158103 | F23: ='Data - Hind. Unilever'!F23 -> 23532.699 | G23: =IFERROR(F23/F22-1,0) -> -0.025488443
B24: 45614 | C24: 1100.5643 | D24: =IFERROR(C24/C23-1,0) -> 0.029549308 | F24: ='Data - Hind. Unilever'!F24 -> 23907.25 | G24: =IFERROR(F24/F23-1,0) -> 0.015916184
B25: 45621 | C25: 1094.369 | D25: =IFERROR(C25/C24-1,0) -> -0.0056292143 | F25: ='Data - Hind. Unilever'!F25 -> 24131.1 | G25: =IFERROR(F25/F24-1,0) -> 0.0093632521
B26: 45628 | C26: 1110.6036 | D26: =IFERROR(C26/C25-1,0) -> 0.014834685 | F26: ='Data - Hind. Unilever'!F26 -> 24677.801 | G26: =IFERROR(F26/F25-1,0) -> 0.02265546
B27: 45635 | C27: 1103.6005 | D27: =IFERROR(C27/C26-1,0) -> -0.0063057364 | F27: ='Data - Hind. Unilever'!F27 -> 24768.301 | G27: =IFERROR(F27/F26-1,0) -> 0.0036672636
B28: 45642 | C28: 1059.525 | D28: =IFERROR(C28/C27-1,0) -> -0.039937859 | F28: ='Data - Hind. Unilever'!F28 -> 23587.5 | G28: =IFERROR(F28/F27-1,0) -> -0.047673871
B29: 45649 | C29: 1060.5536 | D29: =IFERROR(C29/C28-1,0) -> 0.00097077882 | F29: ='Data - Hind. Unilever'!F29 -> 23813.4 | G29: =IFERROR(F29/F28-1,0) -> 0.0095771231
B30: 45656 | C30: 1093.4142 | D30: =IFERROR(C30/C29-1,0) -> 0.03098438 | F30: ='Data - Hind. Unilever'!F30 -> 24004.75 | G30: =IFERROR(F30/F29-1,0) -> 0.0080353753
B31: 45663 | C31: 1100.8582 | D31: =IFERROR(C31/C30-1,0) -> 0.0068080054 | F31: ='Data - Hind. Unilever'!F31 -> 23431.5 | G31: =IFERROR(F31/F30-1,0) -> -0.02388069
B32: 45670 | C32: 1085.8234 | D32: =IFERROR(C32/C31-1,0) -> -0.013657336 | F32: ='Data - Hind. Unilever'!F32 -> 23203.199 | G32: =IFERROR(F32/F31-1,0) -> -0.0097433276
B33: 45677 | C33: 1081.2688 | D33: =IFERROR(C33/C32-1,0) -> -0.0041945731 | F33: ='Data - Hind. Unilever'!F33 -> 23092.199 | G33: =IFERROR(F33/F32-1,0) -> -0.0047838231
B34: 45684 | C34: 1139.6934 | D34: =IFERROR(C34/C33-1,0) -> 0.054033336 | F34: ='Data - Hind. Unilever'!F34 -> 23482.15 | G34: =IFERROR(F34/F33-1,0) -> 0.016886706
... B111: 46223 | C111: 1443.5 | D111: =IFERROR(C111/C110-1,0) -> 0.011420999 | F111: ='Data - Hind. Unilever'!F111 -> 23869.6 | G111: =IFERROR(F111/F110-1,0) -> -0.019096549

Sheet Data - Britannia Inds.
B2: ='Data - Hind. Unilever'!B2 -> Regression Beta - 2 Years Weekly
B4: Britannia India Weekly Returns | F4: Nifty Returns | I4: Beta Drifting | L4: SUMMARY OUTPUT
B6: Date | C6: Adj Closing Price | D6: Return | F6: Adj Closing Price | G6: Return | I6: Levered Raw Beta | J6: =M21 -> 0.51192831 | L6: Regression Statistics
B7: 45495 | C7: 5722.3496 | F7: ='Data - Hind. Unilever'!F7 -> 24834.85 | I7: Beta Weight | J7: 0.75 | L7: Multiple R | M7: 0.32575591
B8: 45502 | C8: 5573.8052 | D8: =IFERROR(C8/C7-1,0) -> -0.025958644 | F8: ='Data - Hind. Unilever'!F8 -> 24717.699 | G8: =IFERROR(F8/F7-1,0) -> -0.0047171774 | L8: R Square | M8: 0.10611692
B9: 45509 | C9: 5666.0459 | D9: =IFERROR(C9/C8-1,0) -> 0.016548968 | F9: ='Data - Hind. Unilever'!F9 -> 24367.5 | G9: =IFERROR(F9/F8-1,0) -> -0.014167954 | L9: Adjusted R Square | M9: 0.097353355
B10: 45516 | C10: 5655.5337 | D10: =IFERROR(C10/C9-1,0) -> -0.0018552986 | F10: ='Data - Hind. Unilever'!F10 -> 24541.15 | G10: =IFERROR(F10/F9-1,0) -> 0.0071263113 | I10: Market Beta | J10: 1 | L10: Standard Error | M10: 0.027518436
B11: 45523 | C11: 5717.7188 | D11: =IFERROR(C11/C10-1,0) -> 0.010995436 | F11: ='Data - Hind. Unilever'!F11 -> 24823.15 | G11: =IFERROR(F11/F10-1,0) -> 0.011490904 | I11: Market Beta Weight | J11: 0.25 | L11: Observations | M11: 104
B12: 45530 | C12: 5779.5093 | D12: =IFERROR(C12/C11-1,0) -> 0.01080685 | F12: ='Data - Hind. Unilever'!F12 -> 25235.9 | G12: =IFERROR(F12/F11-1,0) -> 0.016627624
B13: 45537 | C13: 5767.9604 | D13: =IFERROR(C13/C12-1,0) -> -0.0019982368 | F13: ='Data - Hind. Unilever'!F13 -> 24852.15 | G13: =IFERROR(F13/F12-1,0) -> -0.015206511 | I13: Adjusted Beta | J13: =IFERROR((J6*J7)+(J10*J11),0) -> 0.63394623 | L13: ANOVA
B14: 45544 | C14: 6053.7651 | D14: =IFERROR(C14/C13-1,0) -> 0.04955039 | F14: ='Data - Hind. Unilever'!F14 -> 25356.5 | G14: =IFERROR(F14/F13-1,0) -> 0.020294003 | M14: df | N14: SS | O14: MS | P14: F | Q14: Significance F
B15: 45551 | C15: 6130.2129 | D15: =IFERROR(C15/C14-1,0) -> 0.012628133 | F15: ='Data - Hind. Unilever'!F15 -> 25790.949 | G15: =IFERROR(F15/F14-1,0) -> 0.017133643 | L15: Regression | M15: 1 | N15: 0.0091696246 | O15: 0.0091696246 | P15: 12.108883 | Q15: 0.000739614
B16: 45558 | C16: 6187.7095 | D16: =IFERROR(C16/C15-1,0) -> 0.0093792146 | F16: ='Data - Hind. Unilever'!F16 -> 26178.949 | G16: =IFERROR(F16/F15-1,0) -> 0.015044037 | L16: Residual | M16: 102 | N16: 0.077240959 | O16: 0.00075726431
B17: 45565 | C17: 6125.7222 | D17: =IFERROR(C17/C16-1,0) -> -0.010017811 | F17: ='Data - Hind. Unilever'!F17 -> 25014.6 | G17: =IFERROR(F17/F16-1,0) -> -0.04447656 | L17: Total | M17: 103 | N17: 0.086410584
B18: 45572 | C18: 5901.165 | D18: =IFERROR(C18/C17-1,0) -> -0.036658066 | F18: ='Data - Hind. Unilever'!F18 -> 24964.25 | G18: =IFERROR(F18/F17-1,0) -> -0.0020128089
B19: 45579 | C19: 5811.0464 | D19: =IFERROR(C19/C18-1,0) -> -0.015271332 | F19: ='Data - Hind. Unilever'!F19 -> 24854.051 | G19: =IFERROR(F19/F18-1,0) -> -0.0044142812 | M19: Coefficients | N19: Standard Error | O19: t Stat | P19: P-value | Q19: Lower 95% | R19: Upper 95% | S19: Lower 95.0% | T19: Upper 95.0%
B20: 45586 | C20: 5596.0635 | D20: =IFERROR(C20/C19-1,0) -> -0.036995559 | F20: ='Data - Hind. Unilever'!F20 -> 24180.801 | G20: =IFERROR(F20/F19-1,0) -> -0.02708814 | L20: Intercept | M20: -5.9181317e-05 | N20: 0.0026985863 | O20: -0.021930489 | P20: 0.98254625 | Q20: -0.0054118144 | R20: 0.0052934518 | S20: -0.0054118144 | T20: 0.0052934518
B21: 45593 | C21: 5619.4072 | D21: =IFERROR(C21/C20-1,0) -> 0.0041714591 | F21: ='Data - Hind. Unilever'!F21 -> 24304.35 | G21: =IFERROR(F21/F20-1,0) -> 0.005109377 | L21: X Variable 1 | M21: 0.51192831 | N21: 0.14711505 | O21: 3.479782 | P21: 0.000739614 | Q21: 0.2201263 | R21: 0.80373033 | S21: 0.2201263 | T21: 0.80373033
B22: 45600 | C22: 5672.8076 | D22: =IFERROR(C22/C21-1,0) -> 0.0095028512 | F22: ='Data - Hind. Unilever'!F22 -> 24148.199 | G22: =IFERROR(F22/F21-1,0) -> -0.006424792 | M22: =SLOPE(D8:D111,G8:G111) -> 0.51192831
B23: 45607 | C23: 4852.0142 | D23: =IFERROR(C23/C22-1,0) -> -0.14468911 | F23: ='Data - Hind. Unilever'!F23 -> 23532.699 | G23: =IFERROR(F23/F22-1,0) -> -0.025488443
B24: 45614 | C24: 4785.6343 | D24: =IFERROR(C24/C23-1,0) -> -0.013680892 | F24: ='Data - Hind. Unilever'!F24 -> 23907.25 | G24: =IFERROR(F24/F23-1,0) -> 0.015916184
B25: 45621 | C25: 4877.2334 | D25: =IFERROR(C25/C24-1,0) -> 0.019140435 | F25: ='Data - Hind. Unilever'!F25 -> 24131.1 | G25: =IFERROR(F25/F24-1,0) -> 0.0093632521
B26: 45628 | C26: 4807.8433 | D26: =IFERROR(C26/C25-1,0) -> -0.014227356 | F26: ='Data - Hind. Unilever'!F26 -> 24677.801 | G26: =IFERROR(F26/F25-1,0) -> 0.02265546
B27: 45635 | C27: 4787.3613 | D27: =IFERROR(C27/C26-1,0) -> -0.0042601084 | F27: ='Data - Hind. Unilever'!F27 -> 24768.301 | G27: =IFERROR(F27/F26-1,0) -> 0.0036672636
B28: 45642 | C28: 4637.3276 | D28: =IFERROR(C28/C27-1,0) -> -0.031339538 | F28: ='Data - Hind. Unilever'!F28 -> 23587.5 | G28: =IFERROR(F28/F27-1,0) -> -0.047673871
B29: 45649 | C29: 4707.6064 | D29: =IFERROR(C29/C28-1,0) -> 0.015155023 | F29: ='Data - Hind. Unilever'!F29 -> 23813.4 | G29: =IFERROR(F29/F28-1,0) -> 0.0095771231
B30: 45656 | C30: 4771.5684 | D30: =IFERROR(C30/C29-1,0) -> 0.013586929 | F30: ='Data - Hind. Unilever'!F30 -> 24004.75 | G30: =IFERROR(F30/F29-1,0) -> 0.0080353753
B31: 45663 | C31: 4875.3091 | D31: =IFERROR(C31/C30-1,0) -> 0.021741431 | F31: ='Data - Hind. Unilever'!F31 -> 23431.5 | G31: =IFERROR(F31/F30-1,0) -> -0.02388069
B32: 45670 | C32: 4791.606 | D32: =IFERROR(C32/C31-1,0) -> -0.017168783 | F32: ='Data - Hind. Unilever'!F32 -> 23203.199 | G32: =IFERROR(F32/F31-1,0) -> -0.0097433276
B33: 45677 | C33: 5035.5586 | D33: =IFERROR(C33/C32-1,0) -> 0.0509125 | F33: ='Data - Hind. Unilever'!F33 -> 23092.199 | G33: =IFERROR(F33/F32-1,0) -> -0.0047838231
B34: 45684 | C34: 5134.0679 | D34: =IFERROR(C34/C33-1,0) -> 0.019562731 | F34: ='Data - Hind. Unilever'!F34 -> 23482.15 | G34: =IFERROR(F34/F33-1,0) -> 0.016886706
... B111: 46223 | C111: 5379.5 | D111: =IFERROR(C111/C110-1,0) -> -0.0060969977 | F111: ='Data - Hind. Unilever'!F111 -> 23869.6 | G111: =IFERROR(F111/F110-1,0) -> -0.019096549

Sheet Data - Godrej Consumer
B2: ='Data - Hind. Unilever'!B2 -> Regression Beta - 2 Years Weekly
B4: Godrej Weekly Returns | F4: Nifty Returns | I4: Beta Drifting | L4: SUMMARY OUTPUT
B6: Date | C6: Adj Closing Price | D6: Return | F6: Adj Closing Price | G6: Return | I6: Levered Raw Beta | J6: =M21 -> 0.92476014 | L6: Regression Statistics
B7: 45495 | C7: 1419.2407 | F7: ='Data - Hind. Unilever'!F7 -> 24834.85 | I7: Beta Weight | J7: 0.75 | L7: Multiple R | M7: 0.49135767
B8: 45502 | C8: 1411.1654 | D8: =IFERROR(C8/C7-1,0) -> -0.0056898856 | F8: ='Data - Hind. Unilever'!F8 -> 24717.699 | G8: =IFERROR(F8/F7-1,0) -> -0.0047171774 | L8: R Square | M8: 0.24143236
B9: 45509 | C9: 1397.2872 | D9: =IFERROR(C9/C8-1,0) -> -0.0098345479 | F9: ='Data - Hind. Unilever'!F9 -> 24367.5 | G9: =IFERROR(F9/F8-1,0) -> -0.014167954 | L9: Adjusted R Square | M9: 0.23399542
B10: 45516 | C10: 1363.8181 | D10: =IFERROR(C10/C9-1,0) -> -0.023952925 | F10: ='Data - Hind. Unilever'!F10 -> 24541.15 | G10: =IFERROR(F10/F9-1,0) -> 0.0071263113 | I10: Market Beta | J10: 1 | L10: Standard Error | M10: 0.030359531
B11: 45523 | C11: 1386.4343 | D11: =IFERROR(C11/C10-1,0) -> 0.016583011 | F11: ='Data - Hind. Unilever'!F11 -> 24823.15 | G11: =IFERROR(F11/F10-1,0) -> 0.011490904 | I11: Market Beta Weight | J11: 0.25 | L11: Observations | M11: 104
B12: 45530 | C12: 1437.7334 | D12: =IFERROR(C12/C11-1,0) -> 0.037000723 | F12: ='Data - Hind. Unilever'!F12 -> 25235.9 | G12: =IFERROR(F12/F11-1,0) -> 0.016627624
B13: 45537 | C13: 1401.0912 | D13: =IFERROR(C13/C12-1,0) -> -0.025486096 | F13: ='Data - Hind. Unilever'!F13 -> 24852.15 | G13: =IFERROR(F13/F12-1,0) -> -0.015206511 | I13: Adjusted Beta | J13: =IFERROR((J6*J7)+(J10*J11),0) -> 0.94357011 | L13: ANOVA
B14: 45544 | C14: 1447.537 | D14: =IFERROR(C14/C13-1,0) -> 0.033149734 | F14: ='Data - Hind. Unilever'!F14 -> 25356.5 | G14: =IFERROR(F14/F13-1,0) -> 0.020294003 | M14: df | N14: SS | O14: MS | P14: F | Q14: Significance F
B15: 45551 | C15: 1413.8552 | D15: =IFERROR(C15/C14-1,0) -> -0.023268326 | F15: ='Data - Hind. Unilever'!F15 -> 25790.949 | G15: =IFERROR(F15/F14-1,0) -> 0.017133643 | L15: Regression | M15: 1 | N15: 0.029922058 | O15: 0.029922058 | P15: 32.463948 | Q15: 1.1820065e-07
B16: 45558 | C16: 1347.8994 | D16: =IFERROR(C16/C15-1,0) -> -0.046649621 | F16: ='Data - Hind. Unilever'!F16 -> 26178.949 | G16: =IFERROR(F16/F15-1,0) -> 0.015044037 | L16: Residual | M16: 102 | N16: 0.094013516 | O16: 0.00092170114
B17: 45565 | C17: 1303.8317 | D17: =IFERROR(C17/C16-1,0) -> -0.032693648 | F17: ='Data - Hind. Unilever'!F17 -> 25014.6 | G17: =IFERROR(F17/F16-1,0) -> -0.04447656 | L17: Total | M17: 103 | N17: 0.12393557
B18: 45572 | C18: 1277.0901 | D18: =IFERROR(C18/C17-1,0) -> -0.020509992 | F18: ='Data - Hind. Unilever'!F18 -> 24964.25 | G18: =IFERROR(F18/F17-1,0) -> -0.0020128089
B19: 45579 | C19: 1296.9399 | D19: =IFERROR(C19/C18-1,0) -> 0.015543033 | F19: ='Data - Hind. Unilever'!F19 -> 24854.051 | G19: =IFERROR(F19/F18-1,0) -> -0.0044142812 | M19: Coefficients | N19: Standard Error | O19: t Stat | P19: P-value | Q19: Lower 95% | R19: Upper 95% | S19: Lower 95.0% | T19: Upper 95.0%
B20: 45586 | C20: 1253.3574 | D20: =IFERROR(C20/C19-1,0) -> -0.033604115 | F20: ='Data - Hind. Unilever'!F20 -> 24180.801 | G20: =IFERROR(F20/F19-1,0) -> -0.02708814 | L20: Intercept | M20: -0.0020117227 | N20: 0.0029771974 | O20: -0.67571022 | P20: 0.50075375 | Q20: -0.0079169796 | R20: 0.0038935342 | S20: -0.0079169796 | T20: 0.0038935342
B21: 45593 | C21: 1242.4598 | D21: =IFERROR(C21/C20-1,0) -> -0.008694713 | F21: ='Data - Hind. Unilever'!F21 -> 24304.35 | G21: =IFERROR(F21/F20-1,0) -> 0.005109377 | L21: X Variable 1 | M21: 0.92476014 | N21: 0.1623037 | O21: 5.6977143 | P21: 1.1820065e-07 | Q21: 0.60283151 | R21: 1.2466888 | S21: 0.60283151 | T21: 1.2466888
B22: 45600 | C22: 1219.0256 | D22: =IFERROR(C22/C21-1,0) -> -0.018861136 | F22: ='Data - Hind. Unilever'!F22 -> 24148.199 | G22: =IFERROR(F22/F21-1,0) -> -0.006424792 | M22: =SLOPE(D8:D111,G8:G111) -> 0.92476014
B23: 45607 | C23: 1145.0197 | D23: =IFERROR(C23/C22-1,0) -> -0.060709126 | F23: ='Data - Hind. Unilever'!F23 -> 23532.699 | G23: =IFERROR(F23/F22-1,0) -> -0.025488443
B24: 45614 | C24: 1161.7794 | D24: =IFERROR(C24/C23-1,0) -> 0.014637099 | F24: ='Data - Hind. Unilever'!F24 -> 23907.25 | G24: =IFERROR(F24/F23-1,0) -> 0.015916184
B25: 45621 | C25: 1212.7893 | D25: =IFERROR(C25/C24-1,0) -> 0.043906689 | F25: ='Data - Hind. Unilever'!F25 -> 24131.1 | G25: =IFERROR(F25/F24-1,0) -> 0.0093632521
B26: 45628 | C26: 1203.8248 | D26: =IFERROR(C26/C25-1,0) -> -0.0073916199 | F26: ='Data - Hind. Unilever'!F26 -> 24677.801 | G26: =IFERROR(F26/F25-1,0) -> 0.02265546
B27: 45635 | C27: 1082.999 | D27: =IFERROR(C27/C26-1,0) -> -0.10036826 | F27: ='Data - Hind. Unilever'!F27 -> 24768.301 | G27: =IFERROR(F27/F26-1,0) -> 0.0036672636
B28: 45642 | C28: 1042.2205 | D28: =IFERROR(C28/C27-1,0) -> -0.037653371 | F28: ='Data - Hind. Unilever'!F28 -> 23587.5 | G28: =IFERROR(F28/F27-1,0) -> -0.047673871
B29: 45649 | C29: 1040.4664 | D29: =IFERROR(C29/C28-1,0) -> -0.0016829725 | F29: ='Data - Hind. Unilever'!F29 -> 23813.4 | G29: =IFERROR(F29/F28-1,0) -> 0.0095771231
B30: 45656 | C30: 1088.066 | D30: =IFERROR(C30/C29-1,0) -> 0.045748337 | F30: ='Data - Hind. Unilever'!F30 -> 24004.75 | G30: =IFERROR(F30/F29-1,0) -> 0.0080353753
B31: 45663 | C31: 1144.2402 | D31: =IFERROR(C31/C30-1,0) -> 0.05162756 | F31: ='Data - Hind. Unilever'!F31 -> 23431.5 | G31: =IFERROR(F31/F30-1,0) -> -0.02388069
B32: 45670 | C32: 1157.3459 | D32: =IFERROR(C32/C31-1,0) -> 0.011453638 | F32: ='Data - Hind. Unilever'!F32 -> 23203.199 | G32: =IFERROR(F32/F31-1,0) -> -0.0097433276
B33: 45677 | C33: 1101.4152 | D33: =IFERROR(C33/C32-1,0) -> -0.048326765 | F33: ='Data - Hind. Unilever'!F33 -> 23092.199 | G33: =IFERROR(F33/F32-1,0) -> -0.0047838231
B34: 45684 | C34: 1161.1948 | D34: =IFERROR(C34/C33-1,0) -> 0.054275323 | F34: ='Data - Hind. Unilever'!F34 -> 23482.15 | G34: =IFERROR(F34/F33-1,0) -> 0.016886706
... B111: 46223 | C111: 1059.5 | D111: =IFERROR(C111/C110-1,0) -> -0.011568266 | F111: ='Data - Hind. Unilever'!F111 -> 23869.6 | G111: =IFERROR(F111/F110-1,0) -> -0.019096549

Sheet Data - Dabur India
B2: ='Data - Hind. Unilever'!B2 -> Regression Beta - 2 Years Weekly
B4: Dabur India Weekly Returns | F4: Nifty Returns | I4: Beta Drifting | L4: SUMMARY OUTPUT
B6: Date | C6: Adj Closing Price | D6: Return | F6: Adj Closing Price | G6: Return | I6: Levered Raw Beta | J6: =M21 -> 0.87404026 | L6: Regression Statistics
B7: 45495 | C7: 611.74072 | F7: ='Data - Hind. Unilever'!F7 -> 24834.85 | I7: Beta Weight | J7: 0.75 | L7: Multiple R | M7: 0.49186415
B8: 45502 | C8: 607.0011 | D8: =IFERROR(C8/C7-1,0) -> -0.0077477661 | F8: ='Data - Hind. Unilever'!F8 -> 24717.699 | G8: =IFERROR(F8/F7-1,0) -> -0.0047171774 | L8: R Square | M8: 0.24193034
B9: 45509 | C9: 603.51904 | D9: =IFERROR(C9/C8-1,0) -> -0.0057364899 | F9: ='Data - Hind. Unilever'!F9 -> 24367.5 | G9: =IFERROR(F9/F8-1,0) -> -0.014167954 | L9: Adjusted R Square | M9: 0.23449828
B10: 45516 | C10: 597.37695 | D10: =IFERROR(C10/C9-1,0) -> -0.010177127 | F10: ='Data - Hind. Unilever'!F10 -> 24541.15 | G10: =IFERROR(F10/F9-1,0) -> 0.0071263113 | I10: Market Beta | J10: 1 | L10: Standard Error | M10: 0.028655459
B11: 45523 | C11: 622.18701 | D11: =IFERROR(C11/C10-1,0) -> 0.041531663 | F11: ='Data - Hind. Unilever'!F11 -> 24823.15 | G11: =IFERROR(F11/F10-1,0) -> 0.011490904 | I11: Market Beta Weight | J11: 0.25 | L11: Observations | M11: 104
B12: 45530 | C12: 616.2868 | D12: =IFERROR(C12/C11-1,0) -> -0.009483013 | F12: ='Data - Hind. Unilever'!F12 -> 25235.9 | G12: =IFERROR(F12/F11-1,0) -> 0.016627624
B13: 45537 | C13: 623.29944 | D13: =IFERROR(C13/C12-1,0) -> 0.011378849 | F13: ='Data - Hind. Unilever'!F13 -> 24852.15 | G13: =IFERROR(F13/F12-1,0) -> -0.015206511 | I13: Adjusted Beta | J13: =IFERROR((J6*J7)+(J10*J11),0) -> 0.90553019 | L13: ANOVA
B14: 45544 | C14: 639.25916 | D14: =IFERROR(C14/C13-1,0) -> 0.025605216 | F14: ='Data - Hind. Unilever'!F14 -> 25356.5 | G14: =IFERROR(F14/F13-1,0) -> 0.020294003 | M14: df | N14: SS | O14: MS | P14: F | Q14: Significance F
B15: 45551 | C15: 645.69135 | D15: =IFERROR(C15/C14-1,0) -> 0.010061944 | F15: ='Data - Hind. Unilever'!F15 -> 25790.949 | G15: =IFERROR(F15/F14-1,0) -> 0.017133643 | L15: Regression | M15: 1 | N15: 0.026729826 | O15: 0.026729826 | P15: 32.552278 | Q15: 1.1419806e-07
B16: 45558 | C16: 612.27271 | D16: =IFERROR(C16/C15-1,0) -> -0.05175637 | F16: ='Data - Hind. Unilever'!F16 -> 26178.949 | G16: =IFERROR(F16/F15-1,0) -> 0.015044037 | L16: Residual | M16: 102 | N16: 0.083755804 | O16: 0.00082113533
B17: 45565 | C17: 553.70538 | D17: =IFERROR(C17/C16-1,0) -> -0.095655614 | F17: ='Data - Hind. Unilever'!F17 -> 25014.6 | G17: =IFERROR(F17/F16-1,0) -> -0.04447656 | L17: Total | M17: 103 | N17: 0.11048563
B18: 45572 | C18: 552.15771 | D18: =IFERROR(C18/C17-1,0) -> -0.0027951118 | F18: ='Data - Hind. Unilever'!F18 -> 24964.25 | G18: =IFERROR(F18/F17-1,0) -> -0.0020128089
B19: 45579 | C19: 552.68976 | D19: =IFERROR(C19/C18-1,0) -> 0.00096357154 | F19: ='Data - Hind. Unilever'!F19 -> 24854.051 | G19: =IFERROR(F19/F18-1,0) -> -0.0044142812 | M19: Coefficients | N19: Standard Error | O19: t Stat | P19: P-value | Q19: Lower 95% | R19: Upper 95% | S19: Lower 95.0% | T19: Upper 95.0%
B20: 45586 | C20: 521.06049 | D20: =IFERROR(C20/C19-1,0) -> -0.057227897 | F20: ='Data - Hind. Unilever'!F20 -> 24180.801 | G20: =IFERROR(F20/F19-1,0) -> -0.02708814 | L20: Intercept | M20: -0.0028181025 | N20: 0.0028100881 | O20: -1.002852 | P20: 0.31830543 | Q20: -0.0083918989 | R20: 0.0027556939 | S20: -0.0083918989 | T20: 0.0027556939
B21: 45593 | C21: 524.78442 | D21: =IFERROR(C21/C20-1,0) -> 0.007146844 | F21: ='Data - Hind. Unilever'!F21 -> 24304.35 | G21: =IFERROR(F21/F20-1,0) -> 0.005109377 | L21: X Variable 1 | M21: 0.87404026 | N21: 0.15319364 | O21: 5.7054604 | P21: 1.1419806e-07 | Q21: 0.57018139 | R21: 1.1778991 | S21: 0.57018139 | T21: 1.1778991
B22: 45600 | C22: 516.75494 | D22: =IFERROR(C22/C21-1,0) -> -0.01530053 | F22: ='Data - Hind. Unilever'!F22 -> 24148.199 | G22: =IFERROR(F22/F21-1,0) -> -0.006424792 | M22: =SLOPE(D8:D111,G8:G111) -> 0.87404026
B23: 45607 | C23: 494.00415 | D23: =IFERROR(C23/C22-1,0) -> -0.044026272 | F23: ='Data - Hind. Unilever'!F23 -> 23532.699 | G23: =IFERROR(F23/F22-1,0) -> -0.025488443
B24: 45614 | C24: 498.76822 | D24: =IFERROR(C24/C23-1,0) -> 0.0096437825 | F24: ='Data - Hind. Unilever'!F24 -> 23907.25 | G24: =IFERROR(F24/F23-1,0) -> 0.015916184
B25: 45621 | C25: 512.5257 | D25: =IFERROR(C25/C24-1,0) -> 0.027582906 | F25: ='Data - Hind. Unilever'!F25 -> 24131.1 | G25: =IFERROR(F25/F24-1,0) -> 0.0093632521
B26: 45628 | C26: 509.26855 | D26: =IFERROR(C26/C25-1,0) -> -0.0063550787 | F26: ='Data - Hind. Unilever'!F26 -> 24677.801 | G26: =IFERROR(F26/F25-1,0) -> 0.02265546
B27: 45635 | C27: 498.57373 | D27: =IFERROR(C27/C26-1,0) -> -0.021000362 | F27: ='Data - Hind. Unilever'!F27 -> 24768.301 | G27: =IFERROR(F27/F26-1,0) -> 0.0036672636
B28: 45642 | C28: 488.60809 | D28: =IFERROR(C28/C27-1,0) -> -0.019988292 | F28: ='Data - Hind. Unilever'!F28 -> 23587.5 | G28: =IFERROR(F28/F27-1,0) -> -0.047673871
B29: 45649 | C29: 493.08051 | D29: =IFERROR(C29/C28-1,0) -> 0.009153373 | F29: ='Data - Hind. Unilever'!F29 -> 23813.4 | G29: =IFERROR(F29/F28-1,0) -> 0.0095771231
B30: 45656 | C30: 510.33804 | D30: =IFERROR(C30/C29-1,0) -> 0.034999432 | F30: ='Data - Hind. Unilever'!F30 -> 24004.75 | G30: =IFERROR(F30/F29-1,0) -> 0.0080353753
B31: 45663 | C31: 503.53229 | D31: =IFERROR(C31/C30-1,0) -> -0.01333578 | F31: ='Data - Hind. Unilever'!F31 -> 23431.5 | G31: =IFERROR(F31/F30-1,0) -> -0.02388069
B32: 45670 | C32: 511.45612 | D32: =IFERROR(C32/C31-1,0) -> 0.015736485 | F32: ='Data - Hind. Unilever'!F32 -> 23203.199 | G32: =IFERROR(F32/F31-1,0) -> -0.0097433276
B33: 45677 | C33: 507.17825 | D33: =IFERROR(C33/C32-1,0) -> -0.0083640852 | F33: ='Data - Hind. Unilever'!F33 -> 23092.199 | G33: =IFERROR(F33/F32-1,0) -> -0.0047838231
B34: 45684 | C34: 524.1441 | D34: =IFERROR(C34/C33-1,0) -> 0.033451456 | F34: ='Data - Hind. Unilever'!F34 -> 23482.15 | G34: =IFERROR(F34/F33-1,0) -> 0.016886706
... B111: 46223 | C111: 423.20001 | D111: =IFERROR(C111/C110-1,0) -> -0.0093632956 | F111: ='Data - Hind. Unilever'!F111 -> 23869.6 | G111: =IFERROR(F111/F110-1,0) -> -0.019096549

Sheet Beta Comps
B4: S.No. | C4: Name | D4: CMP Rs. | E4: Mar Cap Rs.Cr. | F4: Debt Rs.Cr. | G4: Debt / Eq
B5: 1 | C5: Hind. Unilever | D5: 2177 | E5: 511505.98 | F5: 1478 | G5: 0.03
B6: 2 | C6: Nestle India | D6: 1436 | E6: 276905.89 | F6: 444.16 | G6: 0.08
B7: 3 | C7: Britannia Inds. | D7: 5359.9 | E7: 129103.03 | F7: 1380.28 | G7: 0.27
B8: 4 | C8: Godrej Consumer | D8: 1071 | E8: 109595.96 | F8: 4420.52 | G8: 0.35
B9: 5 | C9: Dabur India | D9: 426.75 | E9: 75703.42 | F9: 1287.32 | G9: 0.11

Sheet DCF>
B2: Year | C2: Annual
B3: 2000 | C3: -0.1465
B4: 2001 | C4: -0.1618 | E4: Average Return | F4: =AVERAGE(C3:C28) -> 0.15149231
B5: 2002 | C5: 0.0325 | E5: Dividend Yield | F5: 0.013
B6: 2003 | C6: 0.719 | E6: Total Market Return | F6: =SUM(F4,F5) -> 0.16449231
B7: 2004 | C7: 0.1068
B8: 2005 | C8: 0.3634
B9: 2006 | C9: 0.3983
B10: 2007 | C10: 0.5477
B11: 2008 | C11: -0.5179
B12: 2009 | C12: 0.7576
B13: 2010 | C13: 0.1795
B14: 2011 | C14: -0.2462
B15: 2012 | C15: 0.277
B16: 2013 | C16: 0.0676
B17: 2014 | C17: 0.3139
B18: 2015 | C18: -0.0406
... B28: 2025 | C28: 0.1051
