Workbook
Name UPDATE: 'Data Sheet'!$E$1

Sheet Financials>

Sheet HistoricalFS
B2: ="Historical Statement - " & 'Data Sheet'!B1
B3: Years | C3: =IFERROR('Data Sheet'!B16,0) | D3: =IFERROR('Data Sheet'!C16,0) | E3: =IFERROR('Data Sheet'!D16,0) | F3: =IFERROR('Data Sheet'!E16,0) | G3: =IFERROR('Data Sheet'!F16,0) | H3: =IFERROR('Data Sheet'!G16,0) | I3: =IFERROR('Data Sheet'!H16,0) | J3: =IFERROR('Data Sheet'!I16,0) | ... L3: =IFERROR('Data Sheet'!K16,0) | M3: LTM
A5: # | B5: Income Statement
B6: Sales | C6: =IFERROR('Data Sheet'!B17,0) | D6: =IFERROR('Data Sheet'!C17,0) | E6: =IFERROR('Data Sheet'!D17,0) | F6: =IFERROR('Data Sheet'!E17,0) | G6: =IFERROR('Data Sheet'!F17,0) | H6: =IFERROR('Data Sheet'!G17,0) | I6: =IFERROR('Data Sheet'!H17,0) | J6: =IFERROR('Data Sheet'!I17,0) | ... L6: =IFERROR('Data Sheet'!K17,0) | M6: =IFERROR(SUM('Data Sheet'!H42:K42),0)
B7: Sales Growth | C7: - | D7: =D6/C6-1 | E7: =E6/D6-1 | F7: =F6/E6-1 | G7: =G6/F6-1 | H7: =H6/G6-1 | I7: =I6/H6-1 | J7: =J6/I6-1 | K7: =K6/J6-1 | L7: =L6/K6-1 | M7: -
B9: COS | C9: =IFERROR(SUM('Data Sheet'!B20:B22)-1*'Data Sheet'!B19,0) | D9: =IFERROR(SUM('Data Sheet'!C20:C22)-1*'Data Sheet'!C19,0) | E9: =IFERROR(SUM('Data Sheet'!D20:D22)-1*'Data Sheet'!D19,0) | F9: =IFERROR(SUM('Data Sheet'!E20:E22)-1*'Data Sheet'!E19,0) | G9: =IFERROR(SUM('Data Sheet'!F20:F22)-1*'Data Sheet'!F19,0) | H9: =IFERROR(SUM('Data Sheet'!G20:G22)-1*'Data Sheet'!G19,0) | I9: =IFERROR(SUM('Data Sheet'!H20:H22)-1*'Data Sheet'!H19,0) | J9: =IFERROR(SUM('Data Sheet'!I20:I22)-1*'Data Sheet'!I19,0) | ... L9: =IFERROR(SUM('Data Sheet'!K20:K22)-1*'Data Sheet'!K19,0) | M9: =IFERROR(SUM('Data Sheet'!H43:K43),0)
B10: COS % Sales | C10: =C9/C6 | D10: =D9/D6 | E10: =E9/E6 | F10: =F9/F6 | G10: =G9/G6 | H10: =H9/H6 | I10: =I9/I6 | J10: =J9/J6 | ... M10: =M9/M6
B12: Gross Profit | C12: =C6-C9 | D12: =D6-D9 | E12: =E6-E9 | F12: =F6-F9 | G12: =G6-G9 | H12: =H6-H9 | I12: =I6-I9 | J12: =J6-J9 | ... M12: =M6-M9
B13: Gross Margins | C13: =C12/C6 | D13: =D12/D6 | E13: =E12/E6 | F13: =F12/F6 | G13: =G12/G6 | H13: =H12/H6 | I13: =I12/I6 | J13: =J12/J6 | ... M13: =M12/M6
B15: Selling & General Expenses | C15: =IFERROR(SUM('Data Sheet'!B23:B24),0) | D15: =IFERROR(SUM('Data Sheet'!C23:C24),0) | E15: =IFERROR(SUM('Data Sheet'!D23:D24),0) | F15: =IFERROR(SUM('Data Sheet'!E23:E24),0) | G15: =IFERROR(SUM('Data Sheet'!F23:F24),0) | H15: =IFERROR(SUM('Data Sheet'!G23:G24),0) | I15: =IFERROR(SUM('Data Sheet'!H23:H24),0) | J15: =IFERROR(SUM('Data Sheet'!I23:I24),0) | ... L15: =IFERROR(SUM('Data Sheet'!K23:K24),0)
B16: SG&A % Sales | C16: =C15/C6 | D16: =D15/D6 | E16: =E15/E6 | F16: =F15/F6 | G16: =G15/G6 | H16: =H15/H6 | I16: =I15/I6 | J16: =J15/J6 | ... M16: =M15/M6
B18: EBITDA | C18: =C12-C15 | D18: =D12-D15 | E18: =E12-E15 | F18: =F12-F15 | G18: =G12-G15 | H18: =H12-H15 | I18: =I12-I15 | J18: =J12-J15 | ... M18: =M12-M15
B19: EBITDA % Sales | C19: =C18/C6 | D19: =D18/D6 | E19: =E18/E6 | F19: =F18/F6 | G19: =G18/G6 | H19: =H18/H6 | I19: =I18/I6 | J19: =J18/J6 | ... M19: =M18/M6
B21: Interest | C21: =IFERROR(('Data Sheet'!B27),0) | D21: =IFERROR(('Data Sheet'!C27),0) | E21: =IFERROR(('Data Sheet'!D27),0) | F21: =IFERROR(('Data Sheet'!E27),0) | G21: =IFERROR(('Data Sheet'!F27),0) | H21: =IFERROR(('Data Sheet'!G27),0) | I21: =IFERROR(('Data Sheet'!H27),0) | J21: =IFERROR(('Data Sheet'!I27),0) | ... L21: =IFERROR(('Data Sheet'!K27),0) | M21: =IFERROR(SUM('Data Sheet'!H46:K46),0)
B22: Interest % Sales | C22: =C21/C6 | D22: =D21/D6 | E22: =E21/E6 | F22: =F21/F6 | G22: =G21/G6 | H22: =H21/H6 | I22: =I21/I6 | J22: =J21/J6 | ... M22: =M21/M6
B24: Depreciation | C24: =IFERROR(('Data Sheet'!B26),0) | D24: =IFERROR(('Data Sheet'!C26),0) | E24: =IFERROR(('Data Sheet'!D26),0) | F24: =IFERROR(('Data Sheet'!E26),0) | G24: =IFERROR(('Data Sheet'!F26),0) | H24: =IFERROR(('Data Sheet'!G26),0) | I24: =IFERROR(('Data Sheet'!H26),0) | J24: =IFERROR(('Data Sheet'!I26),0) | ... L24: =IFERROR(('Data Sheet'!K26),0) | M24: =IFERROR(SUM('Data Sheet'!H45:K45),0)
B25: Depreciation % Sales | C25: =C24/C6 | D25: =D24/D6 | E25: =E24/E6 | F25: =F24/F6 | G25: =G24/G6 | H25: =H24/H6 | I25: =I24/I6 | J25: =J24/J6 | ... M25: =M24/M6
B27: Earnings Before Tax | C27: =IFERROR(C18-SUM(C21,C24),0) | D27: =IFERROR(D18-SUM(D21,D24),0) | E27: =IFERROR(E18-SUM(E21,E24),0) | F27: =IFERROR(F18-SUM(F21,F24),0) | G27: =IFERROR(G18-SUM(G21,G24),0) | H27: =IFERROR(H18-SUM(H21,H24),0) | I27: =IFERROR(I18-SUM(I21,I24),0) | J27: =IFERROR(J18-SUM(J21,J24),0) | ... M27: =IFERROR(M18-SUM(M21,M24),0)
B28: EBT % Sales | C28: =C27/C6 | D28: =D27/D6 | E28: =E27/E6 | F28: =F27/F6 | G28: =G27/G6 | H28: =H27/H6 | I28: =I27/I6 | J28: =J27/J6 | ... M28: =M27/M6
B30: Tax | C30: =IFERROR('Data Sheet'!B29,0) | D30: =IFERROR('Data Sheet'!C29,0) | E30: =IFERROR('Data Sheet'!D29,0) | F30: =IFERROR('Data Sheet'!E29,0) | G30: =IFERROR('Data Sheet'!F29,0) | H30: =IFERROR('Data Sheet'!G29,0) | I30: =IFERROR('Data Sheet'!H29,0) | J30: =IFERROR('Data Sheet'!I29,0) | ... L30: =IFERROR('Data Sheet'!K29,0) | M30: =IFERROR(SUM('Data Sheet'!H48:K48),0)
B31: Effective Tax rate | C31: =C30/C27 | D31: =D30/D27 | E31: =E30/E27 | F31: =F30/F27 | G31: =G30/G27 | H31: =H30/H27 | I31: =I30/I27 | J31: =J30/J27 | ... M31: =M30/M27
B33: Net Profit | C33: =IFERROR((C27-C30),0) | D33: =IFERROR((D27-D30),0) | E33: =IFERROR((E27-E30),0) | F33: =IFERROR((F27-F30),0) | G33: =IFERROR((G27-G30),0) | H33: =IFERROR((H27-H30),0) | I33: =IFERROR((I27-I30),0) | J33: =IFERROR((J27-J30),0) | ... M33: =IFERROR((M27-M30),0)
B34: Net Margin | C34: =C33/C6 | D34: =D33/D6 | E34: =E33/E6 | F34: =F33/F6 | G34: =G33/G6 | H34: =H33/H6 | I34: =I33/I6 | J34: =J33/J6 | ... M34: =M33/M6
B36: No. of Equity Shares O/S | C36: =IFERROR('Data Sheet'!B93,0) | D36: =IFERROR('Data Sheet'!C93,0) | E36: =IFERROR('Data Sheet'!D93,0) | F36: =IFERROR('Data Sheet'!E93,0) | G36: =IFERROR('Data Sheet'!F93,0) | H36: =IFERROR('Data Sheet'!G93,0) | I36: =IFERROR('Data Sheet'!H93,0) | J36: =IFERROR('Data Sheet'!I93,0) | ... L36: =IFERROR('Data Sheet'!K93,0) | M36: =L36
B38: Earnings Per Share | C38: =IFERROR(C33/C36,0) | D38: =IFERROR(D33/D36,0) | E38: =IFERROR(E33/E36,0) | F38: =IFERROR(F33/F36,0) | G38: =IFERROR(G33/G36,0) | H38: =IFERROR(H33/H36,0) | I38: =IFERROR(I33/I36,0) | J38: =IFERROR(J33/J36,0) | ... M38: =IFERROR(M33/M36,0)
B39: EPS growth % | D39: =IFERROR((D38/C38-1),0) | E39: =IFERROR((E38/D38-1),0) | F39: =IFERROR((F38/E38-1),0) | G39: =IFERROR((G38/F38-1),0) | H39: =IFERROR((H38/G38-1),0) | I39: =IFERROR((I38/H38-1),0) | J39: =IFERROR((J38/I38-1),0) | K39: =IFERROR((K38/J38-1),0) | ... M39: =IFERROR((M38/L38-1),0)
B41: Dividends Per Share | C41: =IFERROR(('Data Sheet'!B31/C36),0) | D41: =IFERROR(('Data Sheet'!C31/D36),0) | E41: =IFERROR(('Data Sheet'!D31/E36),0) | F41: =IFERROR(('Data Sheet'!E31/F36),0) | G41: =IFERROR(('Data Sheet'!F31/G36),0) | H41: =IFERROR(('Data Sheet'!G31/H36),0) | I41: =IFERROR(('Data Sheet'!H31/I36),0) | J41: =IFERROR(('Data Sheet'!I31/J36),0) | ... M41: =IFERROR(('Data Sheet'!L31/M36),0)
B42: Dividend Payout Ratio | C42: =IFERROR((C41/C38),0) | D42: =IFERROR((D41/D38),0) | E42: =IFERROR((E41/E38),0) | F42: =IFERROR((F41/F38),0) | G42: =IFERROR((G41/G38),0) | H42: =IFERROR((H41/H38),0) | I42: =IFERROR((I41/I38),0) | J42: =IFERROR((J41/J38),0) | ... M42: =IFERROR((M41/M38),0)
B44: Retained Earnings | C44: =IFERROR(IF(C38>C41,1-C42,0),0) | D44: =IFERROR(IF(D38>D41,1-D42,0),0) | E44: =IFERROR(IF(E38>E41,1-E42,0),0) | F44: =IFERROR(IF(F38>F41,1-F42,0),0) | G44: =IFERROR(IF(G38>G41,1-G42,0),0) | H44: =IFERROR(IF(H38>H41,1-H42,0),0) | I44: =IFERROR(IF(I38>I41,1-I42,0),0) | J44: =IFERROR(IF(J38>J41,1-J42,0),0) | ... M44: =IFERROR(IF(M38>M41,1-M42,0),0)
A46: # | B46: Balance Sheet
B47: Equity Share Capital | C47: =IFERROR('Data Sheet'!B57,0) | D47: =IFERROR('Data Sheet'!C57,0) | E47: =IFERROR('Data Sheet'!D57,0) | F47: =IFERROR('Data Sheet'!E57,0) | G47: =IFERROR('Data Sheet'!F57,0) | H47: =IFERROR('Data Sheet'!G57,0) | I47: =IFERROR('Data Sheet'!H57,0) | J47: =IFERROR('Data Sheet'!I57,0) | ... L47: =IFERROR('Data Sheet'!K57,0)
B48: Reserves | C48: =IFERROR('Data Sheet'!B58,0) | D48: =IFERROR('Data Sheet'!C58,0) | E48: =IFERROR('Data Sheet'!D58,0) | F48: =IFERROR('Data Sheet'!E58,0) | G48: =IFERROR('Data Sheet'!F58,0) | H48: =IFERROR('Data Sheet'!G58,0) | I48: =IFERROR('Data Sheet'!H58,0) | J48: =IFERROR('Data Sheet'!I58,0) | ... L48: =IFERROR('Data Sheet'!K58,0)
B49: Borrowings | C49: =IFERROR('Data Sheet'!B59,0) | D49: =IFERROR('Data Sheet'!C59,0) | E49: =IFERROR('Data Sheet'!D59,0) | F49: =IFERROR('Data Sheet'!E59,0) | G49: =IFERROR('Data Sheet'!F59,0) | H49: =IFERROR('Data Sheet'!G59,0) | I49: =IFERROR('Data Sheet'!H59,0) | J49: =IFERROR('Data Sheet'!I59,0) | ... L49: =IFERROR('Data Sheet'!K59,0)
B50: Other Liabilities | C50: =IFERROR('Data Sheet'!B60,0) | D50: =IFERROR('Data Sheet'!C60,0) | E50: =IFERROR('Data Sheet'!D60,0) | F50: =IFERROR('Data Sheet'!E60,0) | G50: =IFERROR('Data Sheet'!F60,0) | H50: =IFERROR('Data Sheet'!G60,0) | I50: =IFERROR('Data Sheet'!H60,0) | J50: =IFERROR('Data Sheet'!I60,0) | ... L50: =IFERROR('Data Sheet'!K60,0)
B51: Total Liabilities | C51: =IFERROR('Data Sheet'!B61,0) | D51: =IFERROR('Data Sheet'!C61,0) | E51: =IFERROR('Data Sheet'!D61,0) | F51: =IFERROR('Data Sheet'!E61,0) | G51: =IFERROR('Data Sheet'!F61,0) | H51: =IFERROR('Data Sheet'!G61,0) | I51: =IFERROR('Data Sheet'!H61,0) | J51: =IFERROR('Data Sheet'!I61,0) | ... L51: =IFERROR('Data Sheet'!K61,0)
B53: Fixed Assets Net Block | C53: =IFERROR('Data Sheet'!B62,0) | D53: =IFERROR('Data Sheet'!C62,0) | E53: =IFERROR('Data Sheet'!D62,0) | F53: =IFERROR('Data Sheet'!E62,0) | G53: =IFERROR('Data Sheet'!F62,0) | H53: =IFERROR('Data Sheet'!G62,0) | I53: =IFERROR('Data Sheet'!H62,0) | J53: =IFERROR('Data Sheet'!I62,0) | ... L53: =IFERROR('Data Sheet'!K62,0)
B54: Capital Work in Progress | C54: =IFERROR('Data Sheet'!B63,0) | D54: =IFERROR('Data Sheet'!C63,0) | E54: =IFERROR('Data Sheet'!D63,0) | F54: =IFERROR('Data Sheet'!E63,0) | G54: =IFERROR('Data Sheet'!F63,0) | H54: =IFERROR('Data Sheet'!G63,0) | I54: =IFERROR('Data Sheet'!H63,0) | J54: =IFERROR('Data Sheet'!I63,0) | ... L54: =IFERROR('Data Sheet'!K63,0)
B55: Investments | C55: =IFERROR('Data Sheet'!B64,0) | D55: =IFERROR('Data Sheet'!C64,0) | E55: =IFERROR('Data Sheet'!D64,0) | F55: =IFERROR('Data Sheet'!E64,0) | G55: =IFERROR('Data Sheet'!F64,0) | H55: =IFERROR('Data Sheet'!G64,0) | I55: =IFERROR('Data Sheet'!H64,0) | J55: =IFERROR('Data Sheet'!I64,0) | ... L55: =IFERROR('Data Sheet'!K64,0)
B56: Other Assets | C56: =IFERROR('Data Sheet'!B65-SUM('Data Sheet'!B67:B69),0) | D56: =IFERROR('Data Sheet'!C65-SUM('Data Sheet'!C67:C69),0) | E56: =IFERROR('Data Sheet'!D65-SUM('Data Sheet'!D67:D69),0) | F56: =IFERROR('Data Sheet'!E65-SUM('Data Sheet'!E67:E69),0) | G56: =IFERROR('Data Sheet'!F65-SUM('Data Sheet'!F67:F69),0) | H56: =IFERROR('Data Sheet'!G65-SUM('Data Sheet'!G67:G69),0) | I56: =IFERROR('Data Sheet'!H65-SUM('Data Sheet'!H67:H69),0) | J56: =IFERROR('Data Sheet'!I65-SUM('Data Sheet'!I67:I69),0) | ... L56: =IFERROR('Data Sheet'!K65-SUM('Data Sheet'!K67:K69),0)
B57: Total Non Current Asset | C57: =IFERROR(SUM(C53:C56),0) | D57: =IFERROR(SUM(D53:D56),0) | E57: =IFERROR(SUM(E53:E56),0) | F57: =IFERROR(SUM(F53:F56),0) | G57: =IFERROR(SUM(G53:G56),0) | H57: =IFERROR(SUM(H53:H56),0) | I57: =IFERROR(SUM(I53:I56),0) | J57: =IFERROR(SUM(J53:J56),0) | ... L57: =IFERROR(SUM(L53:L56),0)
B59: Receivables | C59: =IFERROR('Data Sheet'!B67,0) | D59: =IFERROR('Data Sheet'!C67,0) | E59: =IFERROR('Data Sheet'!D67,0) | F59: =IFERROR('Data Sheet'!E67,0) | G59: =IFERROR('Data Sheet'!F67,0) | H59: =IFERROR('Data Sheet'!G67,0) | I59: =IFERROR('Data Sheet'!H67,0) | J59: =IFERROR('Data Sheet'!I67,0) | ... L59: =IFERROR('Data Sheet'!K67,0)
B60: Inventory | C60: =IFERROR('Data Sheet'!B68,0) | D60: =IFERROR('Data Sheet'!C68,0) | E60: =IFERROR('Data Sheet'!D68,0) | F60: =IFERROR('Data Sheet'!E68,0) | G60: =IFERROR('Data Sheet'!F68,0) | H60: =IFERROR('Data Sheet'!G68,0) | I60: =IFERROR('Data Sheet'!H68,0) | J60: =IFERROR('Data Sheet'!I68,0) | ... L60: =IFERROR('Data Sheet'!K68,0)
B61: Cash & Bank | C61: =IFERROR('Data Sheet'!B69,0) | D61: =IFERROR('Data Sheet'!C69,0) | E61: =IFERROR('Data Sheet'!D69,0) | F61: =IFERROR('Data Sheet'!E69,0) | G61: =IFERROR('Data Sheet'!F69,0) | H61: =IFERROR('Data Sheet'!G69,0) | I61: =IFERROR('Data Sheet'!H69,0) | J61: =IFERROR('Data Sheet'!I69,0) | ... L61: =IFERROR('Data Sheet'!K69,0)
B62: Total Current Asset | C62: =IFERROR(SUM(C59:C61),0) | D62: =IFERROR(SUM(D59:D61),0) | E62: =IFERROR(SUM(E59:E61),0) | F62: =IFERROR(SUM(F59:F61),0) | G62: =IFERROR(SUM(G59:G61),0) | H62: =IFERROR(SUM(H59:H61),0) | I62: =IFERROR(SUM(I59:I61),0) | J62: =IFERROR(SUM(J59:J61),0) | ... L62: =IFERROR(SUM(L59:L61),0)
B64: Total Asset | C64: =IFERROR((C62+C57),0) | D64: =IFERROR((D62+D57),0) | E64: =IFERROR((E62+E57),0) | F64: =IFERROR((F62+F57),0) | G64: =IFERROR((G62+G57),0) | H64: =IFERROR((H62+H57),0) | I64: =IFERROR((I62+I57),0) | J64: =IFERROR((J62+J57),0) | ... L64: =IFERROR((L62+L57),0)
B66: CHECK | C66: =C64=C51 | D66: =D64=D51 | E66: =E64=E51 | F66: =F64=F51 | G66: =G64=G51 | H66: =H64=H51 | I66: =I64=I51 | J66: =J64=J51 | ... L66: =L64=L51
A68: # | B68: Cash Flow Statement
B69: Operating Activities
B70: Profit from operations | C70: =IFERROR('Cash Flow Data'!E4,0) | D70: =IFERROR('Cash Flow Data'!F4,0) | E70: =IFERROR('Cash Flow Data'!G4,0) | F70: =IFERROR('Cash Flow Data'!H4,0) | G70: =IFERROR('Cash Flow Data'!I4,0) | H70: =IFERROR('Cash Flow Data'!J4,0) | I70: =IFERROR('Cash Flow Data'!K4,0) | J70: =IFERROR('Cash Flow Data'!L4,0) | ... L70: =IFERROR('Cash Flow Data'!N4,0)
B71: Receivables | C71: =IFERROR('Cash Flow Data'!E5,0) | D71: =IFERROR('Cash Flow Data'!F5,0) | E71: =IFERROR('Cash Flow Data'!G5,0) | F71: =IFERROR('Cash Flow Data'!H5,0) | G71: =IFERROR('Cash Flow Data'!I5,0) | H71: =IFERROR('Cash Flow Data'!J5,0) | I71: =IFERROR('Cash Flow Data'!K5,0) | J71: =IFERROR('Cash Flow Data'!L5,0) | ... L71: =IFERROR('Cash Flow Data'!N5,0)
B72: Inventory | C72: =IFERROR('Cash Flow Data'!E6,0) | D72: =IFERROR('Cash Flow Data'!F6,0) | E72: =IFERROR('Cash Flow Data'!G6,0) | F72: =IFERROR('Cash Flow Data'!H6,0) | G72: =IFERROR('Cash Flow Data'!I6,0) | H72: =IFERROR('Cash Flow Data'!J6,0) | I72: =IFERROR('Cash Flow Data'!K6,0) | J72: =IFERROR('Cash Flow Data'!L6,0) | ... L72: =IFERROR('Cash Flow Data'!N6,0)
B73: Payables | C73: =IFERROR('Cash Flow Data'!E7,0) | D73: =IFERROR('Cash Flow Data'!F7,0) | E73: =IFERROR('Cash Flow Data'!G7,0) | F73: =IFERROR('Cash Flow Data'!H7,0) | G73: =IFERROR('Cash Flow Data'!I7,0) | H73: =IFERROR('Cash Flow Data'!J7,0) | I73: =IFERROR('Cash Flow Data'!K7,0) | J73: =IFERROR('Cash Flow Data'!L7,0) | ... L73: =IFERROR('Cash Flow Data'!N7,0)
B74: Loans Advances | C74: =IFERROR('Cash Flow Data'!E8,0) | D74: =IFERROR('Cash Flow Data'!F8,0) | E74: =IFERROR('Cash Flow Data'!G8,0) | F74: =IFERROR('Cash Flow Data'!H8,0) | G74: =IFERROR('Cash Flow Data'!I8,0) | H74: =IFERROR('Cash Flow Data'!J8,0) | I74: =IFERROR('Cash Flow Data'!K8,0) | J74: =IFERROR('Cash Flow Data'!L8,0) | ... L74: =IFERROR('Cash Flow Data'!N8,0)
B75: Other WC items | C75: =IFERROR('Cash Flow Data'!E9,0) | D75: =IFERROR('Cash Flow Data'!F9,0) | E75: =IFERROR('Cash Flow Data'!G9,0) | F75: =IFERROR('Cash Flow Data'!H9,0) | G75: =IFERROR('Cash Flow Data'!I9,0) | H75: =IFERROR('Cash Flow Data'!J9,0) | I75: =IFERROR('Cash Flow Data'!K9,0) | J75: =IFERROR('Cash Flow Data'!L9,0) | ... L75: =IFERROR('Cash Flow Data'!N9,0)
B76: Working capital changes | C76: =IFERROR('Cash Flow Data'!E10,0) | D76: =IFERROR('Cash Flow Data'!F10,0) | E76: =IFERROR('Cash Flow Data'!G10,0) | F76: =IFERROR('Cash Flow Data'!H10,0) | G76: =IFERROR('Cash Flow Data'!I10,0) | H76: =IFERROR('Cash Flow Data'!J10,0) | I76: =IFERROR('Cash Flow Data'!K10,0) | J76: =IFERROR('Cash Flow Data'!L10,0) | ... L76: =IFERROR('Cash Flow Data'!N10,0)
B77: Direct taxes | C77: =IFERROR('Cash Flow Data'!E11,0) | D77: =IFERROR('Cash Flow Data'!F11,0) | E77: =IFERROR('Cash Flow Data'!G11,0) | F77: =IFERROR('Cash Flow Data'!H11,0) | G77: =IFERROR('Cash Flow Data'!I11,0) | H77: =IFERROR('Cash Flow Data'!J11,0) | I77: =IFERROR('Cash Flow Data'!K11,0) | J77: =IFERROR('Cash Flow Data'!L11,0) | ... L77: =IFERROR('Cash Flow Data'!N11,0)
B78: Other operating items | C78: =IFERROR('Cash Flow Data'!E12,0) | D78: =IFERROR('Cash Flow Data'!F12,0) | E78: =IFERROR('Cash Flow Data'!G12,0) | F78: =IFERROR('Cash Flow Data'!H12,0) | G78: =IFERROR('Cash Flow Data'!I12,0) | H78: =IFERROR('Cash Flow Data'!J12,0) | I78: =IFERROR('Cash Flow Data'!K12,0) | J78: =IFERROR('Cash Flow Data'!L12,0) | ... L78: =IFERROR('Cash Flow Data'!N12,0)
B79: Cash from Operating Activities | C79: =IFERROR(SUM(C70,C76,C77,C78),0) | D79: =IFERROR(SUM(D70,D76,D77,D78),0) | E79: =IFERROR(SUM(E70,E76,E77,E78),0) | F79: =IFERROR(SUM(F70,F76,F77,F78),0) | G79: =IFERROR(SUM(G70,G76,G77,G78),0) | H79: =IFERROR(SUM(H70,H76,H77,H78),0) | I79: =IFERROR(SUM(I70,I76,I77,I78),0) | J79: =IFERROR(SUM(J70,J76,J77,J78),0) | ... L79: =IFERROR(SUM(L70,L76,L77,L78),0)
B81: Investing Activities
B82: Fixed assets purchased | C82: =IFERROR('Cash Flow Data'!E14,0) | D82: =IFERROR('Cash Flow Data'!F14,0) | E82: =IFERROR('Cash Flow Data'!G14,0) | F82: =IFERROR('Cash Flow Data'!H14,0) | G82: =IFERROR('Cash Flow Data'!I14,0) | H82: =IFERROR('Cash Flow Data'!J14,0) | I82: =IFERROR('Cash Flow Data'!K14,0) | J82: =IFERROR('Cash Flow Data'!L14,0) | ... L82: =IFERROR('Cash Flow Data'!N14,0)
B83: Fixed assets sold | C83: =IFERROR('Cash Flow Data'!E15,0) | D83: =IFERROR('Cash Flow Data'!F15,0) | E83: =IFERROR('Cash Flow Data'!G15,0) | F83: =IFERROR('Cash Flow Data'!H15,0) | G83: =IFERROR('Cash Flow Data'!I15,0) | H83: =IFERROR('Cash Flow Data'!J15,0) | I83: =IFERROR('Cash Flow Data'!K15,0) | J83: =IFERROR('Cash Flow Data'!L15,0) | ... L83: =IFERROR('Cash Flow Data'!N15,0)
B84: Investments purchased | C84: =IFERROR('Cash Flow Data'!E16,0) | D84: =IFERROR('Cash Flow Data'!F16,0) | E84: =IFERROR('Cash Flow Data'!G16,0) | F84: =IFERROR('Cash Flow Data'!H16,0) | G84: =IFERROR('Cash Flow Data'!I16,0) | H84: =IFERROR('Cash Flow Data'!J16,0) | I84: =IFERROR('Cash Flow Data'!K16,0) | J84: =IFERROR('Cash Flow Data'!L16,0) | ... L84: =IFERROR('Cash Flow Data'!N16,0)
B85: Investments sold | C85: =IFERROR('Cash Flow Data'!E17,0) | D85: =IFERROR('Cash Flow Data'!F17,0) | E85: =IFERROR('Cash Flow Data'!G17,0) | F85: =IFERROR('Cash Flow Data'!H17,0) | G85: =IFERROR('Cash Flow Data'!I17,0) | H85: =IFERROR('Cash Flow Data'!J17,0) | I85: =IFERROR('Cash Flow Data'!K17,0) | J85: =IFERROR('Cash Flow Data'!L17,0) | ... L85: =IFERROR('Cash Flow Data'!N17,0)
B86: Interest received | C86: =IFERROR('Cash Flow Data'!E18,0) | D86: =IFERROR('Cash Flow Data'!F18,0) | E86: =IFERROR('Cash Flow Data'!G18,0) | F86: =IFERROR('Cash Flow Data'!H18,0) | G86: =IFERROR('Cash Flow Data'!I18,0) | H86: =IFERROR('Cash Flow Data'!J18,0) | I86: =IFERROR('Cash Flow Data'!K18,0) | J86: =IFERROR('Cash Flow Data'!L18,0) | ... L86: =IFERROR('Cash Flow Data'!N18,0)
B87: Dividends received | C87: =IFERROR('Cash Flow Data'!E19,0) | D87: =IFERROR('Cash Flow Data'!F19,0) | E87: =IFERROR('Cash Flow Data'!G19,0) | F87: =IFERROR('Cash Flow Data'!H19,0) | G87: =IFERROR('Cash Flow Data'!I19,0) | H87: =IFERROR('Cash Flow Data'!J19,0) | I87: =IFERROR('Cash Flow Data'!K19,0) | J87: =IFERROR('Cash Flow Data'!L19,0) | ... L87: =IFERROR('Cash Flow Data'!N19,0)
B88: Acquisition of companies | C88: =IFERROR('Cash Flow Data'!E20,0) | D88: =IFERROR('Cash Flow Data'!F20,0) | E88: =IFERROR('Cash Flow Data'!G20,0) | F88: =IFERROR('Cash Flow Data'!H20,0) | G88: =IFERROR('Cash Flow Data'!I20,0) | H88: =IFERROR('Cash Flow Data'!J20,0) | I88: =IFERROR('Cash Flow Data'!K20,0) | J88: =IFERROR('Cash Flow Data'!L20,0) | ... L88: =IFERROR('Cash Flow Data'!N20,0)
B89: Other investing items | C89: =IFERROR('Cash Flow Data'!E21,0) | D89: =IFERROR('Cash Flow Data'!F21,0) | E89: =IFERROR('Cash Flow Data'!G21,0) | F89: =IFERROR('Cash Flow Data'!H21,0) | G89: =IFERROR('Cash Flow Data'!I21,0) | H89: =IFERROR('Cash Flow Data'!J21,0) | I89: =IFERROR('Cash Flow Data'!K21,0) | J89: =IFERROR('Cash Flow Data'!L21,0) | ... L89: =IFERROR('Cash Flow Data'!N21,0)
B90: Cash from Investing Activities | C90: =IFERROR(SUM(C82:C89),0) | D90: =IFERROR(SUM(D82:D89),0) | E90: =IFERROR(SUM(E82:E89),0) | F90: =IFERROR(SUM(F82:F89),0) | G90: =IFERROR(SUM(G82:G89),0) | H90: =IFERROR(SUM(H82:H89),0) | I90: =IFERROR(SUM(I82:I89),0) | J90: =IFERROR(SUM(J82:J89),0) | ... L90: =IFERROR(SUM(L82:L89),0)
B92: Financing Activities
B93: Proceeds from shares | C93: =IFERROR('Cash Flow Data'!E23,0) | D93: =IFERROR('Cash Flow Data'!F23,0) | E93: =IFERROR('Cash Flow Data'!G23,0) | F93: =IFERROR('Cash Flow Data'!H23,0) | G93: =IFERROR('Cash Flow Data'!I23,0) | H93: =IFERROR('Cash Flow Data'!J23,0) | I93: =IFERROR('Cash Flow Data'!K23,0) | J93: =IFERROR('Cash Flow Data'!L23,0) | ... L93: =IFERROR('Cash Flow Data'!N23,0)
B94: Proceeds from borrowings | C94: =IFERROR('Cash Flow Data'!E24,0) | D94: =IFERROR('Cash Flow Data'!F24,0) | E94: =IFERROR('Cash Flow Data'!G24,0) | F94: =IFERROR('Cash Flow Data'!H24,0) | G94: =IFERROR('Cash Flow Data'!I24,0) | H94: =IFERROR('Cash Flow Data'!J24,0) | I94: =IFERROR('Cash Flow Data'!K24,0) | J94: =IFERROR('Cash Flow Data'!L24,0) | ... L94: =IFERROR('Cash Flow Data'!N24,0)
B95: Repayment of borrowings | C95: =IFERROR('Cash Flow Data'!E25,0) | D95: =IFERROR('Cash Flow Data'!F25,0) | E95: =IFERROR('Cash Flow Data'!G25,0) | F95: =IFERROR('Cash Flow Data'!H25,0) | G95: =IFERROR('Cash Flow Data'!I25,0) | H95: =IFERROR('Cash Flow Data'!J25,0) | I95: =IFERROR('Cash Flow Data'!K25,0) | J95: =IFERROR('Cash Flow Data'!L25,0) | ... L95: =IFERROR('Cash Flow Data'!N25,0)
B96: Proceeds from deposits | C96: =IFERROR('Cash Flow Data'!E26,0) | D96: =IFERROR('Cash Flow Data'!F26,0) | E96: =IFERROR('Cash Flow Data'!G26,0) | F96: =IFERROR('Cash Flow Data'!H26,0) | G96: =IFERROR('Cash Flow Data'!I26,0) | H96: =IFERROR('Cash Flow Data'!J26,0) | I96: =IFERROR('Cash Flow Data'!K26,0) | J96: =IFERROR('Cash Flow Data'!L26,0) | ... L96: =IFERROR('Cash Flow Data'!N26,0)
B97: Interest paid fin | C97: =IFERROR('Cash Flow Data'!E27,0) | D97: =IFERROR('Cash Flow Data'!F27,0) | E97: =IFERROR('Cash Flow Data'!G27,0) | F97: =IFERROR('Cash Flow Data'!H27,0) | G97: =IFERROR('Cash Flow Data'!I27,0) | H97: =IFERROR('Cash Flow Data'!J27,0) | I97: =IFERROR('Cash Flow Data'!K27,0) | J97: =IFERROR('Cash Flow Data'!L27,0) | ... L97: =IFERROR('Cash Flow Data'!N27,0)
B98: Dividends paid | C98: =IFERROR('Cash Flow Data'!E28,0) | D98: =IFERROR('Cash Flow Data'!F28,0) | E98: =IFERROR('Cash Flow Data'!G28,0) | F98: =IFERROR('Cash Flow Data'!H28,0) | G98: =IFERROR('Cash Flow Data'!I28,0) | H98: =IFERROR('Cash Flow Data'!J28,0) | I98: =IFERROR('Cash Flow Data'!K28,0) | J98: =IFERROR('Cash Flow Data'!L28,0) | ... L98: =IFERROR('Cash Flow Data'!N28,0)
B99: Financial liabilities | C99: =IFERROR('Cash Flow Data'!E29,0) | D99: =IFERROR('Cash Flow Data'!F29,0) | E99: =IFERROR('Cash Flow Data'!G29,0) | F99: =IFERROR('Cash Flow Data'!H29,0) | G99: =IFERROR('Cash Flow Data'!I29,0) | H99: =IFERROR('Cash Flow Data'!J29,0) | I99: =IFERROR('Cash Flow Data'!K29,0) | J99: =IFERROR('Cash Flow Data'!L29,0) | ... L99: =IFERROR('Cash Flow Data'!N29,0)
B100: Application money refund | C100: =IFERROR('Cash Flow Data'!E30,0) | D100: =IFERROR('Cash Flow Data'!F30,0) | E100: =IFERROR('Cash Flow Data'!G30,0) | F100: =IFERROR('Cash Flow Data'!H30,0) | G100: =IFERROR('Cash Flow Data'!I30,0) | H100: =IFERROR('Cash Flow Data'!J30,0) | I100: =IFERROR('Cash Flow Data'!K30,0) | J100: =IFERROR('Cash Flow Data'!L30,0) | ... L100: =IFERROR('Cash Flow Data'!N30,0)
B101: Other financing items | C101: =IFERROR('Cash Flow Data'!E31,0) | D101: =IFERROR('Cash Flow Data'!F31,0) | E101: =IFERROR('Cash Flow Data'!G31,0) | F101: =IFERROR('Cash Flow Data'!H31,0) | G101: =IFERROR('Cash Flow Data'!I31,0) | H101: =IFERROR('Cash Flow Data'!J31,0) | I101: =IFERROR('Cash Flow Data'!K31,0) | J101: =IFERROR('Cash Flow Data'!L31,0) | ... L101: =IFERROR('Cash Flow Data'!N31,0)
B102: Cash from Financing Activities | C102: =IFERROR(SUM(C93:C101),0) | D102: =IFERROR(SUM(D93:D101),0) | E102: =IFERROR(SUM(E93:E101),0) | F102: =IFERROR(SUM(F93:F101),0) | G102: =IFERROR(SUM(G93:G101),0) | H102: =IFERROR(SUM(H93:H101),0) | I102: =IFERROR(SUM(I93:I101),0) | J102: =IFERROR(SUM(J93:J101),0) | ... L102: =IFERROR(SUM(L93:L101),0)
B104: Net Cash Flow | C104: =IFERROR(SUM(C102,C90,C79),0) | D104: =IFERROR(SUM(D102,D90,D79),0) | E104: =IFERROR(SUM(E102,E90,E79),0) | F104: =IFERROR(SUM(F102,F90,F79),0) | G104: =IFERROR(SUM(G102,G90,G79),0) | H104: =IFERROR(SUM(H102,H90,H79),0) | I104: =IFERROR(SUM(I102,I90,I79),0) | J104: =IFERROR(SUM(J102,J90,J79),0) | ... L104: =IFERROR(SUM(L102,L90,L79),0)

Sheet Ratio Analysis
B2: ="Ratio Analysis - " & 'Data Sheet'!B1
B3: Years | C3: =IFERROR('Data Sheet'!B16,0) | D3: =IFERROR('Data Sheet'!C16,0) | E3: =IFERROR('Data Sheet'!D16,0) | F3: =IFERROR('Data Sheet'!E16,0) | G3: =IFERROR('Data Sheet'!F16,0) | H3: =IFERROR('Data Sheet'!G16,0) | I3: =IFERROR('Data Sheet'!H16,0) | J3: =IFERROR('Data Sheet'!I16,0) | ... L3: =IFERROR('Data Sheet'!K16,0) | M3: LTM | N3: Trend | O3: Mean | P3: Median
B5: Sales growth | D5: =IFERROR(HistoricalFS!D7,0) | E5: =IFERROR(HistoricalFS!E7,0) | F5: =IFERROR(HistoricalFS!F7,0) | G5: =IFERROR(HistoricalFS!G7,0) | H5: =IFERROR(HistoricalFS!H7,0) | I5: =IFERROR(HistoricalFS!I7,0) | J5: =IFERROR(HistoricalFS!J7,0) | K5: =IFERROR(HistoricalFS!K7,0) | L5: =IFERROR(HistoricalFS!L7,0) | O5: =IFERROR(AVERAGE(D5:L5),0) | P5: =IFERROR(MEDIAN(C5:L5),0)
B6: EBITDA growth | D6: =IFERROR(HistoricalFS!D18/HistoricalFS!C18-1,0) | E6: =IFERROR(HistoricalFS!E18/HistoricalFS!D18-1,0) | F6: =IFERROR(HistoricalFS!F18/HistoricalFS!E18-1,0) | G6: =IFERROR(HistoricalFS!G18/HistoricalFS!F18-1,0) | H6: =IFERROR(HistoricalFS!H18/HistoricalFS!G18-1,0) | I6: =IFERROR(HistoricalFS!I18/HistoricalFS!H18-1,0) | J6: =IFERROR(HistoricalFS!J18/HistoricalFS!I18-1,0) | K6: =IFERROR(HistoricalFS!K18/HistoricalFS!J18-1,0) | L6: =IFERROR(HistoricalFS!L18/HistoricalFS!K18-1,0) | O6: =IFERROR(AVERAGE(D6:L6),0) | P6: =IFERROR(MEDIAN(C6:L6),0)
B7: EBIT growth | D7: =IFERROR((HistoricalFS!D18-HistoricalFS!D24)/(HistoricalFS!C18-HistoricalFS!C24)-1,0) | E7: =IFERROR((HistoricalFS!E18-HistoricalFS!E24)/(HistoricalFS!D18-HistoricalFS!D24)-1,0) | F7: =IFERROR((HistoricalFS!F18-HistoricalFS!F24)/(HistoricalFS!E18-HistoricalFS!E24)-1,0) | G7: =IFERROR((HistoricalFS!G18-HistoricalFS!G24)/(HistoricalFS!F18-HistoricalFS!F24)-1,0) | H7: =IFERROR((HistoricalFS!H18-HistoricalFS!H24)/(HistoricalFS!G18-HistoricalFS!G24)-1,0) | I7: =IFERROR((HistoricalFS!I18-HistoricalFS!I24)/(HistoricalFS!H18-HistoricalFS!H24)-1,0) | J7: =IFERROR((HistoricalFS!J18-HistoricalFS!J24)/(HistoricalFS!I18-HistoricalFS!I24)-1,0) | K7: =IFERROR((HistoricalFS!K18-HistoricalFS!K24)/(HistoricalFS!J18-HistoricalFS!J24)-1,0) | L7: =IFERROR((HistoricalFS!L18-HistoricalFS!L24)/(HistoricalFS!K18-HistoricalFS!K24)-1,0) | O7: =IFERROR(AVERAGE(D7:L7),0) | P7: =IFERROR(MEDIAN(C7:L7),0)
B8: Net profit growth | D8: =IFERROR(HistoricalFS!D33/HistoricalFS!C33-1,0) | E8: =IFERROR(HistoricalFS!E33/HistoricalFS!D33-1,0) | F8: =IFERROR(HistoricalFS!F33/HistoricalFS!E33-1,0) | G8: =IFERROR(HistoricalFS!G33/HistoricalFS!F33-1,0) | H8: =IFERROR(HistoricalFS!H33/HistoricalFS!G33-1,0) | I8: =IFERROR(HistoricalFS!I33/HistoricalFS!H33-1,0) | J8: =IFERROR(HistoricalFS!J33/HistoricalFS!I33-1,0) | K8: =IFERROR(HistoricalFS!K33/HistoricalFS!J33-1,0) | L8: =IFERROR(HistoricalFS!L33/HistoricalFS!K33-1,0) | O8: =IFERROR(AVERAGE(D8:L8),0) | P8: =IFERROR(MEDIAN(C8:L8),0)
B9: Dividend growth | D9: =IFERROR(HistoricalFS!D41/HistoricalFS!C41-1,0) | E9: =IFERROR(HistoricalFS!E41/HistoricalFS!D41-1,0) | F9: =IFERROR(HistoricalFS!F41/HistoricalFS!E41-1,0) | G9: =IFERROR(HistoricalFS!G41/HistoricalFS!F41-1,0) | H9: =IFERROR(HistoricalFS!H41/HistoricalFS!G41-1,0) | I9: =IFERROR(HistoricalFS!I41/HistoricalFS!H41-1,0) | J9: =IFERROR(HistoricalFS!J41/HistoricalFS!I41-1,0) | K9: =IFERROR(HistoricalFS!K41/HistoricalFS!J41-1,0) | L9: =IFERROR(HistoricalFS!L41/HistoricalFS!K41-1,0) | O9: =IFERROR(AVERAGE(D9:L9),0) | P9: =IFERROR(MEDIAN(C9:L9),0)
B11: Gross margin | C11: =IFERROR(HistoricalFS!C13,0) | D11: =IFERROR(HistoricalFS!D13,0) | E11: =IFERROR(HistoricalFS!E13,0) | F11: =IFERROR(HistoricalFS!F13,0) | G11: =IFERROR(HistoricalFS!G13,0) | H11: =IFERROR(HistoricalFS!H13,0) | I11: =IFERROR(HistoricalFS!I13,0) | J11: =IFERROR(HistoricalFS!J13,0) | ... L11: =IFERROR(HistoricalFS!L13,0) | O11: =IFERROR(AVERAGE(C11:L11),0) | P11: =IFERROR(MEDIAN(C11:L11),0)
B12: EBITDA margin | C12: =IFERROR(HistoricalFS!C19,0) | D12: =IFERROR(HistoricalFS!D19,0) | E12: =IFERROR(HistoricalFS!E19,0) | F12: =IFERROR(HistoricalFS!F19,0) | G12: =IFERROR(HistoricalFS!G19,0) | H12: =IFERROR(HistoricalFS!H19,0) | I12: =IFERROR(HistoricalFS!I19,0) | J12: =IFERROR(HistoricalFS!J19,0) | ... L12: =IFERROR(HistoricalFS!L19,0) | O12: =IFERROR(AVERAGE(C12:L12),0) | P12: =IFERROR(MEDIAN(C12:L12),0)
B13: EBIT margin | C13: =IFERROR((HistoricalFS!C18-HistoricalFS!C24)/HistoricalFS!C6,0) | D13: =IFERROR((HistoricalFS!D18-HistoricalFS!D24)/HistoricalFS!D6,0) | E13: =IFERROR((HistoricalFS!E18-HistoricalFS!E24)/HistoricalFS!E6,0) | F13: =IFERROR((HistoricalFS!F18-HistoricalFS!F24)/HistoricalFS!F6,0) | G13: =IFERROR((HistoricalFS!G18-HistoricalFS!G24)/HistoricalFS!G6,0) | H13: =IFERROR((HistoricalFS!H18-HistoricalFS!H24)/HistoricalFS!H6,0) | I13: =IFERROR((HistoricalFS!I18-HistoricalFS!I24)/HistoricalFS!I6,0) | J13: =IFERROR((HistoricalFS!J18-HistoricalFS!J24)/HistoricalFS!J6,0) | ... L13: =IFERROR((HistoricalFS!L18-HistoricalFS!L24)/HistoricalFS!L6,0) | O13: =IFERROR(AVERAGE(C13:L13),0) | P13: =IFERROR(MEDIAN(C13:L13),0)
B14: EBT margin | C14: =IFERROR(HistoricalFS!C28,0) | D14: =IFERROR(HistoricalFS!D28,0) | E14: =IFERROR(HistoricalFS!E28,0) | F14: =IFERROR(HistoricalFS!F28,0) | G14: =IFERROR(HistoricalFS!G28,0) | H14: =IFERROR(HistoricalFS!H28,0) | I14: =IFERROR(HistoricalFS!I28,0) | J14: =IFERROR(HistoricalFS!J28,0) | ... L14: =IFERROR(HistoricalFS!L28,0) | O14: =IFERROR(AVERAGE(C14:L14),0) | P14: =IFERROR(MEDIAN(C14:L14),0)
B15: Net Profit margin | C15: =IFERROR(HistoricalFS!C34,0) | D15: =IFERROR(HistoricalFS!D34,0) | E15: =IFERROR(HistoricalFS!E34,0) | F15: =IFERROR(HistoricalFS!F34,0) | G15: =IFERROR(HistoricalFS!G34,0) | H15: =IFERROR(HistoricalFS!H34,0) | I15: =IFERROR(HistoricalFS!I34,0) | J15: =IFERROR(HistoricalFS!J34,0) | ... L15: =IFERROR(HistoricalFS!L34,0) | O15: =IFERROR(AVERAGE(C15:L15),0) | P15: =IFERROR(MEDIAN(C15:L15),0)
B17: SalesExpenses%sales | C17: =IFERROR(HistoricalFS!C16,0) | D17: =IFERROR(HistoricalFS!D16,0) | E17: =IFERROR(HistoricalFS!E16,0) | F17: =IFERROR(HistoricalFS!F16,0) | G17: =IFERROR(HistoricalFS!G16,0) | H17: =IFERROR(HistoricalFS!H16,0) | I17: =IFERROR(HistoricalFS!I16,0) | J17: =IFERROR(HistoricalFS!J16,0) | ... L17: =IFERROR(HistoricalFS!L16,0) | O17: =IFERROR(AVERAGE(C17:L17),0) | P17: =IFERROR(MEDIAN(C17:L17),0)
B18: Depreciation%sales | C18: =IFERROR(HistoricalFS!C25,0) | D18: =IFERROR(HistoricalFS!D25,0) | E18: =IFERROR(HistoricalFS!E25,0) | F18: =IFERROR(HistoricalFS!F25,0) | G18: =IFERROR(HistoricalFS!G25,0) | H18: =IFERROR(HistoricalFS!H25,0) | I18: =IFERROR(HistoricalFS!I25,0) | J18: =IFERROR(HistoricalFS!J25,0) | ... L18: =IFERROR(HistoricalFS!L25,0) | O18: =IFERROR(AVERAGE(C18:L18),0) | P18: =IFERROR(MEDIAN(C18:L18),0)
B19: OperatingIncome%sales | C19: =C13 | D19: =D13 | E19: =E13 | F19: =F13 | G19: =G13 | H19: =H13 | I19: =I13 | J19: =J13 | ... L19: =L13 | O19: =IFERROR(AVERAGE(C19:L19),0) | P19: =IFERROR(MEDIAN(C19:L19),0)
B21: Return on Capital Employed | C21: =IFERROR((HistoricalFS!C18-HistoricalFS!C24)/(SUM(HistoricalFS!C47:C49)),0) | D21: =IFERROR((HistoricalFS!D18-HistoricalFS!D24)/(SUM(HistoricalFS!D47:D49)),0) | E21: =IFERROR((HistoricalFS!E18-HistoricalFS!E24)/(SUM(HistoricalFS!E47:E49)),0) | F21: =IFERROR((HistoricalFS!F18-HistoricalFS!F24)/(SUM(HistoricalFS!F47:F49)),0) | G21: =IFERROR((HistoricalFS!G18-HistoricalFS!G24)/(SUM(HistoricalFS!G47:G49)),0) | H21: =IFERROR((HistoricalFS!H18-HistoricalFS!H24)/(SUM(HistoricalFS!H47:H49)),0) | I21: =IFERROR((HistoricalFS!I18-HistoricalFS!I24)/(SUM(HistoricalFS!I47:I49)),0) | J21: =IFERROR((HistoricalFS!J18-HistoricalFS!J24)/(SUM(HistoricalFS!J47:J49)),0) | ... L21: =IFERROR((HistoricalFS!L18-HistoricalFS!L24)/(SUM(HistoricalFS!L47:L49)),0) | O21: =IFERROR(AVERAGE(C21:L21),0) | P21: =IFERROR(MEDIAN(C21:L21),0)
B22: Retained earnings % | C22: =HistoricalFS!C44 | D22: =HistoricalFS!D44 | E22: =HistoricalFS!E44 | F22: =HistoricalFS!F44 | G22: =HistoricalFS!G44 | H22: =HistoricalFS!H44 | I22: =HistoricalFS!I44 | J22: =HistoricalFS!J44 | ... L22: =HistoricalFS!L44 | O22: =IFERROR(AVERAGE(C22:L22),0) | P22: =IFERROR(MEDIAN(C22:L22),0)
B23: Return on equity % | C23: =IFERROR(HistoricalFS!C33/SUM(HistoricalFS!C47:C48),0) | D23: =IFERROR(HistoricalFS!D33/SUM(HistoricalFS!D47:D48),0) | E23: =IFERROR(HistoricalFS!E33/SUM(HistoricalFS!E47:E48),0) | F23: =IFERROR(HistoricalFS!F33/SUM(HistoricalFS!F47:F48),0) | G23: =IFERROR(HistoricalFS!G33/SUM(HistoricalFS!G47:G48),0) | H23: =IFERROR(HistoricalFS!H33/SUM(HistoricalFS!H47:H48),0) | I23: =IFERROR(HistoricalFS!I33/SUM(HistoricalFS!I47:I48),0) | J23: =IFERROR(HistoricalFS!J33/SUM(HistoricalFS!J47:J48),0) | ... L23: =IFERROR(HistoricalFS!L33/SUM(HistoricalFS!L47:L48),0) | O23: =IFERROR(AVERAGE(C23:L23),0) | P23: =IFERROR(MEDIAN(C23:L23),0)
B24: Self sustained growth rate | C24: =IFERROR(C22*C23,0) | D24: =IFERROR(D22*D23,0) | E24: =IFERROR(E22*E23,0) | F24: =IFERROR(F22*F23,0) | G24: =IFERROR(G22*G23,0) | H24: =IFERROR(H22*H23,0) | I24: =IFERROR(I22*I23,0) | J24: =IFERROR(J22*J23,0) | ... L24: =IFERROR(L22*L23,0) | O24: =IFERROR(AVERAGE(C24:L24),0) | P24: =IFERROR(MEDIAN(C24:L24),0)
B25: Interest Coverage ratio | C25: =IFERROR((HistoricalFS!C18-HistoricalFS!C24)/HistoricalFS!C21,0) | D25: =IFERROR((HistoricalFS!D18-HistoricalFS!D24)/HistoricalFS!D21,0) | E25: =IFERROR((HistoricalFS!E18-HistoricalFS!E24)/HistoricalFS!E21,0) | F25: =IFERROR((HistoricalFS!F18-HistoricalFS!F24)/HistoricalFS!F21,0) | G25: =IFERROR((HistoricalFS!G18-HistoricalFS!G24)/HistoricalFS!G21,0) | H25: =IFERROR((HistoricalFS!H18-HistoricalFS!H24)/HistoricalFS!H21,0) | I25: =IFERROR((HistoricalFS!I18-HistoricalFS!I24)/HistoricalFS!I21,0) | J25: =IFERROR((HistoricalFS!J18-HistoricalFS!J24)/HistoricalFS!J21,0) | ... L25: =IFERROR((HistoricalFS!L18-HistoricalFS!L24)/HistoricalFS!L21,0) | O25: =IFERROR(AVERAGE(C25:L25),0) | P25: =IFERROR(MEDIAN(C25:L25),0)
B27: Debtor Turnover ratio | C27: =IFERROR(HistoricalFS!C6/HistoricalFS!C59,0) | D27: =IFERROR(HistoricalFS!D6/HistoricalFS!D59,0) | E27: =IFERROR(HistoricalFS!E6/HistoricalFS!E59,0) | F27: =IFERROR(HistoricalFS!F6/HistoricalFS!F59,0) | G27: =IFERROR(HistoricalFS!G6/HistoricalFS!G59,0) | H27: =IFERROR(HistoricalFS!H6/HistoricalFS!H59,0) | I27: =IFERROR(HistoricalFS!I6/HistoricalFS!I59,0) | J27: =IFERROR(HistoricalFS!J6/HistoricalFS!J59,0) | ... L27: =IFERROR(HistoricalFS!L6/HistoricalFS!L59,0) | O27: =IFERROR(AVERAGE(C27:L27),0) | P27: =IFERROR(MEDIAN(C27:L27),0)
B28: Creditor Turnover ratio | C28: =IFERROR(HistoricalFS!C9/HistoricalFS!C50,0) | D28: =IFERROR(HistoricalFS!D9/HistoricalFS!D50,0) | E28: =IFERROR(HistoricalFS!E9/HistoricalFS!E50,0) | F28: =IFERROR(HistoricalFS!F9/HistoricalFS!F50,0) | G28: =IFERROR(HistoricalFS!G9/HistoricalFS!G50,0) | H28: =IFERROR(HistoricalFS!H9/HistoricalFS!H50,0) | I28: =IFERROR(HistoricalFS!I9/HistoricalFS!I50,0) | J28: =IFERROR(HistoricalFS!J9/HistoricalFS!J50,0) | ... L28: =IFERROR(HistoricalFS!L9/HistoricalFS!L50,0) | O28: =IFERROR(AVERAGE(C28:L28),0) | P28: =IFERROR(MEDIAN(C28:L28),0)
B29: Inventory Turnover ratio | C29: =IFERROR(HistoricalFS!C9/HistoricalFS!C60,0) | D29: =IFERROR(HistoricalFS!D9/HistoricalFS!D60,0) | E29: =IFERROR(HistoricalFS!E9/HistoricalFS!E60,0) | F29: =IFERROR(HistoricalFS!F9/HistoricalFS!F60,0) | G29: =IFERROR(HistoricalFS!G9/HistoricalFS!G60,0) | H29: =IFERROR(HistoricalFS!H9/HistoricalFS!H60,0) | I29: =IFERROR(HistoricalFS!I9/HistoricalFS!I60,0) | J29: =IFERROR(HistoricalFS!J9/HistoricalFS!J60,0) | ... L29: =IFERROR(HistoricalFS!L9/HistoricalFS!L60,0) | O29: =IFERROR(AVERAGE(C29:L29),0) | P29: =IFERROR(MEDIAN(C29:L29),0)
B30: Fixed Asset Turnover ratio | C30: =IFERROR(HistoricalFS!C6/HistoricalFS!C53,0) | D30: =IFERROR(HistoricalFS!D6/AVERAGE(HistoricalFS!C53:D53),0) | E30: =IFERROR(HistoricalFS!E6/AVERAGE(HistoricalFS!D53:E53),0) | F30: =IFERROR(HistoricalFS!F6/AVERAGE(HistoricalFS!E53:F53),0) | G30: =IFERROR(HistoricalFS!G6/AVERAGE(HistoricalFS!F53:G53),0) | H30: =IFERROR(HistoricalFS!H6/AVERAGE(HistoricalFS!G53:H53),0) | I30: =IFERROR(HistoricalFS!I6/AVERAGE(HistoricalFS!H53:I53),0) | J30: =IFERROR(HistoricalFS!J6/AVERAGE(HistoricalFS!I53:J53),0) | K30: =IFERROR(HistoricalFS!K6/AVERAGE(HistoricalFS!J53:K53),0) | L30: =IFERROR(HistoricalFS!L6/AVERAGE(HistoricalFS!K53:L53),0) | O30: =IFERROR(AVERAGE(C30:L30),0) | P30: =IFERROR(MEDIAN(C30:L30),0)
B31: Capital Turnover ratio | C31: =IFERROR(HistoricalFS!C6/SUM(HistoricalFS!C47:C48),0) | D31: =IFERROR(HistoricalFS!D6/SUM(HistoricalFS!D47:D48),0) | E31: =IFERROR(HistoricalFS!E6/SUM(HistoricalFS!E47:E48),0) | F31: =IFERROR(HistoricalFS!F6/SUM(HistoricalFS!F47:F48),0) | G31: =IFERROR(HistoricalFS!G6/SUM(HistoricalFS!G47:G48),0) | H31: =IFERROR(HistoricalFS!H6/SUM(HistoricalFS!H47:H48),0) | I31: =IFERROR(HistoricalFS!I6/SUM(HistoricalFS!I47:I48),0) | J31: =IFERROR(HistoricalFS!J6/SUM(HistoricalFS!J47:J48),0) | ... L31: =IFERROR(HistoricalFS!L6/SUM(HistoricalFS!L47:L48),0) | O31: =IFERROR(AVERAGE(C31:L31),0) | P31: =IFERROR(MEDIAN(C31:L31),0)
B33: (in days)
B34: Debtors days | C34: =IFERROR(365/C27,0) | D34: =IFERROR(365/D27,0) | E34: =IFERROR(365/E27,0) | F34: =IFERROR(365/F27,0) | G34: =IFERROR(365/G27,0) | H34: =IFERROR(365/H27,0) | I34: =IFERROR(365/I27,0) | J34: =IFERROR(365/J27,0) | ... L34: =IFERROR(365/L27,0) | O34: =IFERROR(AVERAGE(C34:L34),0) | P34: =IFERROR(MEDIAN(C34:L34),0)
B35: Payable days | C35: =IFERROR(365/C28,0) | D35: =IFERROR(365/D28,0) | E35: =IFERROR(365/E28,0) | F35: =IFERROR(365/F28,0) | G35: =IFERROR(365/G28,0) | H35: =IFERROR(365/H28,0) | I35: =IFERROR(365/I28,0) | J35: =IFERROR(365/J28,0) | ... L35: =IFERROR(365/L28,0) | O35: =IFERROR(AVERAGE(C35:L35),0) | P35: =IFERROR(MEDIAN(C35:L35),0)
B36: Inventory days | C36: =IFERROR(365/C29,0) | D36: =IFERROR(365/D29,0) | E36: =IFERROR(365/E29,0) | F36: =IFERROR(365/F29,0) | G36: =IFERROR(365/G29,0) | H36: =IFERROR(365/H29,0) | I36: =IFERROR(365/I29,0) | J36: =IFERROR(365/J29,0) | ... L36: =IFERROR(365/L29,0) | O36: =IFERROR(AVERAGE(C36:L36),0) | P36: =IFERROR(MEDIAN(C36:L36),0)
B37: Cash Conversion Cycle | C37: =IFERROR(SUM(C36,C34)-C35,0) | D37: =IFERROR(SUM(D36,D34)-D35,0) | E37: =IFERROR(SUM(E36,E34)-E35,0) | F37: =IFERROR(SUM(F36,F34)-F35,0) | G37: =IFERROR(SUM(G36,G34)-G35,0) | H37: =IFERROR(SUM(H36,H34)-H35,0) | I37: =IFERROR(SUM(I36,I34)-I35,0) | J37: =IFERROR(SUM(J36,J34)-J35,0) | ... L37: =IFERROR(SUM(L36,L34)-L35,0) | O37: =IFERROR(AVERAGE(C37:L37),0) | P37: =IFERROR(MEDIAN(C37:L37),0)
B39: CFO/Sales | C39: =IFERROR(HistoricalFS!C79/HistoricalFS!C6,0) | D39: =IFERROR(HistoricalFS!D79/HistoricalFS!D6,0) | E39: =IFERROR(HistoricalFS!E79/HistoricalFS!E6,0) | F39: =IFERROR(HistoricalFS!F79/HistoricalFS!F6,0) | G39: =IFERROR(HistoricalFS!G79/HistoricalFS!G6,0) | H39: =IFERROR(HistoricalFS!H79/HistoricalFS!H6,0) | I39: =IFERROR(HistoricalFS!I79/HistoricalFS!I6,0) | J39: =IFERROR(HistoricalFS!J79/HistoricalFS!J6,0) | ... L39: =IFERROR(HistoricalFS!L79/HistoricalFS!L6,0) | O39: =IFERROR(AVERAGE(C39:L39),0) | P39: =IFERROR(MEDIAN(C39:L39),0)
B40: CFO/Total Assets | C40: =IFERROR(HistoricalFS!C79/HistoricalFS!C64,0) | D40: =IFERROR(HistoricalFS!D79/HistoricalFS!D64,0) | E40: =IFERROR(HistoricalFS!E79/HistoricalFS!E64,0) | F40: =IFERROR(HistoricalFS!F79/HistoricalFS!F64,0) | G40: =IFERROR(HistoricalFS!G79/HistoricalFS!G64,0) | H40: =IFERROR(HistoricalFS!H79/HistoricalFS!H64,0) | I40: =IFERROR(HistoricalFS!I79/HistoricalFS!I64,0) | J40: =IFERROR(HistoricalFS!J79/HistoricalFS!J64,0) | ... L40: =IFERROR(HistoricalFS!L79/HistoricalFS!L64,0) | O40: =IFERROR(AVERAGE(C40:L40),0) | P40: =IFERROR(MEDIAN(C40:L40),0)
B41: CFO/Total Debt | C41: =IFERROR(HistoricalFS!C79/HistoricalFS!C49,0) | D41: =IFERROR(HistoricalFS!D79/HistoricalFS!D49,0) | E41: =IFERROR(HistoricalFS!E79/HistoricalFS!E49,0) | F41: =IFERROR(HistoricalFS!F79/HistoricalFS!F49,0) | G41: =IFERROR(HistoricalFS!G79/HistoricalFS!G49,0) | H41: =IFERROR(HistoricalFS!H79/HistoricalFS!H49,0) | I41: =IFERROR(HistoricalFS!I79/HistoricalFS!I49,0) | J41: =IFERROR(HistoricalFS!J79/HistoricalFS!J49,0) | ... L41: =IFERROR(HistoricalFS!L79/HistoricalFS!L49,0) | O41: =IFERROR(AVERAGE(C41:L41),0) | P41: =IFERROR(MEDIAN(C41:L41),0)

Sheet Forecasting 
B3: ='Data Sheet'!B1& " - "& 'Data Sheet'!A17&" Forecasting " | G3: ='Data Sheet'!B1&" - "& HistoricalFS!B18&" Forecasting " | L3: ='Data Sheet'!B1& " - "&HistoricalFS!B38& " Forecasting "
B4: Year Weight | C4: Year | D4: Sales | E4: Sales Growth | G4: Year Weight | H4: Year | I4: EBITDA | J4: EBITDA Growth | L4: Year Weight | M4: Year | N4: EPS | O4: EPS Growth
B5: 1 | C5: ='Data Sheet'!$B$16 | D5: {=TRANSPOSE('Data Sheet'!B17:K17)} | G5: 1 | H5: ='Data Sheet'!B16 | I5: {=TRANSPOSE(HistoricalFS!C18:L18)} | L5: 1 | M5: ='Data Sheet'!B16 | N5: {=IFERROR(TRANSPOSE(HistoricalFS!C38:L38),0)}
B6: =B5+1 | C6: =C5+365 | D6: 1365.06 | E6: =IFERROR(D6/D5-1,0) | G6: =G5+1 | H6: =H5+365 | I6: 367.5 | J6: =IFERROR(I6/I5-1,0) | L6: =L5+1 | M6: =M5+365 | N6: 19.699138 | O6: =IFERROR(N6/N5-1,0)
B7: =B6+1 | C7: =C6+365 | D7: 1430.59 | E7: =IFERROR(D7/D6-1,0) | G7: =G6+1 | H7: =H6+365 | I7: 308.85 | J7: =IFERROR(I7/I6-1,0) | L7: =L6+1 | M7: =M6+365 | N7: 15.479759 | O7: =IFERROR(N7/N6-1,0)
B8: =B7+1 | C8: =C7+365 | D8: 1437.57 | E8: =IFERROR(D8/D7-1,0) | G8: =G7+1 | H8: =H7+365 | I8: 326.15 | J8: =IFERROR(I8/I7-1,0) | L8: =L7+1 | M8: =M7+365 | N8: 14.733333 | O8: =IFERROR(N8/N7-1,0)
B9: =B8+1 | C9: =C8+365 | D9: 1564.49 | E9: =IFERROR(D9/D8-1,0) | G9: =G8+1 | H9: =H8+365 | I9: 449.53 | J9: =IFERROR(I9/I8-1,0) | L9: =L8+1 | M9: =M8+365 | N9: 23.755492 | O9: =IFERROR(N9/N8-1,0)
B10: =B9+1 | C10: =C9+365 | D10: 2160.35 | E10: =IFERROR(D10/D9-1,0) | G10: =G9+1 | H10: =H9+365 | I10: 662.05 | J10: =IFERROR(I10/I9-1,0) | L10: =L9+1 | M10: =M9+365 | N10: 38.71752 | O10: =IFERROR(N10/N9-1,0)
B11: =B10+1 | C11: =C10+365 | D11: 2647.9 | E11: =IFERROR(D11/D10-1,0) | G11: =G10+1 | H11: =H10+365 | I11: 723.28 | J11: =IFERROR(I11/I10-1,0) | L11: =L10+1 | M11: =M10+365 | N11: 43.147808 | O11: =IFERROR(N11/N10-1,0)
B12: =B11+1 | C12: =C11+365 | D12: 2925.54 | E12: =IFERROR(D12/D11-1,0) | G12: =G11+1 | H12: =H11+365 | I12: 775.76 | J12: =IFERROR(I12/I11-1,0) | L12: =L11+1 | M12: =M11+365 | N12: 45.66055 | O12: =IFERROR(N12/N11-1,0)
B13: =B12+1 | C13: =C12+365 | D13: 3365.87 | E13: =IFERROR(D13/D12-1,0) | G13: =G12+1 | H13: =H12+365 | I13: 809.31 | J13: =IFERROR(I13/I12-1,0) | L13: =L12+1 | M13: =M12+365 | N13: 47.715635 | O13: =IFERROR(N13/N12-1,0)
B14: =B13+1 | C14: =C13+365 | D14: 4117.03 | E14: =IFERROR(D14/D13-1,0) | G14: =G13+1 | H14: =H13+365 | I14: 1051.45 | J14: =IFERROR(I14/I13-1,0) | L14: =L13+1 | M14: =M13+365 | N14: 64.324123 | O14: =IFERROR(N14/N13-1,0)
B15: =B14+1 | C15: =C14+365 | D15: =IFERROR(FORECAST(B15,$D$5:$D$14,$B$5:$B$14),0) | E15: =IFERROR(D15/D14-1,0) | G15: =G14+1 | H15: =H14+365 | I15: =IFERROR(FORECAST(G15,$I$5:$I$14,$G$5:$G$14),0) | J15: =IFERROR(I15/I14-1,0) | L15: =L14+1 | M15: =M14+365 | N15: =IFERROR(FORECAST(L15,$N$5:$N$14,$L$5:$L$14),0) | O15: =IFERROR(N15/N14-1,0)
B16: =B15+1 | C16: =C15+365 | D16: =IFERROR(FORECAST(B16,$D$5:$D$14,$B$5:$B$14),0) | E16: =IFERROR(D16/D15-1,0) | G16: =G15+1 | H16: =H15+365 | I16: =IFERROR(FORECAST(G16,$I$5:$I$14,$G$5:$G$14),0) | J16: =IFERROR(I16/I15-1,0) | L16: =L15+1 | M16: =M15+365 | N16: =IFERROR(FORECAST(L16,$N$5:$N$14,$L$5:$L$14),0) | O16: =IFERROR(N16/N15-1,0)
B17: =B16+1 | C17: =C16+365 | D17: =IFERROR(FORECAST(B17,$D$5:$D$14,$B$5:$B$14),0) | E17: =IFERROR(D17/D16-1,0) | G17: =G16+1 | H17: =H16+365 | I17: =IFERROR(FORECAST(G17,$I$5:$I$14,$G$5:$G$14),0) | J17: =IFERROR(I17/I16-1,0) | L17: =L16+1 | M17: =M16+365 | N17: =IFERROR(FORECAST(L17,$N$5:$N$14,$L$5:$L$14),0) | O17: =IFERROR(N17/N16-1,0)
B18: =B17+1 | C18: =C17+365 | D18: =IFERROR(FORECAST(B18,$D$5:$D$14,$B$5:$B$14),0) | E18: =IFERROR(D18/D17-1,0) | G18: =G17+1 | H18: =H17+365 | I18: =IFERROR(FORECAST(G18,$I$5:$I$14,$G$5:$G$14),0) | J18: =IFERROR(I18/I17-1,0) | L18: =L17+1 | M18: =M17+365 | N18: =IFERROR(FORECAST(L18,$N$5:$N$14,$L$5:$L$14),0) | O18: =IFERROR(N18/N17-1,0)
B19: =B18+1 | C19: =C18+365 | D19: =IFERROR(FORECAST(B19,$D$5:$D$14,$B$5:$B$14),0) | E19: =IFERROR(D19/D18-1,0) | G19: =G18+1 | H19: =H18+365 | I19: =IFERROR(FORECAST(G19,$I$5:$I$14,$G$5:$G$14),0) | J19: =IFERROR(I19/I18-1,0) | L19: =L18+1 | M19: =M18+365 | N19: =IFERROR(FORECAST(L19,$N$5:$N$14,$L$5:$L$14),0) | O19: =IFERROR(N19/N18-1,0)

Sheet Data>

Sheet Data Sheet
A1: COMPANY NAME | B1: HINDUSTAN UNILEVER LTD | E1: =IF(B2<>B3, "A NEW VERSION OF THE WORKSHEET IS AVAILABLE", "")
A2: LATEST VERSION | B2: 2.1 | E2: PLEASE DO NOT MAKE ANY CHANGES TO THIS SHEET
A3: CURRENT VERSION | B3: 2.1
A5: META
A6: Number of shares | B6: =IF(B9>0, B9/B8, 0)
A7: Face Value | B7: 1
A8: Current Price | B8: 2174.6
A9: Market Capitalization | B9: 511001.68
A15: PROFIT & LOSS
A16: Report Date | B16: 42825 | C16: 43190 | D16: 43555 | E16: 43921 | F16: 44286 | G16: 44651 | H16: 45016 | I16: 45382 | J16: 45747 | K16: 46112
A17: Sales | B17: 33162 | C17: 35545 | D17: 39310 | E17: 39783 | F17: 47028 | G17: 52446 | H17: 60580 | I17: 61896 | J17: 61328 | K17: 64468
A18: Raw Material Cost | B18: 13606 | C18: 14233 | D18: 15845 | E18: 15697 | F18: 20141 | G18: 22871 | H18: 28427 | I18: 26822 | J18: 26602 | K18: 29158
A19: Change in Inventory | B19: -144 | C19: 72 | D19: -12 | E19: 108 | F19: 405 | G19: 22 | H19: 75 | I19: 11 | J19: 125 | K19: 429
A20: Power and Fuel | B20: 295 | C20: 295 | D20: 308 | E20: 299 | F20: 339 | G20: 318 | H20: 384 | I20: 446 | J20: 403 | K20: 426
A21: Other Mfr. Exp | B21: 2887 | C21: 2998 | D21: 3041 | E21: 2906 | F21: 2868 | G21: 3354 | H21: 3791 | I21: 3385 | J21: 3687 | K21: 3304
A22: Employee Cost | B22: 1743 | C22: 1860 | D22: 1875 | E22: 1820 | F22: 2358 | G22: 2545 | H22: 2854 | I22: 3009 | J22: 2952 | K22: 3175
A23: Selling and admin | B23: 6689 | C23: 7252 | D23: 7796 | E23: 7620 | F23: 7906 | G23: 8164 | H23: 8785 | I23: 10780 | J23: 10145 | K23: 10744
A24: Other Expenses | B24: 1470 | C24: 1480 | D24: 1553 | E24: 1688 | F24: 2195 | G24: 2359 | H24: 2267 | I24: 2806 | J24: 2966 | K24: 3051
A25: Other Income | B25: 606 | C25: 353 | D25: 322 | E25: 424 | F25: 170 | G25: 219 | H25: 448 | I25: 817 | J25: 1355 | K25: 4923
A26: Depreciation | B26: 432 | C26: 520 | D26: 565 | E26: 1002 | F26: 1074 | G26: 1091 | H26: 1137 | I26: 1216 | J26: 1253 | K26: 1333
A27: Interest | B27: 35 | C27: 26 | D27: 33 | E27: 118 | F27: 117 | G27: 106 | H27: 114 | I27: 334 | J27: 381 | K27: 410
... A31: Dividend Amount | B31: 3672 | C31: 4320 | D31: 4752 | E31: 5400 | F31: 9517.5 | G31: 7990 | H31: 9165 | I31: 9870 | J31: 12455 | K31: 9635
A40: Quarters
A41: Report Date | B41: 45291 | C41: 45382 | D41: 45473 | E41: 45565 | F41: 45657 | G41: 45747 | H41: 45838 | I41: 45930 | J41: 46022 | K41: 46112
A42: Sales | B42: 15567 | C42: 15210 | D42: 15707 | E42: 15926 | F42: 15556 | G42: 15190 | H42: 16514 | I42: 15919 | J42: 16441 | K42: 16351
A43: Expenses | B43: 11902 | C43: 11675 | D43: 11965 | E43: 12139 | F43: 11867 | G43: 11572 | H43: 12797 | I43: 12137 | J43: 12660 | K43: 12514
A44: Other Income | B44: 184 | C44: 309 | D44: 209 | E44: 203 | F44: 733 | G44: 149 | H44: 74 | I44: 269 | J44: 4048 | K44: 503
A45: Depreciation | B45: 313 | C45: 320 | D45: 329 | E45: 338 | F45: 318 | G45: 318 | H45: 361 | I45: 322 | J45: 337 | K45: 348
A46: Interest | B46: 91 | C46: 105 | D46: 93 | E46: 110 | F46: 109 | G46: 77 | H46: 127 | I46: 124 | J46: 88 | K46: 76
A47: Profit before tax | B47: 3445 | C47: 3419 | D47: 3529 | E47: 3542 | F47: 3995 | G47: 3372 | H47: 3303 | I47: 3605 | J47: 7404 | K47: 3916
A48: Tax | B48: 937 | C48: 858 | D48: 917 | E48: 947 | F48: 1006 | G48: 897 | H48: 535 | I48: 911 | J48: 801 | K48: 922
A49: Net profit | B49: 2509 | C49: 2558 | D49: 2610 | E49: 2591 | F49: 2984 | G49: 2464 | H49: 2756 | I49: 2685 | J49: 6607 | K49: 2992
A50: Operating Profit | B50: 3665 | C50: 3535 | D50: 3742 | E50: 3787 | F50: 3689 | G50: 3618 | H50: 3717 | I50: 3782 | J50: 3781 | K50: 3837
A55: BALANCE SHEET
A56: Report Date | B56: 42825 | C56: 43190 | D56: 43555 | E56: 43921 | F56: 44286 | G56: 44651 | H56: 45016 | I56: 45382 | J56: 45747 | K56: 46112
A57: Equity Share Capital | B57: 216 | C57: 216 | D57: 216 | E57: 216 | F57: 235 | G57: 235 | H57: 235 | I57: 235 | J57: 235 | K57: 235
A58: Reserves | B58: 6528 | C58: 7065 | D58: 7651 | E58: 8013 | F58: 47439 | G58: 48826 | H58: 50069 | I58: 50983 | J58: 49167 | K58: 48504
A59: Borrowings | B59: 277 | D59: 99 | G59: 1043 | H59: 1219 | I59: 1484 | J59: 1648 | K59: 1478
A60: Other Liabilities | B60: 8685 | C60: 10581 | D60: 10663 | E60: 11924 | F60: 21066 | G60: 20402 | H60: 21554 | I60: 25787 | J60: 28813 | K60: 29521
A61: Total | B61: 15706 | C61: 17862 | D61: 18629 | E61: 20153 | F61: 68740 | G61: 70506 | H61: 73077 | I61: 78489 | J61: 79863 | K61: 79738
A62: Net Block | B62: 4419 | C62: 4528 | D62: 4715 | E62: 5479 | F62: 51443 | G62: 51473 | H62: 52678 | I62: 53744 | J62: 54335 | K62: 57428
A63: Capital Work in Progress | B63: 229 | C63: 461 | D63: 406 | E63: 597 | F63: 745 | G63: 1313 | H63: 1132 | I63: 1025 | J63: 1009 | K63: 880
A64: Investments | B64: 3794 | C64: 2873 | D64: 2716 | E64: 1255 | F64: 2709 | G64: 3521 | H64: 2882 | I64: 4625 | J64: 3810 | K64: 4359
A65: Other Assets | B65: 7264 | C65: 10000 | D65: 10792 | E65: 12822 | F65: 13843 | G65: 14199 | H65: 16385 | I65: 19095 | J65: 20709 | K65: 17071
A66: Total | B66: 15706 | C66: 17862 | D66: 18629 | E66: 20153 | F66: 68740 | G66: 70506 | H66: 73077 | I66: 78489 | J66: 79863 | K66: 79738
A67: Receivables | B67: 1085 | C67: 1310 | D67: 1816 | E67: 1149 | F67: 1758 | G67: 2236 | H67: 3079 | I67: 2997 | J67: 3819 | K67: 3379
A68: Inventory | B68: 2541 | C68: 2513 | D68: 2574 | E68: 2767 | F68: 3579 | G68: 4096 | H68: 4251 | I68: 4022 | J68: 4415 | K68: 4789
A69: Cash & Bank | B69: 1828 | C69: 3485 | D69: 3757 | E69: 5113 | F69: 4471 | G69: 3846 | H69: 4678 | I69: 7559 | J69: 7554 | K69: 3248
A70: No. of Equity Shares | B70: 2164349639 | C70: 2164528777 | D70: 2164704405 | E70: 2164704405 | F70: 2349567819 | G70: 2349591262 | H70: 2349591262 | I70: 2349591262 | J70: 2349591262 | K70: 2349591262
A71: New Bonus Shares
A72: Face value | B72: 1 | C72: 1 | D72: 1 | E72: 1 | F72: 1 | G72: 1 | H72: 1 | I72: 1 | J72: 1 | K72: 1
A80: CASH FLOW:
A81: Report Date | B81: 42825 | C81: 43190 | D81: 43555 | E81: 43921 | F81: 44286 | G81: 44651 | H81: 45016 | I81: 45382 | J81: 45747 | K81: 46112
A82: Cash from Operating Activity | B82: 5185 | C82: 6059 | D82: 5800 | E82: 7623 | F82: 9163 | G82: 9048 | H82: 9991 | I82: 15469 | J82: 11886 | K82: 10999
A83: Cash from Investing Activity | B83: -1173 | C83: -1063 | D83: -438 | E83: 1791 | F83: -1228 | G83: -1728 | H83: -1484 | I83: -5324 | J83: 6473 | K83: -3676
A84: Cash from Financing Activity | B84: -4214 | C84: -4975 | D84: -5390 | E84: -6819 | F84: -9309 | G84: -8015 | H84: -8953 | I84: -10034 | J84: -13101 | K84: -10810
A85: Net Cash Flow | B85: -202 | C85: 21 | D85: -28 | E85: 2595 | F85: -1374 | G85: -695 | H85: -446 | I85: 111 | J85: 5258 | K85: -3487
A90: PRICE: | B90: 872.61 | C90: 1276.11 | D90: 1633.53 | E90: 2199.83 | F90: 2327.12 | G90: 1960.7 | H90: 2450.44 | I90: 2167.14 | J90: 2161.88 | K90: 2055.2
A92: DERIVED:
A93: Adjusted Equity Shares in Cr | B93: 216.43 | C93: 216.45 | D93: 216.47 | E93: 216.48 | F93: 234.96 | G93: 234.96 | H93: 234.96 | I93: 234.96 | J93: 234.96 | K93: 234.96

Sheet Cash Flow Data
C2: 42064 | D2: 42430 | E2: 42795 | F2: 43160 | G2: 43525 | H2: 43891 | I2: 44256 | J2: 44621 | K2: 44986 | L2: 45352 | M2: 45717 | N2: 46082
B3: Cash from Operating Activity - | C3: 243 | D3: 418 | E3: 312 | F3: 305 | G3: 206 | H3: 333 | I3: 365 | J3: 444 | K3: 493 | L3: 526 | M3: 655 | N3: 873
B4: Profit from operations | C4: 325 | D4: 514 | E4: 462 | F4: 402 | G4: 329 | H4: 343 | I4: 458 | J4: 679 | K4: 758 | L4: 826 | M4: 901 | N4: 1198
B5: Receivables | C5: -26 | D5: -63 | E5: -33 | F5: -15 | G5: -15 | H5: 10 | I5: -30 | J5: -37 | K5: -112 | L5: -55 | M5: -93 | N5: -237
B6: Inventory | C6: 0 | D6: 0 | E6: 0 | F6: 0 | G6: 0 | H6: 0 | I6: 0 | J6: 0 | K6: 0 | L6: 0 | M6: 0 | N6: 0
B7: Payables | C7: 1 | D7: 32 | E7: -12 | F7: 18 | G7: -3 | H7: 0 | I7: 7 | J7: 15 | K7: 20 | L7: 11 | M7: 21 | N7: 53
B8: Loans Advances | C8: -8 | D8: 0 | E8: 0 | F8: 0 | G8: 0 | H8: 0 | I8: 0 | J8: 0 | K8: 0 | L8: 0 | M8: 0 | N8: 0
B9: Other WC items | C9: 19 | D9: 48 | E9: -3 | F9: -6 | G9: -12 | H9: 39 | I9: 31 | J9: -48 | K9: 5 | L9: -84 | M9: -11 | N9: 85
B10: Working capital changes | C10: -15 | D10: 16 | E10: -47 | F10: -3 | G10: -30 | H10: 49 | I10: 7 | J10: -70 | K10: -87 | L10: -128 | M10: -82 | N10: -99
B11: Direct taxes | C11: -68 | D11: 0 | E11: 0 | F11: 0 | G11: 0 | H11: 0 | I11: 0 | J11: -164 | K11: -178 | L11: -172 | M11: -164 | N11: -225
B12: Other operating items | C12: 0 | D12: -113 | E12: -103 | F12: -95 | G12: -93 | H12: -59 | I12: -100 | J12: 0 | K12: 0 | L12: 0 | M12: 0 | N12: 0
B13: Cash from Investing Activity - | C13: -62 | D13: -167 | E13: -175 | F13: 26 | G13: -230 | H13: 24 | I13: -2 | J13: 44 | K13: -55 | L13: -483 | M13: 143 | N13: -141
B14: Fixed assets purchased | C14: -61 | D14: -53 | E14: -30 | F14: -42 | G14: -52 | H14: -34 | I14: -39 | J14: -61 | K14: -91 | L14: -67 | M14: -121 | N14: -119
... B34: CFO/OP | C34: 0.98 | D34: 0.87 | E34: 0.68 | F34: 0.83 | G34: 0.67 | H34: 1.02 | I34: 0.81 | J34: 0.92 | K34: 0.93 | L34: 0.9 | M34: 1.01 | N34: 1.04
