Workbook
Name UPDATE: 'Data Sheet'!$E$1

Sheet Financials>

Sheet HistoricalFS
B2: ="Historical Statement - " & 'Data Sheet'!B1 -> Historical Statement - INFOSYS LTD
B3: Years | C3: =IFERROR('Data Sheet'!B16,0) -> 42825 | D3: =IFERROR('Data Sheet'!C16,0) -> 43190 | E3: =IFERROR('Data Sheet'!D16,0) -> 43555 | F3: =IFERROR('Data Sheet'!E16,0) -> 43921 | G3: =IFERROR('Data Sheet'!F16,0) -> 44286 | H3: =IFERROR('Data Sheet'!G16,0) -> 44651 | I3: =IFERROR('Data Sheet'!H16,0) -> 45016 | J3: =IFERROR('Data Sheet'!I16,0) -> 45382 | ... L3: =IFERROR('Data Sheet'!K16,0) -> 46112 | M3: LTM
A5: # | B5: Income Statement
B6: Sales | C6: =IFERROR('Data Sheet'!B17,0) -> 68484 | D6: =IFERROR('Data Sheet'!C17,0) -> 70522 | E6: =IFERROR('Data Sheet'!D17,0) -> 82675 | F6: =IFERROR('Data Sheet'!E17,0) -> 90791 | G6: =IFERROR('Data Sheet'!F17,0) -> 100472 | H6: =IFERROR('Data Sheet'!G17,0) -> 121641 | I6: =IFERROR('Data Sheet'!H17,0) -> 146767 | J6: =IFERROR('Data Sheet'!I17,0) -> 153670 | ... L6: =IFERROR('Data Sheet'!K17,0) -> 178650 | M6: =IFERROR(SUM('Data Sheet'!H42:K42),0) -> 178650
B7: Sales Growth | C7: - | D7: =D6/C6-1 -> 0.029758776 | E7: =E6/D6-1 -> 0.1723292 | F7: =F6/E6-1 -> 0.098167523 | G7: =G6/F6-1 -> 0.10662951 | H7: =H6/G6-1 -> 0.21069552 | I7: =I6/H6-1 -> 0.20655864 | J7: =J6/I6-1 -> 0.047033734 | K7: =K6/J6-1 -> 0.060649444 | L7: =L6/K6-1 -> 0.096079514 | M7: -
B9: COS | C9: =IFERROR(SUM('Data Sheet'!B20:B22)-1*'Data Sheet'!B19,0) -> 44609 | D9: =IFERROR(SUM('Data Sheet'!C20:C22)-1*'Data Sheet'!C19,0) -> 46395 | E9: =IFERROR(SUM('Data Sheet'!D20:D22)-1*'Data Sheet'!D19,0) -> 55446 | F9: =IFERROR(SUM('Data Sheet'!E20:E22)-1*'Data Sheet'!E19,0) -> 62210 | G9: =IFERROR(SUM('Data Sheet'!F20:F22)-1*'Data Sheet'!F19,0) -> 68490 | H9: =IFERROR(SUM('Data Sheet'!G20:G22)-1*'Data Sheet'!G19,0) -> 84819 | I9: =IFERROR(SUM('Data Sheet'!H20:H22)-1*'Data Sheet'!H19,0) -> 104880 | J9: =IFERROR(SUM('Data Sheet'!I20:I22)-1*'Data Sheet'!I19,0) -> 110030 | ... L9: =IFERROR(SUM('Data Sheet'!K20:K22)-1*'Data Sheet'!K19,0) -> 128257 | M9: =IFERROR(SUM('Data Sheet'!H43:K43),0) -> 136371
B10: COS % Sales | C10: =C9/C6 -> 0.65137842 | D10: =D9/D6 -> 0.65787981 | E10: =E9/E6 -> 0.67065014 | F10: =F9/F6 -> 0.68520007 | G10: =G9/G6 -> 0.68168246 | H10: =H9/H6 -> 0.69728957 | I10: =I9/I6 -> 0.71460206 | J10: =J9/J6 -> 0.71601484 | ... M10: =M9/M6 -> 0.76334173
B12: Gross Profit | C12: =C6-C9 -> 23875 | D12: =D6-D9 -> 24127 | E12: =E6-E9 -> 27229 | F12: =F6-F9 -> 28581 | G12: =G6-G9 -> 31982 | H12: =H6-H9 -> 36822 | I12: =I6-I9 -> 41887 | J12: =J6-J9 -> 43640 | ... M12: =M6-M9 -> 42279
B13: Gross Margins | C13: =C12/C6 -> 0.34862158 | D13: =D12/D6 -> 0.34212019 | E13: =E12/E6 -> 0.32934986 | F13: =F12/F6 -> 0.31479993 | G13: =G12/G6 -> 0.31831754 | H13: =H12/H6 -> 0.30271043 | I13: =I12/I6 -> 0.28539794 | J13: =J12/J6 -> 0.28398516 | ... M13: =M12/M6 -> 0.23665827
B15: Selling & General Expenses | C15: =IFERROR(SUM('Data Sheet'!B23:B24),0) -> 5271 | D15: =IFERROR(SUM('Data Sheet'!C23:C24),0) -> 5305 | E15: =IFERROR(SUM('Data Sheet'!D23:D24),0) -> 7059 | F15: =IFERROR(SUM('Data Sheet'!E23:E24),0) -> 6314 | G15: =IFERROR(SUM('Data Sheet'!F23:F24),0) -> 4093 | H15: =IFERROR(SUM('Data Sheet'!G23:G24),0) -> 5331 | I15: =IFERROR(SUM('Data Sheet'!H23:H24),0) -> 6757 | J15: =IFERROR(SUM('Data Sheet'!I23:I24),0) -> 7215 | ... L15: =IFERROR(SUM('Data Sheet'!K23:K24),0) -> 8113
B16: SG&A % Sales | C16: =C15/C6 -> 0.076966883 | D16: =D15/D6 -> 0.075224753 | E16: =E15/E6 -> 0.085382522 | F16: =F15/F6 -> 0.069544338 | G16: =G15/G6 -> 0.040737718 | H16: =H15/H6 -> 0.043825684 | I16: =I15/I6 -> 0.04603896 | J16: =J15/J6 -> 0.046951259 | ... M16: =M15/M6 -> 0
B18: EBITDA | C18: =C12-C15 -> 18604 | D18: =D12-D15 -> 18822 | E18: =E12-E15 -> 20170 | F18: =F12-F15 -> 22267 | G18: =G12-G15 -> 27889 | H18: =H12-H15 -> 31491 | I18: =I12-I15 -> 35130 | J18: =J12-J15 -> 36425 | ... M18: =M12-M15 -> 42279
B19: EBITDA % Sales | C19: =C18/C6 -> 0.27165469 | D19: =D18/D6 -> 0.26689544 | E19: =E18/E6 -> 0.24396734 | F19: =F18/F6 -> 0.24525559 | G19: =G18/G6 -> 0.27757982 | H19: =H18/H6 -> 0.25888475 | I19: =I18/I6 -> 0.23935898 | J19: =J18/J6 -> 0.2370339 | ... M19: =M18/M6 -> 0.23665827
B21: Interest | C21: =IFERROR(('Data Sheet'!B27),0) -> 0 | D21: =IFERROR(('Data Sheet'!C27),0) -> 0 | E21: =IFERROR(('Data Sheet'!D27),0) -> 0 | F21: =IFERROR(('Data Sheet'!E27),0) -> 170 | G21: =IFERROR(('Data Sheet'!F27),0) -> 195 | H21: =IFERROR(('Data Sheet'!G27),0) -> 200 | I21: =IFERROR(('Data Sheet'!H27),0) -> 284 | J21: =IFERROR(('Data Sheet'!I27),0) -> 470 | ... L21: =IFERROR(('Data Sheet'!K27),0) -> 416 | M21: =IFERROR(SUM('Data Sheet'!H46:K46),0) -> 416
B22: Interest % Sales | C22: =C21/C6 -> 0 | D22: =D21/D6 -> 0 | E22: =E21/E6 -> 0 | F22: =F21/F6 -> 0.0018724323 | G22: =G21/G6 -> 0.0019408392 | H22: =H21/H6 -> 0.0016441825 | I22: =I21/I6 -> 0.0019350399 | J22: =J21/J6 -> 0.003058502 | ... M22: =M21/M6 -> 0.0023285754
B24: Depreciation | C24: =IFERROR(('Data Sheet'!B26),0) -> 1703 | D24: =IFERROR(('Data Sheet'!C26),0) -> 1863 | E24: =IFERROR(('Data Sheet'!D26),0) -> 2011 | F24: =IFERROR(('Data Sheet'!E26),0) -> 2893 | G24: =IFERROR(('Data Sheet'!F26),0) -> 3267 | H24: =IFERROR(('Data Sheet'!G26),0) -> 3476 | I24: =IFERROR(('Data Sheet'!H26),0) -> 4225 | J24: =IFERROR(('Data Sheet'!I26),0) -> 4678 | ... L24: =IFERROR(('Data Sheet'!K26),0) -> 4902 | M24: =IFERROR(SUM('Data Sheet'!H45:K45),0) -> 4901
B25: Depreciation % Sales | C25: =C24/C6 -> 0.024867122 | D25: =D24/D6 -> 0.026417288 | E25: =E24/E6 -> 0.024324161 | F25: =F24/F6 -> 0.031864392 | G25: =G24/G6 -> 0.032516522 | H25: =H24/H6 -> 0.028575891 | I25: =I24/I6 -> 0.028787125 | J25: =J24/J6 -> 0.030441856 | ... M25: =M24/M6 -> 0.027433529
B27: Earnings Before Tax | C27: =IFERROR(C18-SUM(C21,C24),0) -> 16901 | D27: =IFERROR(D18-SUM(D21,D24),0) -> 16959 | E27: =IFERROR(E18-SUM(E21,E24),0) -> 18159 | F27: =IFERROR(F18-SUM(F21,F24),0) -> 19204 | G27: =IFERROR(G18-SUM(G21,G24),0) -> 24427 | H27: =IFERROR(H18-SUM(H21,H24),0) -> 27815 | I27: =IFERROR(I18-SUM(I21,I24),0) -> 30621 | J27: =IFERROR(J18-SUM(J21,J24),0) -> 31277 | ... M27: =IFERROR(M18-SUM(M21,M24),0) -> 36962
B28: EBT % Sales | C28: =C27/C6 -> 0.24678757 | D28: =D27/D6 -> 0.24047815 | E28: =E27/E6 -> 0.21964318 | F28: =F27/F6 -> 0.21151876 | G28: =G27/G6 -> 0.24312246 | H28: =H27/H6 -> 0.22866468 | I28: =I27/I6 -> 0.20863682 | J28: =J27/J6 -> 0.20353355 | ... M28: =M27/M6 -> 0.20689617
B30: Tax | C30: =IFERROR('Data Sheet'!B29,0) -> 5598 | D30: =IFERROR('Data Sheet'!C29,0) -> 4241 | E30: =IFERROR('Data Sheet'!D29,0) -> 5631 | F30: =IFERROR('Data Sheet'!E29,0) -> 5368 | G30: =IFERROR('Data Sheet'!F29,0) -> 7205 | H30: =IFERROR('Data Sheet'!G29,0) -> 7964 | I30: =IFERROR('Data Sheet'!H29,0) -> 9214 | J30: =IFERROR('Data Sheet'!I29,0) -> 9740 | ... L30: =IFERROR('Data Sheet'!K29,0) -> 10521 | M30: =IFERROR(SUM('Data Sheet'!H48:K48),0) -> 10521
B31: Effective Tax rate | C31: =C30/C27 -> 0.331223 | D31: =D30/D27 -> 0.25007371 | E31: =E30/E27 -> 0.31009417 | F31: =F30/F27 -> 0.2795251 | G31: =G30/G27 -> 0.29496049 | H31: =H30/H27 -> 0.28632033 | I31: =I30/I27 -> 0.30090461 | J31: =J30/J27 -> 0.31141094 | ... M31: =M30/M27 -> 0.28464369
B33: Net Profit | C33: =IFERROR((C27-C30),0) -> 11303 | D33: =IFERROR((D27-D30),0) -> 12718 | E33: =IFERROR((E27-E30),0) -> 12528 | F33: =IFERROR((F27-F30),0) -> 13836 | G33: =IFERROR((G27-G30),0) -> 17222 | H33: =IFERROR((H27-H30),0) -> 19851 | I33: =IFERROR((I27-I30),0) -> 21407 | J33: =IFERROR((J27-J30),0) -> 21537 | ... M33: =IFERROR((M27-M30),0) -> 26441
B34: Net Margin | C34: =C33/C6 -> 0.16504585 | D34: =D33/D6 -> 0.18034089 | E34: =E33/E6 -> 0.15153311 | F34: =F33/F6 -> 0.15239396 | G34: =G33/G6 -> 0.17141094 | H34: =H33/H6 -> 0.16319333 | I34: =I33/I6 -> 0.14585704 | J34: =J33/J6 -> 0.14015097 | ... M34: =M33/M6 -> 0.14800448
B36: No. of Equity Shares O/S | C36: =IFERROR('Data Sheet'!B93,0) -> 459.39 | D36: =IFERROR('Data Sheet'!C93,0) -> 436.82 | E36: =IFERROR('Data Sheet'!D93,0) -> 436.89 | F36: =IFERROR('Data Sheet'!E93,0) -> 425.9 | G36: =IFERROR('Data Sheet'!F93,0) -> 426.07 | H36: =IFERROR('Data Sheet'!G93,0) -> 420.67 | I36: =IFERROR('Data Sheet'!H93,0) -> 414.86 | J36: =IFERROR('Data Sheet'!I93,0) -> 415.09 | ... L36: =IFERROR('Data Sheet'!K93,0) -> 405.56 | M36: =L36 -> 405.56
B38: Earnings Per Share | C38: =IFERROR(C33/C36,0) -> 24.604367 | D38: =IFERROR(D33/D36,0) -> 29.114967 | E38: =IFERROR(E33/E36,0) -> 28.67541 | F38: =IFERROR(F33/F36,0) -> 32.486499 | G38: =IFERROR(G33/G36,0) -> 40.420588 | H38: =IFERROR(H33/H36,0) -> 47.189008 | I38: =IFERROR(I33/I36,0) -> 51.60054 | J38: =IFERROR(J33/J36,0) -> 51.885133 | ... M38: =IFERROR(M33/M36,0) -> 65.196272
B39: EPS growth % | D39: =IFERROR((D38/C38-1),0) -> 0.18332521 | E39: =IFERROR((E38/D38-1),0) -> -0.015097286 | F39: =IFERROR((F38/E38-1),0) -> 0.13290442 | G39: =IFERROR((G38/F38-1),0) -> 0.24422727 | H39: =IFERROR((H38/G38-1),0) -> 0.16744981 | I39: =IFERROR((I38/H38-1),0) -> 0.093486431 | J39: =IFERROR((J38/I38-1),0) -> 0.0055153183 | K39: =IFERROR((K38/J38-1),0) -> 0.074273236 | ... M39: =IFERROR((M38/L38-1),0) -> 0
B41: Dividends Per Share | C41: =IFERROR(('Data Sheet'!B31/C36),0) -> 12.824833 | D41: =IFERROR(('Data Sheet'!C31/D36),0) -> 21.669337 | E41: =IFERROR(('Data Sheet'!D31/E36),0) -> 21.109433 | F41: =IFERROR(('Data Sheet'!E31/F36),0) -> 17.438366 | G41: =IFERROR(('Data Sheet'!F31/G36),0) -> 26.91952 | H41: =IFERROR(('Data Sheet'!G31/H36),0) -> 30.92115 | I41: =IFERROR(('Data Sheet'!H31/I36),0) -> 33.913127 | J41: =IFERROR(('Data Sheet'!I31/J36),0) -> 45.901371 | ... M41: =IFERROR(('Data Sheet'!L31/M36),0) -> 0
B42: Dividend Payout Ratio | C42: =IFERROR((C41/C38),0) -> 0.52124215 | D42: =IFERROR((D41/D38),0) -> 0.74426797 | E42: =IFERROR((E41/E38),0) -> 0.73615102 | F42: =IFERROR((F41/F38),0) -> 0.53678809 | G42: =IFERROR((G41/G38),0) -> 0.66598537 | H42: =IFERROR((H41/H38),0) -> 0.6552617 | I42: =IFERROR((I41/I38),0) -> 0.65722427 | J42: =IFERROR((J41/J38),0) -> 0.88467289 | ... M42: =IFERROR((M41/M38),0) -> 0
B44: Retained Earnings | C44: =IFERROR(IF(C38>C41,1-C42,0),0) -> 0.47875785 | D44: =IFERROR(IF(D38>D41,1-D42,0),0) -> 0.25573203 | E44: =IFERROR(IF(E38>E41,1-E42,0),0) -> 0.26384898 | F44: =IFERROR(IF(F38>F41,1-F42,0),0) -> 0.46321191 | G44: =IFERROR(IF(G38>G41,1-G42,0),0) -> 0.33401463 | H44: =IFERROR(IF(H38>H41,1-H42,0),0) -> 0.3447383 | I44: =IFERROR(IF(I38>I41,1-I42,0),0) -> 0.34277573 | J44: =IFERROR(IF(J38>J41,1-J42,0),0) -> 0.11532711 | ... M44: =IFERROR(IF(M38>M41,1-M42,0),0) -> 1
A46: # | B46: Balance Sheet
B47: Equity Share Capital | C47: =IFERROR('Data Sheet'!B57,0) -> 1144 | D47: =IFERROR('Data Sheet'!C57,0) -> 1088 | E47: =IFERROR('Data Sheet'!D57,0) -> 2170 | F47: =IFERROR('Data Sheet'!E57,0) -> 2122 | G47: =IFERROR('Data Sheet'!F57,0) -> 2124 | H47: =IFERROR('Data Sheet'!G57,0) -> 2098 | I47: =IFERROR('Data Sheet'!H57,0) -> 2069 | J47: =IFERROR('Data Sheet'!I57,0) -> 2071 | ... L47: =IFERROR('Data Sheet'!K57,0) -> 2024
B48: Reserves | C48: =IFERROR('Data Sheet'!B58,0) -> 67838 | D48: =IFERROR('Data Sheet'!C58,0) -> 63835 | E48: =IFERROR('Data Sheet'!D58,0) -> 62778 | F48: =IFERROR('Data Sheet'!E58,0) -> 63328 | G48: =IFERROR('Data Sheet'!F58,0) -> 74227 | H48: =IFERROR('Data Sheet'!G58,0) -> 73252 | I48: =IFERROR('Data Sheet'!H58,0) -> 73338 | J48: =IFERROR('Data Sheet'!I58,0) -> 86045 | ... L48: =IFERROR('Data Sheet'!K58,0) -> 90828
B49: Borrowings | C49: =IFERROR('Data Sheet'!B59,0) -> 0 | D49: =IFERROR('Data Sheet'!C59,0) -> 0 | E49: =IFERROR('Data Sheet'!D59,0) -> 0 | F49: =IFERROR('Data Sheet'!E59,0) -> 4633 | G49: =IFERROR('Data Sheet'!F59,0) -> 5325 | H49: =IFERROR('Data Sheet'!G59,0) -> 5474 | I49: =IFERROR('Data Sheet'!H59,0) -> 8299 | J49: =IFERROR('Data Sheet'!I59,0) -> 8359 | ... L49: =IFERROR('Data Sheet'!K59,0) -> 9176
B50: Other Liabilities | C50: =IFERROR('Data Sheet'!B60,0) -> 14166 | D50: =IFERROR('Data Sheet'!C60,0) -> 14426 | E50: =IFERROR('Data Sheet'!D60,0) -> 19118 | F50: =IFERROR('Data Sheet'!E60,0) -> 21717 | G50: =IFERROR('Data Sheet'!F60,0) -> 25835 | H50: =IFERROR('Data Sheet'!G60,0) -> 35905 | I50: =IFERROR('Data Sheet'!H60,0) -> 40890 | J50: =IFERROR('Data Sheet'!I60,0) -> 39545 | ... L50: =IFERROR('Data Sheet'!K60,0) -> 52260
B51: Total Liabilities | C51: =IFERROR('Data Sheet'!B61,0) -> 83148 | D51: =IFERROR('Data Sheet'!C61,0) -> 79349 | E51: =IFERROR('Data Sheet'!D61,0) -> 84066 | F51: =IFERROR('Data Sheet'!E61,0) -> 91800 | G51: =IFERROR('Data Sheet'!F61,0) -> 107511 | H51: =IFERROR('Data Sheet'!G61,0) -> 116729 | I51: =IFERROR('Data Sheet'!H61,0) -> 124596 | J51: =IFERROR('Data Sheet'!I61,0) -> 136020 | ... L51: =IFERROR('Data Sheet'!K61,0) -> 154288
B53: Fixed Assets Net Block | C53: =IFERROR('Data Sheet'!B62,0) -> 14179 | D53: =IFERROR('Data Sheet'!C62,0) -> 12574 | E53: =IFERROR('Data Sheet'!D62,0) -> 15710 | F53: =IFERROR('Data Sheet'!E62,0) -> 23789 | G53: =IFERROR('Data Sheet'!F62,0) -> 25505 | H53: =IFERROR('Data Sheet'!G62,0) -> 25800 | I53: =IFERROR('Data Sheet'!H62,0) -> 29225 | J53: =IFERROR('Data Sheet'!I62,0) -> 27622 | ... L53: =IFERROR('Data Sheet'!K62,0) -> 33770
B54: Capital Work in Progress | C54: =IFERROR('Data Sheet'!B63,0) -> 1365 | D54: =IFERROR('Data Sheet'!C63,0) -> 1606 | E54: =IFERROR('Data Sheet'!D63,0) -> 1388 | F54: =IFERROR('Data Sheet'!E63,0) -> 954 | G54: =IFERROR('Data Sheet'!F63,0) -> 922 | H54: =IFERROR('Data Sheet'!G63,0) -> 416 | I54: =IFERROR('Data Sheet'!H63,0) -> 288 | J54: =IFERROR('Data Sheet'!I63,0) -> 293 | ... L54: =IFERROR('Data Sheet'!K63,0) -> 526
B55: Investments | C55: =IFERROR('Data Sheet'!B64,0) -> 16423 | D55: =IFERROR('Data Sheet'!C64,0) -> 12163 | E55: =IFERROR('Data Sheet'!D64,0) -> 11261 | F55: =IFERROR('Data Sheet'!E64,0) -> 8792 | G55: =IFERROR('Data Sheet'!F64,0) -> 14205 | H55: =IFERROR('Data Sheet'!G64,0) -> 20324 | I55: =IFERROR('Data Sheet'!H64,0) -> 19478 | J55: =IFERROR('Data Sheet'!I64,0) -> 24623 | ... L55: =IFERROR('Data Sheet'!K64,0) -> 21880
B56: Other Assets | C56: =IFERROR('Data Sheet'!B65-SUM('Data Sheet'!B67:B69),0) -> 16234 | D56: =IFERROR('Data Sheet'!C65-SUM('Data Sheet'!C67:C69),0) -> 20046 | E56: =IFERROR('Data Sheet'!D65-SUM('Data Sheet'!D67:D69),0) -> 21312 | F56: =IFERROR('Data Sheet'!E65-SUM('Data Sheet'!E67:E69),0) -> 21129 | G56: =IFERROR('Data Sheet'!F65-SUM('Data Sheet'!F67:F69),0) -> 22871 | H56: =IFERROR('Data Sheet'!G65-SUM('Data Sheet'!G67:G69),0) -> 30019 | I56: =IFERROR('Data Sheet'!H65-SUM('Data Sheet'!H67:H69),0) -> 38008 | J56: =IFERROR('Data Sheet'!I65-SUM('Data Sheet'!I67:I69),0) -> 38503 | ... L56: =IFERROR('Data Sheet'!K65-SUM('Data Sheet'!K67:K69),0) -> 40677
B57: Total Non Current Asset | C57: =IFERROR(SUM(C53:C56),0) -> 48201 | D57: =IFERROR(SUM(D53:D56),0) -> 46389 | E57: =IFERROR(SUM(E53:E56),0) -> 49671 | F57: =IFERROR(SUM(F53:F56),0) -> 54664 | G57: =IFERROR(SUM(G53:G56),0) -> 63503 | H57: =IFERROR(SUM(H53:H56),0) -> 76559 | I57: =IFERROR(SUM(I53:I56),0) -> 86999 | J57: =IFERROR(SUM(J53:J56),0) -> 91041 | ... L57: =IFERROR(SUM(L53:L56),0) -> 96853
B59: Receivables | C59: =IFERROR('Data Sheet'!B67,0) -> 12322 | D59: =IFERROR('Data Sheet'!C67,0) -> 13142 | E59: =IFERROR('Data Sheet'!D67,0) -> 14827 | F59: =IFERROR('Data Sheet'!E67,0) -> 18487 | G59: =IFERROR('Data Sheet'!F67,0) -> 19294 | H59: =IFERROR('Data Sheet'!G67,0) -> 22698 | I59: =IFERROR('Data Sheet'!H67,0) -> 25424 | J59: =IFERROR('Data Sheet'!I67,0) -> 30193 | ... L59: =IFERROR('Data Sheet'!K67,0) -> 35234
B60: Inventory | C60: =IFERROR('Data Sheet'!B68,0) -> 0 | D60: =IFERROR('Data Sheet'!C68,0) -> 0 | E60: =IFERROR('Data Sheet'!D68,0) -> 0 | F60: =IFERROR('Data Sheet'!E68,0) -> 0 | G60: =IFERROR('Data Sheet'!F68,0) -> 0 | H60: =IFERROR('Data Sheet'!G68,0) -> 0 | I60: =IFERROR('Data Sheet'!H68,0) -> 0 | J60: =IFERROR('Data Sheet'!I68,0) -> 0 | ... L60: =IFERROR('Data Sheet'!K68,0) -> 0
B61: Cash & Bank | C61: =IFERROR('Data Sheet'!B69,0) -> 22625 | D61: =IFERROR('Data Sheet'!C69,0) -> 19818 | E61: =IFERROR('Data Sheet'!D69,0) -> 19568 | F61: =IFERROR('Data Sheet'!E69,0) -> 18649 | G61: =IFERROR('Data Sheet'!F69,0) -> 24714 | H61: =IFERROR('Data Sheet'!G69,0) -> 17472 | I61: =IFERROR('Data Sheet'!H69,0) -> 12173 | J61: =IFERROR('Data Sheet'!I69,0) -> 14786 | ... L61: =IFERROR('Data Sheet'!K69,0) -> 22201
B62: Total Current Asset | C62: =IFERROR(SUM(C59:C61),0) -> 34947 | D62: =IFERROR(SUM(D59:D61),0) -> 32960 | E62: =IFERROR(SUM(E59:E61),0) -> 34395 | F62: =IFERROR(SUM(F59:F61),0) -> 37136 | G62: =IFERROR(SUM(G59:G61),0) -> 44008 | H62: =IFERROR(SUM(H59:H61),0) -> 40170 | I62: =IFERROR(SUM(I59:I61),0) -> 37597 | J62: =IFERROR(SUM(J59:J61),0) -> 44979 | ... L62: =IFERROR(SUM(L59:L61),0) -> 57435
B64: Total Asset | C64: =IFERROR((C62+C57),0) -> 83148 | D64: =IFERROR((D62+D57),0) -> 79349 | E64: =IFERROR((E62+E57),0) -> 84066 | F64: =IFERROR((F62+F57),0) -> 91800 | G64: =IFERROR((G62+G57),0) -> 107511 | H64: =IFERROR((H62+H57),0) -> 116729 | I64: =IFERROR((I62+I57),0) -> 124596 | J64: =IFERROR((J62+J57),0) -> 136020 | ... L64: =IFERROR((L62+L57),0) -> 154288
B66: CHECK | C66: =C64=C51 -> TRUE | D66: =D64=D51 -> TRUE | E66: =E64=E51 -> TRUE | F66: =F64=F51 -> TRUE | G66: =G64=G51 -> TRUE | H66: =H64=H51 -> TRUE | I66: =I64=I51 -> TRUE | J66: =J64=J51 -> TRUE | ... L66: =L64=L51 -> TRUE
A68: # | B68: Cash Flow Statement
B69: Operating Activities
B70: Profit from operations | C70: =IFERROR('Cash Flow Data'!E4,0) -> 19340 | D70: =IFERROR('Cash Flow Data'!F4,0) -> 19963 | E70: =IFERROR('Cash Flow Data'!G4,0) -> 22126 | F70: =IFERROR('Cash Flow Data'!H4,0) -> 23920 | G70: =IFERROR('Cash Flow Data'!I4,0) -> 28845 | H70: =IFERROR('Cash Flow Data'!J4,0) -> 32921 | I70: =IFERROR('Cash Flow Data'!K4,0) -> 37605 | J70: =IFERROR('Cash Flow Data'!L4,0) -> 39523 | ... L70: =IFERROR('Cash Flow Data'!N4,0) -> 45273
B71: Receivables | C71: =IFERROR('Cash Flow Data'!E5,0) -> -1743 | D71: =IFERROR('Cash Flow Data'!F5,0) -> -1523 | E71: =IFERROR('Cash Flow Data'!G5,0) -> -2881 | F71: =IFERROR('Cash Flow Data'!H5,0) -> -3861 | G71: =IFERROR('Cash Flow Data'!I5,0) -> -1835 | H71: =IFERROR('Cash Flow Data'!J5,0) -> -7937 | I71: =IFERROR('Cash Flow Data'!K5,0) -> -7076 | J71: =IFERROR('Cash Flow Data'!L5,0) -> -2667 | ... L71: =IFERROR('Cash Flow Data'!N5,0) -> -5177
B72: Inventory | C72: 0 | D72: 0 | E72: 0 | F72: 0 | G72: 0 | H72: 0 | I72: 0 | J72: 0 | K72: 0 | L72: 0
B73: Payables | C73: =IFERROR('Cash Flow Data'!E6,0) -> -19 | D73: =IFERROR('Cash Flow Data'!F6,0) -> 328 | E73: =IFERROR('Cash Flow Data'!G6,0) -> 916 | F73: =IFERROR('Cash Flow Data'!H6,0) -> -373 | G73: =IFERROR('Cash Flow Data'!I6,0) -> -245 | H73: =IFERROR('Cash Flow Data'!J6,0) -> 1489 | I73: =IFERROR('Cash Flow Data'!K6,0) -> -279 | J73: =IFERROR('Cash Flow Data'!L6,0) -> 91 | ... L73: =IFERROR('Cash Flow Data'!N6,0) -> -26
B74: Loans Advances | C74: =IFERROR('Cash Flow Data'!E7,0) -> 0 | D74: =IFERROR('Cash Flow Data'!F7,0) -> 0 | E74: =IFERROR('Cash Flow Data'!G7,0) -> 0 | F74: =IFERROR('Cash Flow Data'!H7,0) -> 0 | G74: =IFERROR('Cash Flow Data'!I7,0) -> -534 | H74: =IFERROR('Cash Flow Data'!J7,0) -> -1914 | I74: =IFERROR('Cash Flow Data'!K7,0) -> -3108 | J74: =IFERROR('Cash Flow Data'!L7,0) -> -1172 | ... L74: =IFERROR('Cash Flow Data'!N7,0) -> -2645
B75: Other WC items | C75: =IFERROR('Cash Flow Data'!E8,0) -> -394 | D75: =IFERROR('Cash Flow Data'!F8,0) -> 1279 | E75: =IFERROR('Cash Flow Data'!G8,0) -> 1512 | F75: =IFERROR('Cash Flow Data'!H8,0) -> 1867 | G75: =IFERROR('Cash Flow Data'!I8,0) -> 3382 | H75: =IFERROR('Cash Flow Data'!J8,0) -> 6938 | I75: =IFERROR('Cash Flow Data'!K8,0) -> 4119 | J75: =IFERROR('Cash Flow Data'!L8,0) -> -1334 | ... L75: =IFERROR('Cash Flow Data'!N8,0) -> 5209
B76: Working capital changes | C76: =IFERROR('Cash Flow Data'!E9,0) -> -2156 | D76: =IFERROR('Cash Flow Data'!F9,0) -> 84 | E76: =IFERROR('Cash Flow Data'!G9,0) -> -453 | F76: =IFERROR('Cash Flow Data'!H9,0) -> -2367 | G76: =IFERROR('Cash Flow Data'!I9,0) -> 768 | H76: =IFERROR('Cash Flow Data'!J9,0) -> -1424 | I76: =IFERROR('Cash Flow Data'!K9,0) -> -6344 | J76: =IFERROR('Cash Flow Data'!L9,0) -> -5082 | ... L76: =IFERROR('Cash Flow Data'!N9,0) -> -2639
B77: Direct taxes | C77: =IFERROR('Cash Flow Data'!E10,0) -> -5653 | D77: =IFERROR('Cash Flow Data'!F10,0) -> -6829 | E77: =IFERROR('Cash Flow Data'!G10,0) -> -6832 | F77: =IFERROR('Cash Flow Data'!H10,0) -> -4550 | G77: =IFERROR('Cash Flow Data'!I10,0) -> -6389 | H77: =IFERROR('Cash Flow Data'!J10,0) -> -7612 | I77: =IFERROR('Cash Flow Data'!K10,0) -> -8794 | J77: =IFERROR('Cash Flow Data'!L10,0) -> -9231 | ... L77: =IFERROR('Cash Flow Data'!N10,0) -> -8648
B78: Other operating items | C78: 0 | D78: 0 | E78: 0 | F78: 0 | G78: 0 | H78: 0 | I78: 0 | J78: 0 | K78: 0 | L78: 0
B79: Cash from Operating Activities | C79: =IFERROR(SUM(C70,C76,C77,C78),0) -> 11531 | D79: =IFERROR(SUM(D70,D76,D77,D78),0) -> 13218 | E79: =IFERROR(SUM(E70,E76,E77,E78),0) -> 14841 | F79: =IFERROR(SUM(F70,F76,F77,F78),0) -> 17003 | G79: =IFERROR(SUM(G70,G76,G77,G78),0) -> 23224 | H79: =IFERROR(SUM(H70,H76,H77,H78),0) -> 23885 | I79: =IFERROR(SUM(I70,I76,I77,I78),0) -> 22467 | J79: =IFERROR(SUM(J70,J76,J77,J78),0) -> 25210 | ... L79: =IFERROR(SUM(L70,L76,L77,L78),0) -> 33986
B81: Investing Activities
B82: Fixed assets purchased | C82: =IFERROR('Cash Flow Data'!E12,0) -> -2760 | D82: =IFERROR('Cash Flow Data'!F12,0) -> -1998 | E82: =IFERROR('Cash Flow Data'!G12,0) -> -2445 | F82: =IFERROR('Cash Flow Data'!H12,0) -> -3307 | G82: =IFERROR('Cash Flow Data'!I12,0) -> -2107 | H82: =IFERROR('Cash Flow Data'!J12,0) -> -2161 | I82: =IFERROR('Cash Flow Data'!K12,0) -> -2579 | J82: =IFERROR('Cash Flow Data'!L12,0) -> -2201 | ... L82: =IFERROR('Cash Flow Data'!N12,0) -> -2727
B83: Fixed assets sold | C83: =IFERROR('Cash Flow Data'!E15,0) -> 0 | D83: =IFERROR('Cash Flow Data'!F15,0) -> 0 | E83: =IFERROR('Cash Flow Data'!G15,0) -> 0 | F83: =IFERROR('Cash Flow Data'!H15,0) -> 0 | G83: =IFERROR('Cash Flow Data'!I15,0) -> 0 | H83: =IFERROR('Cash Flow Data'!J15,0) -> 0 | I83: =IFERROR('Cash Flow Data'!K15,0) -> 0 | J83: =IFERROR('Cash Flow Data'!L15,0) -> 0 | ... L83: =IFERROR('Cash Flow Data'!N15,0) -> 0
B84: Investments purchased | C84: =IFERROR('Cash Flow Data'!E13,0) -> -66410 | D84: =IFERROR('Cash Flow Data'!F13,0) -> -69159 | E84: =IFERROR('Cash Flow Data'!G13,0) -> -79410 | F84: =IFERROR('Cash Flow Data'!H13,0) -> -37482 | G84: =IFERROR('Cash Flow Data'!I13,0) -> -46738 | H84: =IFERROR('Cash Flow Data'!J13,0) -> -59951 | I84: =IFERROR('Cash Flow Data'!K13,0) -> -75800 | J84: =IFERROR('Cash Flow Data'!L13,0) -> -78092 | ... L84: =IFERROR('Cash Flow Data'!N13,0) -> -82617
B85: Investments sold | C85: =IFERROR('Cash Flow Data'!E14,0) -> 52048 | D85: =IFERROR('Cash Flow Data'!F14,0) -> 74003 | E85: =IFERROR('Cash Flow Data'!G14,0) -> 78098 | F85: =IFERROR('Cash Flow Data'!H14,0) -> 38861 | G85: =IFERROR('Cash Flow Data'!I14,0) -> 40381 | H85: =IFERROR('Cash Flow Data'!J14,0) -> 57356 | I85: =IFERROR('Cash Flow Data'!K14,0) -> 76722 | J85: =IFERROR('Cash Flow Data'!L14,0) -> 72930 | ... L85: =IFERROR('Cash Flow Data'!N14,0) -> 89699
B86: Interest received | C86: =IFERROR('Cash Flow Data'!E15,0) -> 0 | D86: =IFERROR('Cash Flow Data'!F15,0) -> 0 | E86: =IFERROR('Cash Flow Data'!G15,0) -> 0 | F86: =IFERROR('Cash Flow Data'!H15,0) -> 0 | G86: =IFERROR('Cash Flow Data'!I15,0) -> 0 | H86: =IFERROR('Cash Flow Data'!J15,0) -> 0 | I86: =IFERROR('Cash Flow Data'!K15,0) -> 0 | J86: =IFERROR('Cash Flow Data'!L15,0) -> 0 | ... L86: =IFERROR('Cash Flow Data'!N15,0) -> 0
B87: Dividends received | C87: =IFERROR('Cash Flow Data'!E16,0) -> 2753 | D87: =IFERROR('Cash Flow Data'!F16,0) -> 1768 | E87: =IFERROR('Cash Flow Data'!G16,0) -> 1557 | F87: =IFERROR('Cash Flow Data'!H16,0) -> 1929 | G87: =IFERROR('Cash Flow Data'!I16,0) -> 1418 | H87: =IFERROR('Cash Flow Data'!J16,0) -> 1898 | I87: =IFERROR('Cash Flow Data'!K16,0) -> 1525 | J87: =IFERROR('Cash Flow Data'!L16,0) -> 1768 | ... L87: =IFERROR('Cash Flow Data'!N16,0) -> 2713
B88: Acquisition of companies | C88: =IFERROR('Cash Flow Data'!E17,0) -> 0 | D88: =IFERROR('Cash Flow Data'!F17,0) -> 0 | E88: =IFERROR('Cash Flow Data'!G17,0) -> 0 | F88: =IFERROR('Cash Flow Data'!H17,0) -> 0 | G88: =IFERROR('Cash Flow Data'!I17,0) -> 0 | H88: =IFERROR('Cash Flow Data'!J17,0) -> 0 | I88: =IFERROR('Cash Flow Data'!K17,0) -> 0 | J88: =IFERROR('Cash Flow Data'!L17,0) -> 0 | ... L88: =IFERROR('Cash Flow Data'!N17,0) -> 0
B89: Inter corporate deposits | C89: =IFERROR('Cash Flow Data'!E18,0) -> -164 | D89: =IFERROR('Cash Flow Data'!F18,0) -> -130 | E89: =IFERROR('Cash Flow Data'!G18,0) -> -24 | F89: =IFERROR('Cash Flow Data'!H18,0) -> -108 | G89: =IFERROR('Cash Flow Data'!I18,0) -> 0 | H89: =IFERROR('Cash Flow Data'!J18,0) -> 0 | I89: =IFERROR('Cash Flow Data'!K18,0) -> 0 | J89: =IFERROR('Cash Flow Data'!L18,0) -> 0 | ... L89: =IFERROR('Cash Flow Data'!N18,0) -> 0
B90: Other investing items | C90: =IFERROR('Cash Flow Data'!E19,0) -> -131 | D90: =IFERROR('Cash Flow Data'!F19,0) -> 49 | E90: =IFERROR('Cash Flow Data'!G19,0) -> 1592 | F90: =IFERROR('Cash Flow Data'!H19,0) -> -224 | G90: =IFERROR('Cash Flow Data'!I19,0) -> -327 | H90: =IFERROR('Cash Flow Data'!J19,0) -> -3627 | I90: =IFERROR('Cash Flow Data'!K19,0) -> -939 | J90: =IFERROR('Cash Flow Data'!L19,0) -> 502 | ... L90: =IFERROR('Cash Flow Data'!N19,0) -> -3522
B91: Cash from Investing Activities | C91: =IFERROR(SUM(C82:C90),0) -> -14664 | D91: =IFERROR(SUM(D82:D90),0) -> 4533 | E91: =IFERROR(SUM(E82:E90),0) -> -632 | F91: =IFERROR(SUM(F82:F90),0) -> -331 | G91: =IFERROR(SUM(G82:G90),0) -> -7373 | H91: =IFERROR(SUM(H82:H90),0) -> -6485 | I91: =IFERROR(SUM(I82:I90),0) -> -1071 | J91: =IFERROR(SUM(J82:J90),0) -> -5093 | ... L91: =IFERROR(SUM(L82:L90),0) -> 3546
B93: Financing Activities
B94: Proceeds from shares | C94: =IFERROR('Cash Flow Data'!E21,0) -> 0 | D94: =IFERROR('Cash Flow Data'!F21,0) -> 5 | E94: =IFERROR('Cash Flow Data'!G21,0) -> 6 | F94: =IFERROR('Cash Flow Data'!H21,0) -> 6 | G94: =IFERROR('Cash Flow Data'!I21,0) -> 15 | H94: =IFERROR('Cash Flow Data'!J21,0) -> 21 | I94: =IFERROR('Cash Flow Data'!K21,0) -> 35 | J94: =IFERROR('Cash Flow Data'!L21,0) -> 5 | ... L94: =IFERROR('Cash Flow Data'!N21,0) -> 2
B95: Proceeds from borrowings | C95: 0 | D95: 0 | E95: 0 | F95: 0 | G95: 0 | H95: 0 | I95: 0 | J95: 0 | K95: 0 | L95: 0
B96: Repayment of borrowings | C96: =IFERROR('Cash Flow Data'!E22,0) -> 0 | D96: =IFERROR('Cash Flow Data'!F22,0) -> 0 | E96: =IFERROR('Cash Flow Data'!G22,0) -> 0 | F96: =IFERROR('Cash Flow Data'!H22,0) -> 0 | G96: =IFERROR('Cash Flow Data'!I22,0) -> 0 | H96: =IFERROR('Cash Flow Data'!J22,0) -> 0 | I96: =IFERROR('Cash Flow Data'!K22,0) -> 0 | J96: =IFERROR('Cash Flow Data'!L22,0) -> 0 | ... L96: =IFERROR('Cash Flow Data'!N22,0) -> 0
B97: Proceeds from deposits | C97: 0 | D97: 0 | E97: 0 | F97: 0 | G97: 0 | H97: 0 | I97: 0 | J97: 0 | K97: 0 | L97: 0
B98: Interest paid fin | C98: 0 | D98: 0 | E98: 0 | F98: 0 | G98: 0 | H98: 0 | I98: 0 | J98: 0 | K98: 0 | L98: 0
B99: Dividends paid | C99: =IFERROR('Cash Flow Data'!E23,0) -> -6939 | D99: =IFERROR('Cash Flow Data'!F23,0) -> -7464 | E99: =IFERROR('Cash Flow Data'!G23,0) -> -13705 | F99: =IFERROR('Cash Flow Data'!H23,0) -> -9548 | G99: =IFERROR('Cash Flow Data'!I23,0) -> -9137 | H99: =IFERROR('Cash Flow Data'!J23,0) -> -12731 | I99: =IFERROR('Cash Flow Data'!K23,0) -> -13653 | J99: =IFERROR('Cash Flow Data'!L23,0) -> -14731 | ... L99: =IFERROR('Cash Flow Data'!N23,0) -> -18656
B100: Financial liabilities | C100: =IFERROR('Cash Flow Data'!E24,0) -> 0 | D100: =IFERROR('Cash Flow Data'!F24,0) -> 0 | E100: =IFERROR('Cash Flow Data'!G24,0) -> 0 | F100: =IFERROR('Cash Flow Data'!H24,0) -> -571 | G100: =IFERROR('Cash Flow Data'!I24,0) -> -698 | H100: =IFERROR('Cash Flow Data'!J24,0) -> -915 | I100: =IFERROR('Cash Flow Data'!K24,0) -> -1231 | J100: =IFERROR('Cash Flow Data'!L24,0) -> -2024 | ... L100: =IFERROR('Cash Flow Data'!N24,0) -> -2824
B101: Application money refund | C101: 0 | D101: 0 | E101: 0 | F101: 0 | G101: 0 | H101: 0 | I101: 0 | J101: 0 | K101: 0 | L101: 0
B102: Other financing items | C102: =IFERROR('Cash Flow Data'!E25,0) -> 0 | D102: =IFERROR('Cash Flow Data'!F25,0) -> -13046 | E102: =IFERROR('Cash Flow Data'!G25,0) -> -813 | F102: =IFERROR('Cash Flow Data'!H25,0) -> -7478 | G102: =IFERROR('Cash Flow Data'!I25,0) -> 34 | H102: =IFERROR('Cash Flow Data'!J25,0) -> -11017 | I102: =IFERROR('Cash Flow Data'!K25,0) -> -11846 | J102: =IFERROR('Cash Flow Data'!L25,0) -> -754 | ... L102: =IFERROR('Cash Flow Data'!N25,0) -> -18308
B103: Cash from Financing Activities | C103: =IFERROR(SUM(C94:C102),0) -> -6939 | D103: =IFERROR(SUM(D94:D102),0) -> -20505 | E103: =IFERROR(SUM(E94:E102),0) -> -14512 | F103: =IFERROR(SUM(F94:F102),0) -> -17591 | G103: =IFERROR(SUM(G94:G102),0) -> -9786 | H103: =IFERROR(SUM(H94:H102),0) -> -24642 | I103: =IFERROR(SUM(I94:I102),0) -> -26695 | J103: =IFERROR(SUM(J94:J102),0) -> -17504 | ... L103: =IFERROR(SUM(L94:L102),0) -> -39786
B105: Net Cash Flow | C105: =IFERROR(SUM(C103,C91,C79),0) -> -10072 | D105: =IFERROR(SUM(D103,D91,D79),0) -> -2754 | E105: =IFERROR(SUM(E103,E91,E79),0) -> -303 | F105: =IFERROR(SUM(F103,F91,F79),0) -> -919 | G105: =IFERROR(SUM(G103,G91,G79),0) -> 6065 | H105: =IFERROR(SUM(H103,H91,H79),0) -> -7242 | I105: =IFERROR(SUM(I103,I91,I79),0) -> -5299 | J105: =IFERROR(SUM(J103,J91,J79),0) -> 2613 | ... L105: =IFERROR(SUM(L103,L91,L79),0) -> -2254

Sheet Data>

Sheet Data Sheet
A1: COMPANY NAME | B1: INFOSYS LTD | E1: =IF(B2<>B3, "A NEW VERSION OF THE WORKSHEET IS AVAILABLE", "")
A2: LATEST VERSION | B2: 2.1 | E2: PLEASE DO NOT MAKE ANY CHANGES TO THIS SHEET
A3: CURRENT VERSION | B3: 2.1
A5: META
A6: Number of shares | B6: =IF(B9>0, B9/B8, 0) -> 405.75788
A7: Face Value | B7: 5
A8: Current Price | B8: 1096.5
A9: Market Capitalization | B9: 444913.52
A15: PROFIT & LOSS
A16: Report Date | B16: 42825 | C16: 43190 | D16: 43555 | E16: 43921 | F16: 44286 | G16: 44651 | H16: 45016 | I16: 45382 | J16: 45747 | K16: 46112
A17: Sales | B17: 68484 | C17: 70522 | D17: 82675 | E17: 90791 | F17: 100472 | G17: 121641 | H17: 146767 | I17: 153670 | J17: 162990 | K17: 178650
A18: Raw Material Cost
A19: Change in Inventory
A20: Power and Fuel | B20: 228 | C20: 207 | D20: 221 | E20: 229 | F20: 143 | G20: 132 | H20: 176 | I20: 199 | J20: 222 | K20: 223
A21: Other Mfr. Exp | B21: 6712 | C21: 7286 | D21: 9902 | E21: 11086 | F21: 12800 | G21: 20690 | H21: 26330 | I21: 27195 | J21: 30395 | K21: 32922
A22: Employee Cost | B22: 37669 | C22: 38902 | D22: 45323 | E22: 50895 | F22: 55547 | G22: 63997 | H22: 78374 | I22: 82636 | J22: 85968 | K22: 95112
A23: Selling and admin | B23: 4584 | C23: 4585 | D23: 5553 | E23: 5375 | F23: 3194 | G23: 4305 | H23: 5300 | I23: 5705 | J23: 6039 | K23: 6784
A24: Other Expenses | B24: 687 | C24: 720 | D24: 1506 | E24: 939 | F24: 899 | G24: 1026 | H24: 1457 | I24: 1510 | J24: 1130 | K24: 1329
A25: Other Income | B25: 3050 | C25: 3311 | D25: 2882 | E25: 2803 | F25: 2201 | G25: 2295 | H25: 2701 | I25: 4711 | J25: 3600 | K25: 3033
A26: Depreciation | B26: 1703 | C26: 1863 | D26: 2011 | E26: 2893 | F26: 3267 | G26: 3476 | H26: 4225 | I26: 4678 | J26: 4812 | K26: 4902
A27: Interest | E27: 170 | F27: 195 | G27: 200 | H27: 284 | I27: 470 | J27: 416 | K27: 416
A28: Profit before tax | B28: 19951 | C28: 20270 | D28: 21041 | E28: 22007 | F28: 26628 | G28: 30110 | H28: 33322 | I28: 35988 | J28: 37608 | K28: 39995
A29: Tax | B29: 5598 | C29: 4241 | D29: 5631 | E29: 5368 | F29: 7205 | G29: 7964 | H29: 9214 | I29: 9740 | J29: 10858 | K29: 10521
A30: Net profit | B30: 14353 | C30: 16029 | D30: 15404 | E30: 16594 | F30: 19351 | G30: 22110 | H30: 24095 | I30: 26233 | J30: 26713 | K30: 29440
A31: Dividend Amount | B31: 5891.6 | C31: 9465.6 | D31: 9222.5 | E31: 7427 | F31: 11469.6 | G31: 13007.6 | H31: 14069.2 | I31: 19053.2 | J31: 17827.8 | K31: 19430.4
A40: Quarters
A41: Report Date | B41: 45291 | C41: 45382 | D41: 45473 | E41: 45565 | F41: 45657 | G41: 45747 | H41: 45838 | I41: 45930 | J41: 46022 | K41: 46112
A42: Sales | B42: 38821 | C42: 37923 | D42: 39315 | E42: 40986 | F42: 41764 | G42: 40925 | H42: 42279 | I42: 44490 | J42: 45479 | K42: 46402
A43: Expenses | B43: 29684 | C43: 29139 | D43: 29878 | E43: 31177 | F43: 31649 | G43: 31051 | H43: 32336 | I43: 33955 | J43: 34845 | K43: 35235
A44: Other Income | B44: 789 | C44: 2729 | D44: 838 | E44: 712 | F44: 859 | G44: 1190 | H44: 1042 | I44: 982 | J44: -150 | K44: 1159
A45: Depreciation | B45: 1176 | C45: 1163 | D45: 1149 | E45: 1160 | F45: 1203 | G45: 1299 | H45: 1140 | I45: 1182 | J45: 1155 | K45: 1424
A46: Interest | B46: 131 | C46: 110 | D46: 105 | E46: 108 | F46: 101 | G46: 102 | H46: 105 | I46: 106 | J46: 100 | K46: 105
A47: Profit before tax | B47: 8619 | C47: 10240 | D47: 9021 | E47: 9253 | F47: 9670 | G47: 9663 | H47: 9740 | I47: 10229 | J47: 9229 | K47: 10797
A48: Tax | B48: 2506 | C48: 2265 | D48: 2647 | E48: 2737 | F48: 2848 | G48: 2625 | H48: 2816 | I48: 2854 | J48: 2563 | K48: 2288
A49: Net profit | B49: 6106 | C49: 7969 | D49: 6368 | E49: 6506 | F49: 6806 | G49: 7033 | H49: 6921 | I49: 7364 | J49: 6654 | K49: 8501
A50: Operating Profit | B50: 9137 | C50: 8784 | D50: 9437 | E50: 9809 | F50: 10115 | G50: 9874 | H50: 9943 | I50: 10535 | J50: 10634 | K50: 11167
A55: BALANCE SHEET
A56: Report Date | B56: 42825 | C56: 43190 | D56: 43555 | E56: 43921 | F56: 44286 | G56: 44651 | H56: 45016 | I56: 45382 | J56: 45747 | K56: 46112
A57: Equity Share Capital | B57: 1144 | C57: 1088 | D57: 2170 | E57: 2122 | F57: 2124 | G57: 2098 | H57: 2069 | I57: 2071 | J57: 2073 | K57: 2024
A58: Reserves | B58: 67838 | C58: 63835 | D58: 62778 | E58: 63328 | F58: 74227 | G58: 73252 | H58: 73338 | I58: 86045 | J58: 93745 | K58: 90828
A59: Borrowings | E59: 4633 | F59: 5325 | G59: 5474 | H59: 8299 | I59: 8359 | J59: 8227 | K59: 9176
A60: Other Liabilities | B60: 14166 | C60: 14426 | D60: 19118 | E60: 21717 | F60: 25835 | G60: 35905 | H60: 40890 | I60: 39545 | J60: 43750 | K60: 52260
A61: Total | B61: 83148 | C61: 79349 | D61: 84066 | E61: 91800 | F61: 107511 | G61: 116729 | H61: 124596 | I61: 136020 | J61: 147795 | K61: 154288
A62: Net Block | B62: 14179 | C62: 12574 | D62: 15710 | E62: 23789 | F62: 25505 | G62: 25800 | H62: 29225 | I62: 27622 | J62: 30961 | K62: 33770
A63: Capital Work in Progress | B63: 1365 | C63: 1606 | D63: 1388 | E63: 954 | F63: 922 | G63: 416 | H63: 288 | I63: 293 | J63: 814 | K63: 526
A64: Investments | B64: 16423 | C64: 12163 | D64: 11261 | E64: 8792 | F64: 14205 | G64: 20324 | H64: 19478 | I64: 24623 | J64: 23541 | K64: 21880
A65: Other Assets | B65: 51181 | C65: 53006 | D65: 55707 | E65: 58265 | F65: 66879 | G65: 70189 | H65: 75605 | I65: 83482 | J65: 92479 | K65: 98112
A66: Total | B66: 83148 | C66: 79349 | D66: 84066 | E66: 91800 | F66: 107511 | G66: 116729 | H66: 124596 | I66: 136020 | J66: 147795 | K66: 154288
A67: Receivables | B67: 12322 | C67: 13142 | D67: 14827 | E67: 18487 | F67: 19294 | G67: 22698 | H67: 25424 | I67: 30193 | J67: 31158 | K67: 35234
A68: Inventory
A69: Cash & Bank | B69: 22625 | C69: 19818 | D69: 19568 | E69: 18649 | F69: 24714 | G69: 17472 | H69: 12173 | I69: 14786 | J69: 24455 | K69: 22201
A70: No. of Equity Shares | B70: 2285655150 | C70: 2173312301 | D70: 4335954462 | E70: 4240753210 | F70: 4245146114 | G70: 4193012929 | H70: 4136387925 | I70: 4139950635 | J70: 4143607528 | K70: 4046940812
A71: New Bonus Shares | D71: 2184191490
A72: Face value | B72: 5 | C72: 5 | D72: 5 | E72: 5 | F72: 5 | G72: 5 | H72: 5 | I72: 5 | J72: 5 | K72: 5
A80: CASH FLOW:
A81: Report Date | B81: 42825 | C81: 43190 | D81: 43555 | E81: 43921 | F81: 44286 | G81: 44651 | H81: 45016 | I81: 45382 | J81: 45747 | K81: 46112
A82: Cash from Operating Activity | B82: 11531 | C82: 13218 | D82: 14841 | E82: 17003 | F82: 23224 | G82: 23885 | H82: 22467 | I82: 25210 | J82: 35694 | K82: 33986
A83: Cash from Investing Activity | B83: -14664 | C83: 4533 | D83: -632 | E83: -331 | F83: -7373 | G83: -6485 | H83: -1071 | I83: -5093 | J83: -1864 | K83: 3546
A84: Cash from Financing Activity | B84: -6939 | C84: -20505 | D84: -14512 | E84: -17591 | F84: -9786 | G84: -24642 | H84: -26695 | I84: -17504 | J84: -24161 | K84: -39786
A85: Net Cash Flow | B85: -10072 | C85: -2754 | D85: -303 | E85: -919 | F85: 6065 | G85: -7242 | H85: -5299 | I85: 2613 | J85: 9669 | K85: -2254
A90: PRICE: | B90: 511.13 | C90: 565.9 | D90: 743.85 | E90: 641.5 | F90: 1368.05 | G90: 1906.85 | H90: 1427.95 | I90: 1498.05 | J90: 1570.65 | K90: 1250.6
A92: DERIVED:
A93: Adjusted Equity Shares in Cr | B93: 459.39 | C93: 436.82 | D93: 436.89 | E93: 425.9 | F93: 426.07 | G93: 420.67 | H93: 414.86 | I93: 415.09 | J93: 415.33 | K93: 405.56

Sheet Cash Flow Data
C2: 42064 | D2: 42430 | E2: 42795 | F2: 43160 | G2: 43525 | H2: 43891 | I2: 44256 | J2: 44621 | K2: 44986 | L2: 45352 | M2: 45717 | N2: 46082
B3: Cash from Operating Activity - | C3: 8353 | D3: 10028 | E3: 11531 | F3: 13218 | G3: 14841 | H3: 17003 | I3: 23224 | J3: 23885 | K3: 22467 | L3: 25210 | M3: 35694 | N3: 33986
B4: Profit from operations | C4: 15946 | D4: 17839 | E4: 19340 | F4: 19963 | G4: 22126 | H4: 23920 | I4: 28845 | J4: 32921 | K4: 37605 | L4: 39523 | M4: 41591 | N4: 45273
B5: Receivables | C5: -1475 | D5: -1654 | E5: -1743 | F5: -1523 | G5: -2881 | H5: -3861 | I5: -1835 | J5: -7937 | K5: -7076 | L5: -2667 | M5: -1769 | N5: -5177
B6: Payables | C6: 0 | D6: 242 | E6: -19 | F6: 328 | G6: 916 | H6: -373 | I6: -245 | J6: 1489 | K6: -279 | L6: 91 | M6: 176 | N6: -26
B7: Loans Advances | C7: -221 | D7: -1134 | E7: 0 | F7: 0 | G7: 0 | H7: 0 | I7: -534 | J7: -1914 | K7: -3108 | L7: -1172 | M7: -1024 | N7: -2645
B8: Other WC items | C8: 854 | D8: 600 | E8: -394 | F8: 1279 | G8: 1512 | H8: 1867 | I8: 3382 | J8: 6938 | K8: 4119 | L8: -1334 | M8: 2322 | N8: 5209
B9: Working capital changes | C9: -842 | D9: -1946 | E9: -2156 | F9: 84 | G9: -453 | H9: -2367 | I9: 768 | J9: -1424 | K9: -6344 | L9: -5082 | M9: -295 | N9: -2639
B10: Direct taxes | C10: -6751 | D10: -5865 | E10: -5653 | F10: -6829 | G10: -6832 | H10: -4550 | I10: -6389 | J10: -7612 | K10: -8794 | L10: -9231 | M10: -5602 | N10: -8648
B11: Cash from Investing Activity - | C11: 999 | D11: -885 | E11: -14664 | F11: 4533 | G11: -632 | H11: -331 | I11: -7373 | J11: -6485 | K11: -1071 | L11: -5093 | M11: -1864 | N11: 3546
B12: Fixed assets purchased | C12: -2247 | D12: -2723 | E12: -2760 | F12: -1998 | G12: -2445 | H12: -3307 | I12: -2107 | J12: -2161 | K12: -2579 | L12: -2201 | M12: -2237 | N12: -2727
B13: Investments purchased | C13: -23923 | D13: -24577 | E13: -66410 | F13: -69159 | G13: -79410 | H13: -37482 | I13: -46738 | J13: -59951 | K13: -75800 | L13: -78092 | M13: -82742 | N13: -82617
B14: Investments sold | C14: 25253 | D14: 24980 | E14: 52048 | F14: 74003 | G14: 78098 | H14: 38861 | I14: 40381 | J14: 57356 | K14: 76722 | L14: 72930 | M14: 84877 | N14: 89699
... B28: CFO/OP | C28: 1.01 | D28: 0.93 | E28: 0.92 | F28: 1.07 | G28: 1.07 | H28: 0.97 | I28: 1.06 | J28: 1 | K28: 0.89 | L28: 0.95 | M28: 1.05 | N28: 1.01
