Workbook
Name UPDATE: 'Data Sheet'!$E$1

Sheet HistoricalFS
B2: ="Historical Statement - " & 'Data Sheet'!B1 -> Historical Statement - ECLERX SERVICES LTD
B3: Years | C3: =IFERROR('Data Sheet'!B16,0) -> 42825 | D3: =IFERROR('Data Sheet'!C16,0) -> 43190 | E3: =IFERROR('Data Sheet'!D16,0) -> 43555 | F3: =IFERROR('Data Sheet'!E16,0) -> 43921 | G3: =IFERROR('Data Sheet'!F16,0) -> 44286 | H3: =IFERROR('Data Sheet'!G16,0) -> 44651 | I3: =IFERROR('Data Sheet'!H16,0) -> 45016 | J3: =IFERROR('Data Sheet'!I16,0) -> 45382 | ... L3: =IFERROR('Data Sheet'!K16,0) -> 46112 | M3: LTM
A5: # | B5: Income Statement
B6: Sales | C6: =IFERROR('Data Sheet'!B17,0) -> 1330.03 | D6: =IFERROR('Data Sheet'!C17,0) -> 1365.06 | E6: =IFERROR('Data Sheet'!D17,0) -> 1430.59 | F6: =IFERROR('Data Sheet'!E17,0) -> 1437.57 | G6: =IFERROR('Data Sheet'!F17,0) -> 1564.49 | H6: =IFERROR('Data Sheet'!G17,0) -> 2160.35 | I6: =IFERROR('Data Sheet'!H17,0) -> 2647.9 | J6: =IFERROR('Data Sheet'!I17,0) -> 2925.54 | ... L6: =IFERROR('Data Sheet'!K17,0) -> 4117.03 | M6: =IFERROR(SUM('Data Sheet'!H42:K42),0) -> 4117.03
B7: Sales Growth | C7: - | D7: =D6/C6-1 -> 0.026337752 | E7: =E6/D6-1 -> 0.048005216 | F7: =F6/E6-1 -> 0.0048791058 | G7: =G6/F6-1 -> 0.088287875 | H7: =H6/G6-1 -> 0.38086533 | I7: =I6/H6-1 -> 0.22568102 | J7: =J6/I6-1 -> 0.1048529 | K7: =K6/J6-1 -> 0.15051238 | L7: =L6/K6-1 -> 0.22316964 | M7: -
B9: COS | C9: =IFERROR(SUM('Data Sheet'!B20:B22)-1*'Data Sheet'!B19,0) -> 667.47 | D9: =IFERROR(SUM('Data Sheet'!C20:C22)-1*'Data Sheet'!C19,0) -> 781.61 | E9: =IFERROR(SUM('Data Sheet'!D20:D22)-1*'Data Sheet'!D19,0) -> 879.96 | F9: =IFERROR(SUM('Data Sheet'!E20:E22)-1*'Data Sheet'!E19,0) -> 930.88 | G9: =IFERROR(SUM('Data Sheet'!F20:F22)-1*'Data Sheet'!F19,0) -> 956.15 | H9: =IFERROR(SUM('Data Sheet'!G20:G22)-1*'Data Sheet'!G19,0) -> 1327.6 | I9: =IFERROR(SUM('Data Sheet'!H20:H22)-1*'Data Sheet'!H19,0) -> 1670.43 | J9: =IFERROR(SUM('Data Sheet'!I20:I22)-1*'Data Sheet'!I19,0) -> 1867.16 | ... L9: =IFERROR(SUM('Data Sheet'!K20:K22)-1*'Data Sheet'!K19,0) -> 2524.53 | M9: =IFERROR(SUM('Data Sheet'!H43:K43),0) -> 3065.58
B10: COS % Sales | C10: =C9/C6 -> 0.50184582 | D10: =D9/D6 -> 0.57258289 | E10: =E9/E6 -> 0.61510286 | F10: =F9/F6 -> 0.64753716 | G10: =G9/G6 -> 0.61115763 | H10: =H9/H6 -> 0.61453005 | I10: =I9/I6 -> 0.63085086 | J10: =J9/J6 -> 0.63822747 | ... M10: =M9/M6 -> 0.74460959
B12: Gross Profit | C12: =C6-C9 -> 662.56 | D12: =D6-D9 -> 583.45 | E12: =E6-E9 -> 550.63 | F12: =F6-F9 -> 506.69 | G12: =G6-G9 -> 608.34 | H12: =H6-H9 -> 832.75 | I12: =I6-I9 -> 977.47 | J12: =J6-J9 -> 1058.38 | ... M12: =M6-M9 -> 1051.45
B13: Gross Margins | C13: =C12/C6 -> 0.49815418 | D13: =D12/D6 -> 0.42741711 | E13: =E12/E6 -> 0.38489714 | F13: =F12/F6 -> 0.35246284 | G13: =G12/G6 -> 0.38884237 | H13: =H12/H6 -> 0.38546995 | I13: =I12/I6 -> 0.36914914 | J13: =J12/J6 -> 0.36177253 | ... M13: =M12/M6 -> 0.25539041
B15: Selling & General Expenses | C15: =IFERROR(SUM('Data Sheet'!B23:B24),0) -> 201.29 | D15: =IFERROR(SUM('Data Sheet'!C23:C24),0) -> 215.95 | E15: =IFERROR(SUM('Data Sheet'!D23:D24),0) -> 241.78 | F15: =IFERROR(SUM('Data Sheet'!E23:E24),0) -> 180.54 | G15: =IFERROR(SUM('Data Sheet'!F23:F24),0) -> 158.81 | H15: =IFERROR(SUM('Data Sheet'!G23:G24),0) -> 170.7 | I15: =IFERROR(SUM('Data Sheet'!H23:H24),0) -> 254.19 | J15: =IFERROR(SUM('Data Sheet'!I23:I24),0) -> 282.62 | ... L15: =IFERROR(SUM('Data Sheet'!K23:K24),0) -> 541.05
B16: SG&A % Sales | C16: =C15/C6 -> 0.15134245 | D16: =D15/D6 -> 0.15819817 | E16: =E15/E6 -> 0.16900719 | F16: =F15/F6 -> 0.12558693 | G16: =G15/G6 -> 0.10150912 | H16: =H15/H6 -> 0.079014974 | I16: =I15/I6 -> 0.095996828 | J16: =J15/J6 -> 0.096604388 | ... M16: =M15/M6 -> 0
B18: EBITDA | C18: =C12-C15 -> 461.27 | D18: =D12-D15 -> 367.5 | E18: =E12-E15 -> 308.85 | F18: =F12-F15 -> 326.15 | G18: =G12-G15 -> 449.53 | H18: =H12-H15 -> 662.05 | I18: =I12-I15 -> 723.28 | J18: =J12-J15 -> 775.76 | ... M18: =M12-M15 -> 1051.45
B19: EBITDA % Sales | C19: =C18/C6 -> 0.34681173 | D19: =D18/D6 -> 0.26921894 | E19: =E18/E6 -> 0.21588995 | F19: =F18/F6 -> 0.22687591 | G19: =G18/G6 -> 0.28733325 | H19: =H18/H6 -> 0.30645497 | I19: =I18/I6 -> 0.27315231 | J19: =J18/J6 -> 0.26516814 | ... M19: =M18/M6 -> 0.25539041
B21: Interest | C21: =IFERROR(('Data Sheet'!B27),0) -> 1.57 | D21: =IFERROR(('Data Sheet'!C27),0) -> 1.17 | E21: =IFERROR(('Data Sheet'!D27),0) -> 1.27 | F21: =IFERROR(('Data Sheet'!E27),0) -> 20.16 | G21: =IFERROR(('Data Sheet'!F27),0) -> 21.42 | H21: =IFERROR(('Data Sheet'!G27),0) -> 22.76 | I21: =IFERROR(('Data Sheet'!H27),0) -> 22.19 | J21: =IFERROR(('Data Sheet'!I27),0) -> 24.45 | ... L21: =IFERROR(('Data Sheet'!K27),0) -> 42.14 | M21: =IFERROR(SUM('Data Sheet'!H46:K46),0) -> 42.14
B22: Interest % Sales | C22: =C21/C6 -> 0.0011804245 | D22: =D21/D6 -> 0.00085710518 | E22: =E21/E6 -> 0.00088774562 | F22: =F21/F6 -> 0.014023665 | G22: =G21/G6 -> 0.013691363 | H22: =H21/H6 -> 0.01053533 | I22: =I21/I6 -> 0.0083802258 | J22: =J21/J6 -> 0.0083574314 | ... M22: =M21/M6 -> 0.010235534
B24: Depreciation | C24: =IFERROR(('Data Sheet'!B26),0) -> 51.8 | D24: =IFERROR(('Data Sheet'!C26),0) -> 48.24 | E24: =IFERROR(('Data Sheet'!D26),0) -> 44.69 | F24: =IFERROR(('Data Sheet'!E26),0) -> 70.9 | G24: =IFERROR(('Data Sheet'!F26),0) -> 81.59 | H24: =IFERROR(('Data Sheet'!G26),0) -> 103.19 | I24: =IFERROR(('Data Sheet'!H26),0) -> 114.01 | J24: =IFERROR(('Data Sheet'!I26),0) -> 125.77 | ... L24: =IFERROR(('Data Sheet'!K26),0) -> 175.37 | M24: =IFERROR(SUM('Data Sheet'!H45:K45),0) -> 175.37
B25: Depreciation % Sales | C25: =C24/C6 -> 0.03894649 | D25: =D24/D6 -> 0.035339106 | E25: =E24/E6 -> 0.031238859 | F25: =F24/F6 -> 0.049319337 | G25: =G24/G6 -> 0.05215118 | H25: =H24/H6 -> 0.047765408 | I25: =I24/I6 -> 0.043056762 | J25: =J24/J6 -> 0.042990354 | ... M25: =M24/M6 -> 0.04259624
B27: Earnings Before Tax | C27: =IFERROR(C18-SUM(C21,C24),0) -> 407.9 | D27: =IFERROR(D18-SUM(D21,D24),0) -> 318.09 | E27: =IFERROR(E18-SUM(E21,E24),0) -> 262.89 | F27: =IFERROR(F18-SUM(F21,F24),0) -> 235.09 | G27: =IFERROR(G18-SUM(G21,G24),0) -> 346.52 | H27: =IFERROR(H18-SUM(H21,H24),0) -> 536.1 | I27: =IFERROR(I18-SUM(I21,I24),0) -> 587.08 | J27: =IFERROR(J18-SUM(J21,J24),0) -> 625.54 | ... M27: =IFERROR(M18-SUM(M21,M24),0) -> 833.94
B28: EBT % Sales | C28: =C27/C6 -> 0.30668481 | D28: =D27/D6 -> 0.23302272 | E28: =E27/E6 -> 0.18376334 | F28: =F27/F6 -> 0.16353291 | G28: =G27/G6 -> 0.22149071 | H28: =H27/H6 -> 0.24815423 | I28: =I27/I6 -> 0.22171532 | J28: =J27/J6 -> 0.21382035 | ... M28: =M27/M6 -> 0.20255864
B30: Tax | C30: =IFERROR('Data Sheet'!B29,0) -> 81.91 | D30: =IFERROR('Data Sheet'!C29,0) -> 89.58 | E30: =IFERROR('Data Sheet'!D29,0) -> 83.17 | F30: =IFERROR('Data Sheet'!E29,0) -> 71.55 | G30: =IFERROR('Data Sheet'!F29,0) -> 97.8 | H30: =IFERROR('Data Sheet'!G29,0) -> 142.73 | I30: =IFERROR('Data Sheet'!H29,0) -> 163.8 | J30: =IFERROR('Data Sheet'!I29,0) -> 177.61 | ... L30: =IFERROR('Data Sheet'!K29,0) -> 228.65 | M30: =IFERROR(SUM('Data Sheet'!H48:K48),0) -> 228.64
B31: Effective Tax rate | C31: =C30/C27 -> 0.20080902 | D31: =D30/D27 -> 0.28161841 | E31: =E30/E27 -> 0.31636806 | F31: =F30/F27 -> 0.30435152 | G31: =G30/G27 -> 0.28223479 | H31: =H30/H27 -> 0.26623764 | I31: =I30/I27 -> 0.27900797 | J31: =J30/J27 -> 0.28393068 | ... M31: =M30/M27 -> 0.27416841
B33: Net Profit | C33: =IFERROR((C27-C30),0) -> 325.99 | D33: =IFERROR((D27-D30),0) -> 228.51 | E33: =IFERROR((E27-E30),0) -> 179.72 | F33: =IFERROR((F27-F30),0) -> 163.54 | G33: =IFERROR((G27-G30),0) -> 248.72 | H33: =IFERROR((H27-H30),0) -> 393.37 | I33: =IFERROR((I27-I30),0) -> 423.28 | J33: =IFERROR((J27-J30),0) -> 447.93 | ... M33: =IFERROR((M27-M30),0) -> 605.3
B34: Net Margin | C34: =C33/C6 -> 0.24509973 | D34: =D33/D6 -> 0.16739924 | E34: =E33/E6 -> 0.12562649 | F34: =F33/F6 -> 0.11376142 | G34: =G33/G6 -> 0.15897833 | H34: =H33/H6 -> 0.18208624 | I34: =I33/I6 -> 0.15985498 | J34: =J33/J6 -> 0.1531102 | ... M34: =M33/M6 -> 0.14702346
B36: No. of Equity Shares O/S | C36: =IFERROR('Data Sheet'!B93,0) -> 11.94 | D36: =IFERROR('Data Sheet'!C93,0) -> 11.6 | E36: =IFERROR('Data Sheet'!D93,0) -> 11.61 | F36: =IFERROR('Data Sheet'!E93,0) -> 11.1 | G36: =IFERROR('Data Sheet'!F93,0) -> 10.47 | H36: =IFERROR('Data Sheet'!G93,0) -> 10.16 | I36: =IFERROR('Data Sheet'!H93,0) -> 9.81 | J36: =IFERROR('Data Sheet'!I93,0) -> 9.81 | ... L36: =IFERROR('Data Sheet'!K93,0) -> 9.41 | M36: =L36 -> 9.41
B38: Earnings Per Share | C38: =IFERROR(C33/C36,0) -> 27.302345 | D38: =IFERROR(D33/D36,0) -> 19.699138 | E38: =IFERROR(E33/E36,0) -> 15.479759 | F38: =IFERROR(F33/F36,0) -> 14.733333 | G38: =IFERROR(G33/G36,0) -> 23.755492 | H38: =IFERROR(H33/H36,0) -> 38.71752 | I38: =IFERROR(I33/I36,0) -> 43.147808 | J38: =IFERROR(J33/J36,0) -> 45.66055 | ... M38: =IFERROR(M33/M36,0) -> 64.325186
B39: EPS growth % | D39: =IFERROR((D38/C38-1),0) -> -0.27848183 | E39: =IFERROR((E38/D38-1),0) -> -0.21419105 | F39: =IFERROR((F38/E38-1),0) -> -0.048219452 | G39: =IFERROR((G38/F38-1),0) -> 0.6123637 | H39: =IFERROR((H38/G38-1),0) -> 0.62983448 | I39: =IFERROR((I38/H38-1),0) -> 0.11442594 | J39: =IFERROR((J38/I38-1),0) -> 0.058235683 | K39: =IFERROR((K38/J38-1),0) -> 0.045007876 | ... M39: =IFERROR((M38/L38-1),0) -> 1.6521006e-05
B41: Dividends Per Share | C41: =IFERROR(('Data Sheet'!B31/C36),0) -> 0.33249581 | D41: =IFERROR(('Data Sheet'!C31/D36),0) -> 0.32844828 | E41: =IFERROR(('Data Sheet'!D31/E36),0) -> 0.3255814 | F41: =IFERROR(('Data Sheet'!E31/F36),0) -> 0.32522523 | G41: =IFERROR(('Data Sheet'!F31/G36),0) -> 0.32473734 | H41: =IFERROR(('Data Sheet'!G31/H36),0) -> 0.3257874 | I41: =IFERROR(('Data Sheet'!H31/I36),0) -> 0.48929664 | J41: =IFERROR(('Data Sheet'!I31/J36),0) -> 0.49133537 | ... M41: =IFERROR(('Data Sheet'!L31/M36),0) -> 0
B42: Dividend Payout Ratio | C42: =IFERROR((C41/C38),0) -> 0.012178288 | D42: =IFERROR((D41/D38),0) -> 0.016673231 | E42: =IFERROR((E41/E38),0) -> 0.021032718 | F42: =IFERROR((F41/F38),0) -> 0.02207411 | G42: =IFERROR((G41/G38),0) -> 0.01366999 | H42: =IFERROR((H41/H38),0) -> 0.0084144698 | I42: =IFERROR((I41/I38),0) -> 0.011340011 | J42: =IFERROR((J41/J38),0) -> 0.01076061 | ... M42: =IFERROR((M41/M38),0) -> 0
B44: Retained Earnings | C44: =IFERROR(IF(C38>C41,1-C42,0),0) -> 0.98782171 | D44: =IFERROR(IF(D38>D41,1-D42,0),0) -> 0.98332677 | E44: =IFERROR(IF(E38>E41,1-E42,0),0) -> 0.97896728 | F44: =IFERROR(IF(F38>F41,1-F42,0),0) -> 0.97792589 | G44: =IFERROR(IF(G38>G41,1-G42,0),0) -> 0.98633001 | H44: =IFERROR(IF(H38>H41,1-H42,0),0) -> 0.99158553 | I44: =IFERROR(IF(I38>I41,1-I42,0),0) -> 0.98865999 | J44: =IFERROR(IF(J38>J41,1-J42,0),0) -> 0.98923939 | ... M44: =IFERROR(IF(M38>M41,1-M42,0),0) -> 1
A46: # | B46: Balance Sheet
B47: Equity Share Capital | C47: =IFERROR('Data Sheet'!B57,0) -> 39.71 | D47: =IFERROR('Data Sheet'!C57,0) -> 38.14 | E47: =IFERROR('Data Sheet'!D57,0) -> 37.79 | F47: =IFERROR('Data Sheet'!E57,0) -> 36.1 | G47: =IFERROR('Data Sheet'!F57,0) -> 34.01 | H47: =IFERROR('Data Sheet'!G57,0) -> 33.1 | I47: =IFERROR('Data Sheet'!H57,0) -> 48.03 | J47: =IFERROR('Data Sheet'!I57,0) -> 48.23 | ... L47: =IFERROR('Data Sheet'!K57,0) -> 92.03
B48: Reserves | C48: =IFERROR('Data Sheet'!B58,0) -> 1175.64 | D48: =IFERROR('Data Sheet'!C58,0) -> 1166.61 | E48: =IFERROR('Data Sheet'!D58,0) -> 1343.51 | F48: =IFERROR('Data Sheet'!E58,0) -> 1270.12 | G48: =IFERROR('Data Sheet'!F58,0) -> 1466.81 | H48: =IFERROR('Data Sheet'!G58,0) -> 1534.49 | I48: =IFERROR('Data Sheet'!H58,0) -> 1666.84 | J48: =IFERROR('Data Sheet'!I58,0) -> 2199.27 | ... L48: =IFERROR('Data Sheet'!K58,0) -> 2469.37
B49: Borrowings | C49: =IFERROR('Data Sheet'!B59,0) -> 1.06 | D49: =IFERROR('Data Sheet'!C59,0) -> 6.34 | E49: =IFERROR('Data Sheet'!D59,0) -> 1.67 | F49: =IFERROR('Data Sheet'!E59,0) -> 156.6 | G49: =IFERROR('Data Sheet'!F59,0) -> 174.73 | H49: =IFERROR('Data Sheet'!G59,0) -> 163.12 | I49: =IFERROR('Data Sheet'!H59,0) -> 193.56 | J49: =IFERROR('Data Sheet'!I59,0) -> 265.74 | ... L49: =IFERROR('Data Sheet'!K59,0) -> 384.96
B50: Other Liabilities | C50: =IFERROR('Data Sheet'!B60,0) -> 181.73 | D50: =IFERROR('Data Sheet'!C60,0) -> 207.8 | E50: =IFERROR('Data Sheet'!D60,0) -> 201.01 | F50: =IFERROR('Data Sheet'!E60,0) -> 260.2 | G50: =IFERROR('Data Sheet'!F60,0) -> 315 | H50: =IFERROR('Data Sheet'!G60,0) -> 324.48 | I50: =IFERROR('Data Sheet'!H60,0) -> 365.47 | J50: =IFERROR('Data Sheet'!I60,0) -> 406.15 | ... L50: =IFERROR('Data Sheet'!K60,0) -> 750.66
B51: Total Liabilities | C51: =IFERROR('Data Sheet'!B61,0) -> 1398.14 | D51: =IFERROR('Data Sheet'!C61,0) -> 1418.89 | E51: =IFERROR('Data Sheet'!D61,0) -> 1583.98 | F51: =IFERROR('Data Sheet'!E61,0) -> 1723.02 | G51: =IFERROR('Data Sheet'!F61,0) -> 1990.55 | H51: =IFERROR('Data Sheet'!G61,0) -> 2055.19 | I51: =IFERROR('Data Sheet'!H61,0) -> 2273.9 | J51: =IFERROR('Data Sheet'!I61,0) -> 2919.39 | ... L51: =IFERROR('Data Sheet'!K61,0) -> 3697.02
B53: Fixed Assets Net Block | C53: =IFERROR('Data Sheet'!B62,0) -> 325.06 | D53: =IFERROR('Data Sheet'!C62,0) -> 343.43 | E53: =IFERROR('Data Sheet'!D62,0) -> 347.91 | F53: =IFERROR('Data Sheet'!E62,0) -> 479.74 | G53: =IFERROR('Data Sheet'!F62,0) -> 728.03 | H53: =IFERROR('Data Sheet'!G62,0) -> 712.56 | I53: =IFERROR('Data Sheet'!H62,0) -> 772.51 | J53: =IFERROR('Data Sheet'!I62,0) -> 842.95 | ... L53: =IFERROR('Data Sheet'!K62,0) -> 1053.94
B54: Capital Work in Progress | C54: =IFERROR('Data Sheet'!B63,0) -> 1.85 | D54: =IFERROR('Data Sheet'!C63,0) -> 0.09 | E54: =IFERROR('Data Sheet'!D63,0) -> 0.17 | F54: =IFERROR('Data Sheet'!E63,0) -> 0.8 | G54: =IFERROR('Data Sheet'!F63,0) -> 0.48 | H54: =IFERROR('Data Sheet'!G63,0) -> 2.17 | I54: =IFERROR('Data Sheet'!H63,0) -> 20.82 | J54: =IFERROR('Data Sheet'!I63,0) -> 0.77 | ... L54: =IFERROR('Data Sheet'!K63,0) -> 4.92
B55: Investments | C55: =IFERROR('Data Sheet'!B64,0) -> 251.64 | D55: =IFERROR('Data Sheet'!C64,0) -> 165.27 | E55: =IFERROR('Data Sheet'!D64,0) -> 286.26 | F55: =IFERROR('Data Sheet'!E64,0) -> 436.79 | G55: =IFERROR('Data Sheet'!F64,0) -> 228.62 | H55: =IFERROR('Data Sheet'!G64,0) -> 195.88 | I55: =IFERROR('Data Sheet'!H64,0) -> 274.51 | J55: =IFERROR('Data Sheet'!I64,0) -> 406.5 | ... L55: =IFERROR('Data Sheet'!K64,0) -> 307.85
B56: Other Assets | C56: =IFERROR('Data Sheet'!B65-SUM('Data Sheet'!B67:B69),0) -> 249.85 | D56: =IFERROR('Data Sheet'!C65-SUM('Data Sheet'!C67:C69),0) -> 236.54 | E56: =IFERROR('Data Sheet'!D65-SUM('Data Sheet'!D67:D69),0) -> 255.14 | F56: =IFERROR('Data Sheet'!E65-SUM('Data Sheet'!E67:E69),0) -> 233.11 | G56: =IFERROR('Data Sheet'!F65-SUM('Data Sheet'!F67:F69),0) -> 249.22 | H56: =IFERROR('Data Sheet'!G65-SUM('Data Sheet'!G67:G69),0) -> 321.15 | I56: =IFERROR('Data Sheet'!H65-SUM('Data Sheet'!H67:H69),0) -> 337.19 | J56: =IFERROR('Data Sheet'!I65-SUM('Data Sheet'!I67:I69),0) -> 480.43 | ... L56: =IFERROR('Data Sheet'!K65-SUM('Data Sheet'!K67:K69),0) -> 925.25
B57: Total Non Current Asset | C57: =IFERROR(SUM(C53:C56),0) -> 828.4 | D57: =IFERROR(SUM(D53:D56),0) -> 745.33 | E57: =IFERROR(SUM(E53:E56),0) -> 889.48 | F57: =IFERROR(SUM(F53:F56),0) -> 1150.44 | G57: =IFERROR(SUM(G53:G56),0) -> 1206.35 | H57: =IFERROR(SUM(H53:H56),0) -> 1231.76 | I57: =IFERROR(SUM(I53:I56),0) -> 1405.03 | J57: =IFERROR(SUM(J53:J56),0) -> 1730.65 | ... L57: =IFERROR(SUM(L53:L56),0) -> 2291.96
B59: Receivables | C59: =IFERROR('Data Sheet'!B67,0) -> 213.83 | D59: =IFERROR('Data Sheet'!C67,0) -> 232.85 | E59: =IFERROR('Data Sheet'!D67,0) -> 242.59 | F59: =IFERROR('Data Sheet'!E67,0) -> 237.78 | G59: =IFERROR('Data Sheet'!F67,0) -> 293.02 | H59: =IFERROR('Data Sheet'!G67,0) -> 329.27 | I59: =IFERROR('Data Sheet'!H67,0) -> 440.49 | J59: =IFERROR('Data Sheet'!I67,0) -> 496 | ... L59: =IFERROR('Data Sheet'!K67,0) -> 666.45
B60: Inventory | C60: =IFERROR('Data Sheet'!B68,0) -> 0.25 | D60: =IFERROR('Data Sheet'!C68,0) -> 0.44 | E60: =IFERROR('Data Sheet'!D68,0) -> 0.36 | F60: =IFERROR('Data Sheet'!E68,0) -> 0.3 | G60: =IFERROR('Data Sheet'!F68,0) -> 0.32 | H60: =IFERROR('Data Sheet'!G68,0) -> 0.52 | I60: =IFERROR('Data Sheet'!H68,0) -> 0.45 | J60: =IFERROR('Data Sheet'!I68,0) -> 0.65 | ... L60: =IFERROR('Data Sheet'!K68,0) -> 0.62
B61: Cash & Bank | C61: =IFERROR('Data Sheet'!B69,0) -> 355.66 | D61: =IFERROR('Data Sheet'!C69,0) -> 440.27 | E61: =IFERROR('Data Sheet'!D69,0) -> 451.55 | F61: =IFERROR('Data Sheet'!E69,0) -> 334.5 | G61: =IFERROR('Data Sheet'!F69,0) -> 490.86 | H61: =IFERROR('Data Sheet'!G69,0) -> 493.64 | I61: =IFERROR('Data Sheet'!H69,0) -> 427.93 | J61: =IFERROR('Data Sheet'!I69,0) -> 692.09 | ... L61: =IFERROR('Data Sheet'!K69,0) -> 737.99
B62: Total Current Asset | C62: =IFERROR(SUM(C59:C61),0) -> 569.74 | D62: =IFERROR(SUM(D59:D61),0) -> 673.56 | E62: =IFERROR(SUM(E59:E61),0) -> 694.5 | F62: =IFERROR(SUM(F59:F61),0) -> 572.58 | G62: =IFERROR(SUM(G59:G61),0) -> 784.2 | H62: =IFERROR(SUM(H59:H61),0) -> 823.43 | I62: =IFERROR(SUM(I59:I61),0) -> 868.87 | J62: =IFERROR(SUM(J59:J61),0) -> 1188.74 | ... L62: =IFERROR(SUM(L59:L61),0) -> 1405.06
B64: Total Asset | C64: =IFERROR((C62+C57),0) -> 1398.14 | D64: =IFERROR((D62+D57),0) -> 1418.89 | E64: =IFERROR((E62+E57),0) -> 1583.98 | F64: =IFERROR((F62+F57),0) -> 1723.02 | G64: =IFERROR((G62+G57),0) -> 1990.55 | H64: =IFERROR((H62+H57),0) -> 2055.19 | I64: =IFERROR((I62+I57),0) -> 2273.9 | J64: =IFERROR((J62+J57),0) -> 2919.39 | ... L64: =IFERROR((L62+L57),0) -> 3697.02
B66: CHECK | C66: =C64=C51 -> TRUE | D66: =D64=D51 -> TRUE | E66: =E64=E51 -> TRUE | F66: =F64=F51 -> TRUE | G66: =G64=G51 -> TRUE | H66: =H64=H51 -> TRUE | I66: =I64=I51 -> TRUE | J66: =J64=J51 -> TRUE | ... L66: =L64=L51 -> TRUE
A68: # | B68: Cash Flow Statement
B69: Operating Activities
B70: Profit from operations | C70: =IFERROR('Cash Flow Data'!E4,0) -> 462 | D70: =IFERROR('Cash Flow Data'!F4,0) -> 402 | E70: =IFERROR('Cash Flow Data'!G4,0) -> 329 | F70: =IFERROR('Cash Flow Data'!H4,0) -> 343 | G70: =IFERROR('Cash Flow Data'!I4,0) -> 458 | H70: =IFERROR('Cash Flow Data'!J4,0) -> 679 | I70: =IFERROR('Cash Flow Data'!K4,0) -> 758 | J70: =IFERROR('Cash Flow Data'!L4,0) -> 826 | ... L70: =IFERROR('Cash Flow Data'!N4,0) -> 1198
B71: Receivables | C71: =IFERROR('Cash Flow Data'!E5,0) -> -33 | D71: =IFERROR('Cash Flow Data'!F5,0) -> -15 | E71: =IFERROR('Cash Flow Data'!G5,0) -> -15 | F71: =IFERROR('Cash Flow Data'!H5,0) -> 10 | G71: =IFERROR('Cash Flow Data'!I5,0) -> -30 | H71: =IFERROR('Cash Flow Data'!J5,0) -> -37 | I71: =IFERROR('Cash Flow Data'!K5,0) -> -112 | J71: =IFERROR('Cash Flow Data'!L5,0) -> -55 | ... L71: =IFERROR('Cash Flow Data'!N5,0) -> -237
B72: Inventory | C72: =IFERROR('Cash Flow Data'!E6,0) -> 0 | D72: =IFERROR('Cash Flow Data'!F6,0) -> 0 | E72: =IFERROR('Cash Flow Data'!G6,0) -> 0 | F72: =IFERROR('Cash Flow Data'!H6,0) -> 0 | G72: =IFERROR('Cash Flow Data'!I6,0) -> 0 | H72: =IFERROR('Cash Flow Data'!J6,0) -> 0 | I72: =IFERROR('Cash Flow Data'!K6,0) -> 0 | J72: =IFERROR('Cash Flow Data'!L6,0) -> 0 | ... L72: =IFERROR('Cash Flow Data'!N6,0) -> 0
B73: Payables | C73: =IFERROR('Cash Flow Data'!E7,0) -> -12 | D73: =IFERROR('Cash Flow Data'!F7,0) -> 18 | E73: =IFERROR('Cash Flow Data'!G7,0) -> -3 | F73: =IFERROR('Cash Flow Data'!H7,0) -> 0 | G73: =IFERROR('Cash Flow Data'!I7,0) -> 7 | H73: =IFERROR('Cash Flow Data'!J7,0) -> 15 | I73: =IFERROR('Cash Flow Data'!K7,0) -> 20 | J73: =IFERROR('Cash Flow Data'!L7,0) -> 11 | ... L73: =IFERROR('Cash Flow Data'!N7,0) -> 53
B74: Loans Advances | C74: =IFERROR('Cash Flow Data'!E8,0) -> 0 | D74: =IFERROR('Cash Flow Data'!F8,0) -> 0 | E74: =IFERROR('Cash Flow Data'!G8,0) -> 0 | F74: =IFERROR('Cash Flow Data'!H8,0) -> 0 | G74: =IFERROR('Cash Flow Data'!I8,0) -> 0 | H74: =IFERROR('Cash Flow Data'!J8,0) -> 0 | I74: =IFERROR('Cash Flow Data'!K8,0) -> 0 | J74: =IFERROR('Cash Flow Data'!L8,0) -> 0 | ... L74: =IFERROR('Cash Flow Data'!N8,0) -> 0
B75: Other WC items | C75: =IFERROR('Cash Flow Data'!E9,0) -> -3 | D75: =IFERROR('Cash Flow Data'!F9,0) -> -6 | E75: =IFERROR('Cash Flow Data'!G9,0) -> -12 | F75: =IFERROR('Cash Flow Data'!H9,0) -> 39 | G75: =IFERROR('Cash Flow Data'!I9,0) -> 31 | H75: =IFERROR('Cash Flow Data'!J9,0) -> -48 | I75: =IFERROR('Cash Flow Data'!K9,0) -> 5 | J75: =IFERROR('Cash Flow Data'!L9,0) -> -84 | ... L75: =IFERROR('Cash Flow Data'!N9,0) -> 85
B76: Working capital changes | C76: =IFERROR('Cash Flow Data'!E10,0) -> -47 | D76: =IFERROR('Cash Flow Data'!F10,0) -> -3 | E76: =IFERROR('Cash Flow Data'!G10,0) -> -30 | F76: =IFERROR('Cash Flow Data'!H10,0) -> 49 | G76: =IFERROR('Cash Flow Data'!I10,0) -> 7 | H76: =IFERROR('Cash Flow Data'!J10,0) -> -70 | I76: =IFERROR('Cash Flow Data'!K10,0) -> -87 | J76: =IFERROR('Cash Flow Data'!L10,0) -> -128 | ... L76: =IFERROR('Cash Flow Data'!N10,0) -> -99
B77: Direct taxes | C77: =IFERROR('Cash Flow Data'!E11,0) -> 0 | D77: =IFERROR('Cash Flow Data'!F11,0) -> 0 | E77: =IFERROR('Cash Flow Data'!G11,0) -> 0 | F77: =IFERROR('Cash Flow Data'!H11,0) -> 0 | G77: =IFERROR('Cash Flow Data'!I11,0) -> 0 | H77: =IFERROR('Cash Flow Data'!J11,0) -> -164 | I77: =IFERROR('Cash Flow Data'!K11,0) -> -178 | J77: =IFERROR('Cash Flow Data'!L11,0) -> -172 | ... L77: =IFERROR('Cash Flow Data'!N11,0) -> -225
B78: Other operating items | C78: =IFERROR('Cash Flow Data'!E12,0) -> -103 | D78: =IFERROR('Cash Flow Data'!F12,0) -> -95 | E78: =IFERROR('Cash Flow Data'!G12,0) -> -93 | F78: =IFERROR('Cash Flow Data'!H12,0) -> -59 | G78: =IFERROR('Cash Flow Data'!I12,0) -> -100 | H78: =IFERROR('Cash Flow Data'!J12,0) -> 0 | I78: =IFERROR('Cash Flow Data'!K12,0) -> 0 | J78: =IFERROR('Cash Flow Data'!L12,0) -> 0 | ... L78: =IFERROR('Cash Flow Data'!N12,0) -> 0
B79: Cash from Operating Activities | C79: =IFERROR(SUM(C70,C76,C77,C78),0) -> 312 | D79: =IFERROR(SUM(D70,D76,D77,D78),0) -> 304 | E79: =IFERROR(SUM(E70,E76,E77,E78),0) -> 206 | F79: =IFERROR(SUM(F70,F76,F77,F78),0) -> 333 | G79: =IFERROR(SUM(G70,G76,G77,G78),0) -> 365 | H79: =IFERROR(SUM(H70,H76,H77,H78),0) -> 445 | I79: =IFERROR(SUM(I70,I76,I77,I78),0) -> 493 | J79: =IFERROR(SUM(J70,J76,J77,J78),0) -> 526 | ... L79: =IFERROR(SUM(L70,L76,L77,L78),0) -> 874
B81: Investing Activities
B82: Fixed assets purchased | C82: =IFERROR('Cash Flow Data'!E14,0) -> -30 | D82: =IFERROR('Cash Flow Data'!F14,0) -> -42 | E82: =IFERROR('Cash Flow Data'!G14,0) -> -52 | F82: =IFERROR('Cash Flow Data'!H14,0) -> -34 | G82: =IFERROR('Cash Flow Data'!I14,0) -> -39 | H82: =IFERROR('Cash Flow Data'!J14,0) -> -61 | I82: =IFERROR('Cash Flow Data'!K14,0) -> -91 | J82: =IFERROR('Cash Flow Data'!L14,0) -> -67 | ... L82: =IFERROR('Cash Flow Data'!N14,0) -> -119
B83: Fixed assets sold | C83: =IFERROR('Cash Flow Data'!E15,0) -> 0 | D83: =IFERROR('Cash Flow Data'!F15,0) -> 0 | E83: =IFERROR('Cash Flow Data'!G15,0) -> 0 | F83: =IFERROR('Cash Flow Data'!H15,0) -> 1 | G83: =IFERROR('Cash Flow Data'!I15,0) -> 0 | H83: =IFERROR('Cash Flow Data'!J15,0) -> 0 | I83: =IFERROR('Cash Flow Data'!K15,0) -> 1 | J83: =IFERROR('Cash Flow Data'!L15,0) -> 3 | ... L83: =IFERROR('Cash Flow Data'!N15,0) -> 1
B84: Investments purchased | C84: =IFERROR('Cash Flow Data'!E16,0) -> -803 | D84: =IFERROR('Cash Flow Data'!F16,0) -> -844 | E84: =IFERROR('Cash Flow Data'!G16,0) -> -1363 | F84: =IFERROR('Cash Flow Data'!H16,0) -> -1196 | G84: =IFERROR('Cash Flow Data'!I16,0) -> -919 | H84: =IFERROR('Cash Flow Data'!J16,0) -> -1158 | I84: =IFERROR('Cash Flow Data'!K16,0) -> -1612 | J84: =IFERROR('Cash Flow Data'!L16,0) -> -1662 | ... L84: =IFERROR('Cash Flow Data'!N16,0) -> -2187
B85: Investments sold | C85: =IFERROR('Cash Flow Data'!E17,0) -> 773 | D85: =IFERROR('Cash Flow Data'!F17,0) -> 930 | E85: =IFERROR('Cash Flow Data'!G17,0) -> 1242 | F85: =IFERROR('Cash Flow Data'!H17,0) -> 1059 | G85: =IFERROR('Cash Flow Data'!I17,0) -> 1143 | H85: =IFERROR('Cash Flow Data'!J17,0) -> 1197 | I85: =IFERROR('Cash Flow Data'!K17,0) -> 1548 | J85: =IFERROR('Cash Flow Data'!L17,0) -> 1546 | ... L85: =IFERROR('Cash Flow Data'!N17,0) -> 2198
B86: Interest received | C86: =IFERROR('Cash Flow Data'!E18,0) -> 7 | D86: =IFERROR('Cash Flow Data'!F18,0) -> 14 | E86: =IFERROR('Cash Flow Data'!G18,0) -> 19 | F86: =IFERROR('Cash Flow Data'!H18,0) -> 21 | G86: =IFERROR('Cash Flow Data'!I18,0) -> 13 | H86: =IFERROR('Cash Flow Data'!J18,0) -> 4 | I86: =IFERROR('Cash Flow Data'!K18,0) -> 6 | J86: =IFERROR('Cash Flow Data'!L18,0) -> 21 | ... L86: =IFERROR('Cash Flow Data'!N18,0) -> 30
B87: Dividends received | C87: =IFERROR('Cash Flow Data'!E19,0) -> 13 | D87: =IFERROR('Cash Flow Data'!F19,0) -> 15 | E87: =IFERROR('Cash Flow Data'!G19,0) -> 10 | F87: =IFERROR('Cash Flow Data'!H19,0) -> 7 | G87: =IFERROR('Cash Flow Data'!I19,0) -> 0 | H87: =IFERROR('Cash Flow Data'!J19,0) -> 0 | I87: =IFERROR('Cash Flow Data'!K19,0) -> 0 | J87: =IFERROR('Cash Flow Data'!L19,0) -> 0 | ... L87: =IFERROR('Cash Flow Data'!N19,0) -> 3
B88: Acquisition of companies | C88: =IFERROR('Cash Flow Data'!E20,0) -> 0 | D88: =IFERROR('Cash Flow Data'!F20,0) -> 0 | E88: =IFERROR('Cash Flow Data'!G20,0) -> 0 | F88: =IFERROR('Cash Flow Data'!H20,0) -> 0 | G88: =IFERROR('Cash Flow Data'!I20,0) -> 0 | H88: =IFERROR('Cash Flow Data'!J20,0) -> 0 | I88: =IFERROR('Cash Flow Data'!K20,0) -> 0 | J88: =IFERROR('Cash Flow Data'!L20,0) -> 0 | ... L88: =IFERROR('Cash Flow Data'!N20,0) -> 0
B89: Other investing items | C89: =IFERROR('Cash Flow Data'!E21,0) -> -136 | D89: =IFERROR('Cash Flow Data'!F21,0) -> -47 | E89: =IFERROR('Cash Flow Data'!G21,0) -> -85 | F89: =IFERROR('Cash Flow Data'!H21,0) -> 167 | G89: =IFERROR('Cash Flow Data'!I21,0) -> -200 | H89: =IFERROR('Cash Flow Data'!J21,0) -> 61 | I89: =IFERROR('Cash Flow Data'!K21,0) -> 93 | J89: =IFERROR('Cash Flow Data'!L21,0) -> -324 | ... L89: =IFERROR('Cash Flow Data'!N21,0) -> -67
B90: Cash from Investing Activities | C90: =IFERROR(SUM(C82:C89),0) -> -176 | D90: =IFERROR(SUM(D82:D89),0) -> 26 | E90: =IFERROR(SUM(E82:E89),0) -> -229 | F90: =IFERROR(SUM(F82:F89),0) -> 25 | G90: =IFERROR(SUM(G82:G89),0) -> -2 | H90: =IFERROR(SUM(H82:H89),0) -> 43 | I90: =IFERROR(SUM(I82:I89),0) -> -55 | J90: =IFERROR(SUM(J82:J89),0) -> -483 | ... L90: =IFERROR(SUM(L82:L89),0) -> -141
B92: Financing Activities
B93: Proceeds from shares | C93: =IFERROR('Cash Flow Data'!E23,0) -> 8 | D93: =IFERROR('Cash Flow Data'!F23,0) -> 9 | E93: =IFERROR('Cash Flow Data'!G23,0) -> 5 | F93: =IFERROR('Cash Flow Data'!H23,0) -> 1 | G93: =IFERROR('Cash Flow Data'!I23,0) -> 0 | H93: =IFERROR('Cash Flow Data'!J23,0) -> 0 | I93: =IFERROR('Cash Flow Data'!K23,0) -> 0 | J93: =IFERROR('Cash Flow Data'!L23,0) -> 0 | ... L93: =IFERROR('Cash Flow Data'!N23,0) -> 32
B94: Proceeds from borrowings | C94: =IFERROR('Cash Flow Data'!E24,0) -> 0 | D94: =IFERROR('Cash Flow Data'!F24,0) -> 5 | E94: =IFERROR('Cash Flow Data'!G24,0) -> 0 | F94: =IFERROR('Cash Flow Data'!H24,0) -> 0 | G94: =IFERROR('Cash Flow Data'!I24,0) -> 0 | H94: =IFERROR('Cash Flow Data'!J24,0) -> 0 | I94: =IFERROR('Cash Flow Data'!K24,0) -> 1 | J94: =IFERROR('Cash Flow Data'!L24,0) -> 0 | ... L94: =IFERROR('Cash Flow Data'!N24,0) -> 0
B95: Repayment of borrowings | C95: =IFERROR('Cash Flow Data'!E25,0) -> -2 | D95: =IFERROR('Cash Flow Data'!F25,0) -> 0 | E95: =IFERROR('Cash Flow Data'!G25,0) -> -5 | F95: =IFERROR('Cash Flow Data'!H25,0) -> -1 | G95: =IFERROR('Cash Flow Data'!I25,0) -> -1 | H95: =IFERROR('Cash Flow Data'!J25,0) -> 0 | I95: =IFERROR('Cash Flow Data'!K25,0) -> 0 | J95: =IFERROR('Cash Flow Data'!L25,0) -> -1 | ... L95: =IFERROR('Cash Flow Data'!N25,0) -> 0
B96: Proceeds from deposits | C96: =IFERROR('Cash Flow Data'!E26,0) -> 0 | D96: =IFERROR('Cash Flow Data'!F26,0) -> 0 | E96: =IFERROR('Cash Flow Data'!G26,0) -> 0 | F96: =IFERROR('Cash Flow Data'!H26,0) -> 0 | G96: =IFERROR('Cash Flow Data'!I26,0) -> 0 | H96: =IFERROR('Cash Flow Data'!J26,0) -> 0 | I96: =IFERROR('Cash Flow Data'!K26,0) -> 0 | J96: =IFERROR('Cash Flow Data'!L26,0) -> 0 | ... L96: =IFERROR('Cash Flow Data'!N26,0) -> 0
B97: Interest paid fin | C97: =IFERROR('Cash Flow Data'!E27,0) -> 0 | D97: =IFERROR('Cash Flow Data'!F27,0) -> 0 | E97: =IFERROR('Cash Flow Data'!G27,0) -> 0 | F97: =IFERROR('Cash Flow Data'!H27,0) -> -19 | G97: =IFERROR('Cash Flow Data'!I27,0) -> -20 | H97: =IFERROR('Cash Flow Data'!J27,0) -> -22 | I97: =IFERROR('Cash Flow Data'!K27,0) -> -21 | J97: =IFERROR('Cash Flow Data'!L27,0) -> -23 | ... L97: =IFERROR('Cash Flow Data'!N27,0) -> -43
B98: Dividends paid | C98: =IFERROR('Cash Flow Data'!E28,0) -> -4 | D98: =IFERROR('Cash Flow Data'!F28,0) -> -4 | E98: =IFERROR('Cash Flow Data'!G28,0) -> -4 | F98: =IFERROR('Cash Flow Data'!H28,0) -> -4 | G98: =IFERROR('Cash Flow Data'!I28,0) -> -3 | H98: =IFERROR('Cash Flow Data'!J28,0) -> -3 | I98: =IFERROR('Cash Flow Data'!K28,0) -> -3 | J98: =IFERROR('Cash Flow Data'!L28,0) -> -5 | ... L98: =IFERROR('Cash Flow Data'!N28,0) -> -5
B99: Financial liabilities | C99: =IFERROR('Cash Flow Data'!E29,0) -> 0 | D99: =IFERROR('Cash Flow Data'!F29,0) -> 0 | E99: =IFERROR('Cash Flow Data'!G29,0) -> 0 | F99: =IFERROR('Cash Flow Data'!H29,0) -> -26 | G99: =IFERROR('Cash Flow Data'!I29,0) -> -29 | H99: =IFERROR('Cash Flow Data'!J29,0) -> -36 | I99: =IFERROR('Cash Flow Data'!K29,0) -> -39 | J99: =IFERROR('Cash Flow Data'!L29,0) -> -46 | ... L99: =IFERROR('Cash Flow Data'!N29,0) -> -54
B100: Application money refund | C100: =IFERROR('Cash Flow Data'!E30,0) -> 0 | D100: =IFERROR('Cash Flow Data'!F30,0) -> 0 | E100: =IFERROR('Cash Flow Data'!G30,0) -> 0 | F100: =IFERROR('Cash Flow Data'!H30,0) -> 0 | G100: =IFERROR('Cash Flow Data'!I30,0) -> 0 | H100: =IFERROR('Cash Flow Data'!J30,0) -> 28 | I100: =IFERROR('Cash Flow Data'!K30,0) -> 22 | J100: =IFERROR('Cash Flow Data'!L30,0) -> 15 | ... L100: =IFERROR('Cash Flow Data'!N30,0) -> 0
B101: Other financing items | C101: =IFERROR('Cash Flow Data'!E31,0) -> -247 | D101: =IFERROR('Cash Flow Data'!F31,0) -> -313 | E101: =IFERROR('Cash Flow Data'!G31,0) -> -51 | F101: =IFERROR('Cash Flow Data'!H31,0) -> -260 | G101: =IFERROR('Cash Flow Data'!I31,0) -> -135 | H101: =IFERROR('Cash Flow Data'!J31,0) -> -383 | I101: =IFERROR('Cash Flow Data'!K31,0) -> -399 | J101: =IFERROR('Cash Flow Data'!L31,0) -> -46 | ... L101: =IFERROR('Cash Flow Data'!N31,0) -> -552
B102: Cash from Financing Activities | C102: =IFERROR(SUM(C93:C101),0) -> -245 | D102: =IFERROR(SUM(D93:D101),0) -> -303 | E102: =IFERROR(SUM(E93:E101),0) -> -55 | F102: =IFERROR(SUM(F93:F101),0) -> -309 | G102: =IFERROR(SUM(G93:G101),0) -> -188 | H102: =IFERROR(SUM(H93:H101),0) -> -416 | I102: =IFERROR(SUM(I93:I101),0) -> -439 | J102: =IFERROR(SUM(J93:J101),0) -> -106 | ... L102: =IFERROR(SUM(L93:L101),0) -> -622
B104: Net Cash Flow | C104: =IFERROR(SUM(C102,C90,C79),0) -> -109 | D104: =IFERROR(SUM(D102,D90,D79),0) -> 27 | E104: =IFERROR(SUM(E102,E90,E79),0) -> -78 | F104: =IFERROR(SUM(F102,F90,F79),0) -> 49 | G104: =IFERROR(SUM(G102,G90,G79),0) -> 175 | H104: =IFERROR(SUM(H102,H90,H79),0) -> 72 | I104: =IFERROR(SUM(I102,I90,I79),0) -> -1 | J104: =IFERROR(SUM(J102,J90,J79),0) -> -63 | ... L104: =IFERROR(SUM(L102,L90,L79),0) -> 111

Sheet Data Sheet
A1: COMPANY NAME | B1: ECLERX SERVICES LTD | E1: =IF(B2<>B3, "A NEW VERSION OF THE WORKSHEET IS AVAILABLE", "")
A2: LATEST VERSION | B2: 2.1 | E2: PLEASE DO NOT MAKE ANY CHANGES TO THIS SHEET
A3: CURRENT VERSION | B3: 2.1
A5: META
A6: Number of shares | B6: =IF(B9>0, B9/B8, 0) -> 9.4050712
A7: Face Value | B7: 10
A8: Current Price | B8: 1979.8
A9: Market Capitalization | B9: 18620.16
A15: PROFIT & LOSS
A16: Report Date | B16: 42825 | C16: 43190 | D16: 43555 | E16: 43921 | F16: 44286 | G16: 44651 | H16: 45016 | I16: 45382 | J16: 45747 | K16: 46112
A17: Sales | B17: 1330.03 | C17: 1365.06 | D17: 1430.59 | E17: 1437.57 | F17: 1564.49 | G17: 2160.35 | H17: 2647.9 | I17: 2925.54 | J17: 3365.87 | K17: 4117.03
A18: Raw Material Cost
A19: Change in Inventory
A20: Power and Fuel | B20: 10.02 | C20: 9.37 | D20: 10.64 | E20: 9.36 | F20: 8.75 | G20: 9.61 | H20: 13.38 | I20: 16.27 | J20: 19.82
A21: Other Mfr. Exp | B21: 63.84 | C21: 79.7 | D21: 82.25 | E21: 67.07 | F21: 61.84 | G21: 122.23 | H21: 147.29 | I21: 112.27 | J21: 146.05
A22: Employee Cost | B22: 593.61 | C22: 692.54 | D22: 787.07 | E22: 854.45 | F22: 885.56 | G22: 1195.76 | H22: 1509.76 | I22: 1738.62 | J22: 2065.92 | K22: 2524.53
A23: Selling and admin | B23: 183.77 | C23: 204.89 | D23: 230.33 | E23: 169.91 | F23: 136.48 | G23: 164.36 | H23: 246.33 | I23: 271.87 | J23: 300.43
A24: Other Expenses | B24: 17.52 | C24: 11.06 | D24: 11.45 | E24: 10.63 | F24: 22.33 | G24: 6.34 | H24: 7.86 | I24: 10.75 | J24: 24.34 | K24: 541.05
A25: Other Income | B25: 27.93 | C25: 61.43 | D25: 48.59 | E25: 45.42 | F25: 34.1 | G25: 24.39 | H25: 65.91 | I25: 63.8 | J25: 86.53 | K25: 101.18
A26: Depreciation | B26: 51.8 | C26: 48.24 | D26: 44.69 | E26: 70.9 | F26: 81.59 | G26: 103.19 | H26: 114.01 | I26: 125.77 | J26: 141.19 | K26: 175.37
A27: Interest | B27: 1.57 | C27: 1.17 | D27: 1.27 | E27: 20.16 | F27: 21.42 | G27: 22.76 | H27: 22.19 | I27: 24.45 | J27: 36.12 | K27: 42.14
A28: Profit before tax | B28: 435.83 | C28: 379.52 | D28: 311.48 | E28: 280.51 | F28: 380.62 | G28: 560.49 | H28: 652.99 | I28: 689.34 | J28: 718.53 | K28: 935.12
A29: Tax | B29: 81.91 | C29: 89.58 | D29: 83.17 | E29: 71.55 | F29: 97.8 | G29: 142.73 | H29: 163.8 | I29: 177.61 | J29: 177.27 | K29: 228.65
A30: Net profit | B30: 354.03 | C30: 289.98 | D30: 228.26 | E30: 208.98 | F30: 282.56 | G30: 417.4 | H30: 488.82 | I30: 511.46 | J30: 541.09 | K30: 706.21
A31: Dividend Amount | B31: 3.97 | C31: 3.81 | D31: 3.78 | E31: 3.61 | F31: 3.4 | G31: 3.31 | H31: 4.8 | I31: 4.82 | J31: 4.7 | K31: 9.2
A40: Quarters
A41: Report Date | B41: 45291 | C41: 45382 | D41: 45473 | E41: 45565 | F41: 45657 | G41: 45747 | H41: 45838 | I41: 45930 | J41: 46022 | K41: 46112
A42: Sales | B42: 752.76 | C42: 766.53 | D42: 781.92 | E42: 831.84 | F42: 853.82 | G42: 898.29 | H42: 934.56 | I42: 1004.85 | J42: 1070.33 | K42: 1107.29
A43: Expenses | B43: 545.53 | C43: 571 | D43: 615.55 | E43: 616.18 | F43: 646.34 | G43: 679.71 | H43: 714.03 | I43: 733.78 | J43: 794.07 | K43: 823.7
A44: Other Income | B44: 18.95 | C44: 23.05 | D44: 20.91 | E44: 13.12 | F44: 20.58 | G44: 31.92 | H44: 14.11 | I44: 27.24 | J44: 30.07 | K44: 29.76
A45: Depreciation | B45: 33.53 | C45: 33.53 | D45: 31.65 | E45: 32.8 | F45: 35.78 | G45: 40.96 | H45: 36.9 | I45: 42.5 | J45: 46.31 | K45: 49.66
A46: Interest | B46: 5.86 | C46: 5.58 | D46: 7.72 | E46: 8.12 | F46: 8.28 | G46: 10.78 | H46: 9.69 | I46: 10.8 | J46: 9.91 | K46: 11.74
A47: Profit before tax | B47: 186.79 | C47: 179.47 | D47: 147.91 | E47: 187.86 | F47: 184 | G47: 198.76 | H47: 188.05 | I47: 245.01 | J47: 250.11 | K47: 251.95
A48: Tax | B48: 47.73 | C48: 49.58 | D48: 35.87 | E48: 48.36 | F48: 46.8 | G48: 46.24 | H48: 46.5 | I48: 61.54 | J48: 58.3 | K48: 62.3
A49: Net profit | B49: 138.63 | C49: 130.53 | D49: 111.61 | E49: 140.25 | F49: 137.07 | G49: 152.16 | H49: 141.68 | I49: 183.19 | J49: 191.98 | K49: 189.36
A50: Operating Profit | B50: 207.23 | C50: 195.53 | D50: 166.37 | E50: 215.66 | F50: 207.48 | G50: 218.58 | H50: 220.53 | I50: 271.07 | J50: 276.26 | K50: 283.59
A55: BALANCE SHEET
A56: Report Date | B56: 42825 | C56: 43190 | D56: 43555 | E56: 43921 | F56: 44286 | G56: 44651 | H56: 45016 | I56: 45382 | J56: 45747 | K56: 46112
A57: Equity Share Capital | B57: 39.71 | C57: 38.14 | D57: 37.79 | E57: 36.1 | F57: 34.01 | G57: 33.1 | H57: 48.03 | I57: 48.23 | J57: 46.96 | K57: 92.03
A58: Reserves | B58: 1175.64 | C58: 1166.61 | D58: 1343.51 | E58: 1270.12 | F58: 1466.81 | G58: 1534.49 | H58: 1666.84 | I58: 2199.27 | J58: 2258.8 | K58: 2469.37
A59: Borrowings | B59: 1.06 | C59: 6.34 | D59: 1.67 | E59: 156.6 | F59: 174.73 | G59: 163.12 | H59: 193.56 | I59: 265.74 | J59: 358.13 | K59: 384.96
A60: Other Liabilities | B60: 181.73 | C60: 207.8 | D60: 201.01 | E60: 260.2 | F60: 315 | G60: 324.48 | H60: 365.47 | I60: 406.15 | J60: 475.04 | K60: 750.66
A61: Total | B61: 1398.14 | C61: 1418.89 | D61: 1583.98 | E61: 1723.02 | F61: 1990.55 | G61: 2055.19 | H61: 2273.9 | I61: 2919.39 | J61: 3138.93 | K61: 3697.02
A62: Net Block | B62: 325.06 | C62: 343.43 | D62: 347.91 | E62: 479.74 | F62: 728.03 | G62: 712.56 | H62: 772.51 | I62: 842.95 | J62: 973.92 | K62: 1053.94
A63: Capital Work in Progress | B63: 1.85 | C63: 0.09 | D63: 0.17 | E63: 0.8 | F63: 0.48 | G63: 2.17 | H63: 20.82 | I63: 0.77 | J63: 0.19 | K63: 4.92
A64: Investments | B64: 251.64 | C64: 165.27 | D64: 286.26 | E64: 436.79 | F64: 228.62 | G64: 195.88 | H64: 274.51 | I64: 406.5 | J64: 309.02 | K64: 307.85
A65: Other Assets | B65: 819.59 | C65: 910.1 | D65: 949.64 | E65: 805.69 | F65: 1033.42 | G65: 1144.58 | H65: 1206.06 | I65: 1669.17 | J65: 1855.8 | K65: 2330.31
A66: Total | B66: 1398.14 | C66: 1418.89 | D66: 1583.98 | E66: 1723.02 | F66: 1990.55 | G66: 2055.19 | H66: 2273.9 | I66: 2919.39 | J66: 3138.93 | K66: 3697.02
A67: Receivables | B67: 213.83 | C67: 232.85 | D67: 242.59 | E67: 237.78 | F67: 293.02 | G67: 329.27 | H67: 440.49 | I67: 496 | J67: 789.88 | K67: 666.45
... A69: Cash & Bank | B69: 355.66 | C69: 440.27 | D69: 451.55 | E69: 334.5 | F69: 490.86 | G69: 493.64 | H69: 427.93 | I69: 692.09 | J69: 739.13 | K69: 737.99
A70: No. of Equity Shares | B70: 39709058 | C70: 38141422 | D70: 37790235 | E70: 36099796 | F70: 34005981 | G70: 33098094 | H70: 48033979 | I70: 48232242 | J70: 46960349
A71: New Bonus Shares
A72: Face value | B72: 10 | C72: 10 | D72: 10 | E72: 10 | F72: 10 | G72: 10 | H72: 10 | I72: 10 | J72: 10 | K72: 10
A80: CASH FLOW:
A81: Report Date | B81: 42825 | C81: 43190 | D81: 43555 | E81: 43921 | F81: 44286 | G81: 44651 | H81: 45016 | I81: 45382 | J81: 45747 | K81: 46112
A82: Cash from Operating Activity | B82: 312.43 | C82: 305 | D82: 206.16 | E82: 332.8 | F82: 364.57 | G82: 443.96 | H82: 492.57 | I82: 525.89 | J82: 654.62 | K82: 873.47
A83: Cash from Investing Activity | B83: -175.38 | C83: 26.31 | D83: -229.69 | E83: 24.38 | F83: -1.8 | G83: 43.66 | H83: -54.8 | I83: -483.44 | J83: 142.73 | K83: -140.82
A84: Cash from Financing Activity | B84: -245.29 | C84: -303.51 | D84: -53.87 | E84: -308.24 | F84: -188.31 | G84: -416.34 | H84: -440.07 | I84: -106.51 | J84: -609.6 | K84: -621.57
A85: Net Cash Flow | B85: -108.25 | C85: 27.8 | D85: -77.41 | E85: 48.94 | F85: 174.46 | G85: 71.28 | H85: -2.3 | I85: -64.05 | J85: 187.74 | K85: 111.08
A90: PRICE: | B90: 470.17 | C90: 400.5 | D90: 382.55 | E90: 121.8 | F90: 367.67 | G90: 790.4 | H90: 645.2 | I90: 1183.65 | J90: 1388.5 | K90: 1387.2
A92: DERIVED:
A93: Adjusted Equity Shares in Cr | B93: 11.94 | C93: 11.6 | D93: 11.61 | E93: 11.1 | F93: 10.47 | G93: 10.16 | H93: 9.81 | I93: 9.81 | J93: 9.53 | K93: 9.41

Sheet Cash Flow Data
C2: 42064 | D2: 42430 | E2: 42795 | F2: 43160 | G2: 43525 | H2: 43891 | I2: 44256 | J2: 44621 | K2: 44986 | L2: 45352 | M2: 45717 | N2: 46082
B3: Cash from Operating Activity - | C3: 243 | D3: 418 | E3: 312 | F3: 305 | G3: 206 | H3: 333 | I3: 365 | J3: 444 | K3: 493 | L3: 526 | M3: 655 | N3: 873
B4: Profit from operations | C4: 325 | D4: 514 | E4: 462 | F4: 402 | G4: 329 | H4: 343 | I4: 458 | J4: 679 | K4: 758 | L4: 826 | M4: 901 | N4: 1198
B5: Receivables | C5: -26 | D5: -63 | E5: -33 | F5: -15 | G5: -15 | H5: 10 | I5: -30 | J5: -37 | K5: -112 | L5: -55 | M5: -93 | N5: -237
B6: Inventory | C6: 0 | D6: 0 | E6: 0 | F6: 0 | G6: 0 | H6: 0 | I6: 0 | J6: 0 | K6: 0 | L6: 0 | M6: 0 | N6: 0
B7: Payables | C7: 1 | D7: 32 | E7: -12 | F7: 18 | G7: -3 | H7: 0 | I7: 7 | J7: 15 | K7: 20 | L7: 11 | M7: 21 | N7: 53
B8: Loans Advances | C8: -8 | D8: 0 | E8: 0 | F8: 0 | G8: 0 | H8: 0 | I8: 0 | J8: 0 | K8: 0 | L8: 0 | M8: 0 | N8: 0
B9: Other WC items | C9: 19 | D9: 48 | E9: -3 | F9: -6 | G9: -12 | H9: 39 | I9: 31 | J9: -48 | K9: 5 | L9: -84 | M9: -11 | N9: 85
B10: Working capital changes | C10: -15 | D10: 16 | E10: -47 | F10: -3 | G10: -30 | H10: 49 | I10: 7 | J10: -70 | K10: -87 | L10: -128 | M10: -82 | N10: -99
B11: Direct taxes | C11: -68 | D11: 0 | E11: 0 | F11: 0 | G11: 0 | H11: 0 | I11: 0 | J11: -164 | K11: -178 | L11: -172 | M11: -164 | N11: -225
B12: Other operating items | C12: 0 | D12: -113 | E12: -103 | F12: -95 | G12: -93 | H12: -59 | I12: -100 | J12: 0 | K12: 0 | L12: 0 | M12: 0 | N12: 0
B13: Cash from Investing Activity - | C13: -62 | D13: -167 | E13: -175 | F13: 26 | G13: -230 | H13: 24 | I13: -2 | J13: 44 | K13: -55 | L13: -483 | M13: 143 | N13: -141
B14: Fixed assets purchased | C14: -61 | D14: -53 | E14: -30 | F14: -42 | G14: -52 | H14: -34 | I14: -39 | J14: -61 | K14: -91 | L14: -67 | M14: -121 | N14: -119
... B34: CFO/OP | C34: 0.98 | D34: 0.87 | E34: 0.68 | F34: 0.83 | G34: 0.67 | H34: 1.02 | I34: 0.81 | J34: 0.92 | K34: 0.93 | L34: 0.9 | M34: 1.01 | N34: 1.04
