Workbook
Name UPDATE: 'Data Sheet'!$E$1

Sheet HistoricalFS
B2: ="Historical Statement - " & 'Data Sheet'!B1 -> Historical Statement - HINDUSTAN UNILEVER LTD
B3: Years | C3: =IFERROR('Data Sheet'!B16,0) -> 42825 | D3: =IFERROR('Data Sheet'!C16,0) -> 43190 | E3: =IFERROR('Data Sheet'!D16,0) -> 43555 | F3: =IFERROR('Data Sheet'!E16,0) -> 43921 | G3: =IFERROR('Data Sheet'!F16,0) -> 44286 | H3: =IFERROR('Data Sheet'!G16,0) -> 44651 | I3: =IFERROR('Data Sheet'!H16,0) -> 45016 | J3: =IFERROR('Data Sheet'!I16,0) -> 45382 | ... L3: =IFERROR('Data Sheet'!K16,0) -> 46112 | M3: LTM
A5: # | B5: Income Statement
B6: Sales | C6: =IFERROR('Data Sheet'!B17,0) -> 33162 | D6: =IFERROR('Data Sheet'!C17,0) -> 35545 | E6: =IFERROR('Data Sheet'!D17,0) -> 39310 | F6: =IFERROR('Data Sheet'!E17,0) -> 39783 | G6: =IFERROR('Data Sheet'!F17,0) -> 47028 | H6: =IFERROR('Data Sheet'!G17,0) -> 52446 | I6: =IFERROR('Data Sheet'!H17,0) -> 60580 | J6: =IFERROR('Data Sheet'!I17,0) -> 61896 | ... L6: =IFERROR('Data Sheet'!K17,0) -> 64468 | M6: =IFERROR(SUM('Data Sheet'!H42:K42),0) -> 65225
B7: Sales Growth | C7: - | D7: =IFERROR(D6/C6-1,0) -> 0.071859357 | E7: =IFERROR(E6/D6-1,0) -> 0.10592207 | F7: =IFERROR(F6/E6-1,0) -> 0.012032562 | G7: =IFERROR(G6/F6-1,0) -> 0.18211296 | H7: =IFERROR(H6/G6-1,0) -> 0.11520796 | I7: =IFERROR(I6/H6-1,0) -> 0.15509286 | J7: =IFERROR(J6/I6-1,0) -> 0.021723341 | K7: =IFERROR(K6/J6-1,0) -> -0.0091766835 | ... M7: =IFERROR(M6/L6-1,0) -> 0.01174226
B9: COGS | C9: =IFERROR(SUM('Data Sheet'!B18:B21),0) -> 16644 | D9: =IFERROR(SUM('Data Sheet'!C18:C21),0) -> 17598 | E9: =IFERROR(SUM('Data Sheet'!D18:D21),0) -> 19182 | F9: =IFERROR(SUM('Data Sheet'!E18:E21),0) -> 19010 | G9: =IFERROR(SUM('Data Sheet'!F18:F21),0) -> 23753 | H9: =IFERROR(SUM('Data Sheet'!G18:G21),0) -> 26565 | I9: =IFERROR(SUM('Data Sheet'!H18:H21),0) -> 32677 | J9: =IFERROR(SUM('Data Sheet'!I18:I21),0) -> 30664 | ... M9: =IFERROR(SUM('Data Sheet'!L18:L21),0) -> 0
B10: COGS % Sales | C10: =IFERROR(C9/C6,0) -> 0.50189976 | D10: =IFERROR(D9/D6,0) -> 0.49509073 | E10: =IFERROR(E9/E6,0) -> 0.48796744 | F10: =IFERROR(F9/F6,0) -> 0.47784229 | G10: =IFERROR(G9/G6,0) -> 0.50508208 | H10: =IFERROR(H9/H6,0) -> 0.50652099 | I10: =IFERROR(I9/I6,0) -> 0.53940244 | J10: =IFERROR(J9/J6,0) -> 0.49541166 | ... M10: =IFERROR(M9/M6,0) -> 0
B12: Gross Profit | C12: =IFERROR(C6-C9,0) -> 16518 | D12: =IFERROR(D6-D9,0) -> 17947 | E12: =IFERROR(E6-E9,0) -> 20128 | F12: =IFERROR(F6-F9,0) -> 20773 | G12: =IFERROR(G6-G9,0) -> 23275 | H12: =IFERROR(H6-H9,0) -> 25881 | I12: =IFERROR(I6-I9,0) -> 27903 | J12: =IFERROR(J6-J9,0) -> 31232 | ... M12: =IFERROR(M6-M9,0) -> 65225
B13: Gross Margins | C13: =IFERROR(C12/C6,0) -> 0.49810024 | D13: =IFERROR(D12/D6,0) -> 0.50490927 | E13: =IFERROR(E12/E6,0) -> 0.51203256 | F13: =IFERROR(F12/F6,0) -> 0.52215771 | G13: =IFERROR(G12/G6,0) -> 0.49491792 | H13: =IFERROR(H12/H6,0) -> 0.49347901 | I13: =IFERROR(I12/I6,0) -> 0.46059756 | J13: =IFERROR(J12/J6,0) -> 0.50458834 | ... M13: =IFERROR(M12/M6,0) -> 1
B15: Employee Compenstation | C15: =IFERROR('Data Sheet'!B22,0) -> 1743 | D15: =IFERROR('Data Sheet'!C22,0) -> 1860 | E15: =IFERROR('Data Sheet'!D22,0) -> 1875 | F15: =IFERROR('Data Sheet'!E22,0) -> 1820 | G15: =IFERROR('Data Sheet'!F22,0) -> 2358 | H15: =IFERROR('Data Sheet'!G22,0) -> 2545 | I15: =IFERROR('Data Sheet'!H22,0) -> 2854 | J15: =IFERROR('Data Sheet'!I22,0) -> 3009 | ... M15: =IFERROR('Data Sheet'!L22,0) -> 0
B16: Employee Compenstation% Sales | C16: =IFERROR(C15/C6,0) -> 0.052560159 | D16: =IFERROR(D15/D6,0) -> 0.052328035 | E16: =IFERROR(E15/E6,0) -> 0.047697787 | F16: =IFERROR(F15/F6,0) -> 0.045748184 | G16: =IFERROR(G15/G6,0) -> 0.050140342 | H16: =IFERROR(H15/H6,0) -> 0.048526103 | I16: =IFERROR(I15/I6,0) -> 0.047111258 | J16: =IFERROR(J15/J6,0) -> 0.048613804 | ... M16: =IFERROR(M15/M6,0) -> 0
B18: Selling & General Expenses | C18: =IFERROR(SUM('Data Sheet'!B23:B24),0) -> 8159 | D18: =IFERROR(SUM('Data Sheet'!C23:C24),0) -> 8732 | E18: =IFERROR(SUM('Data Sheet'!D23:D24),0) -> 9349 | F18: =IFERROR(SUM('Data Sheet'!E23:E24),0) -> 9308 | G18: =IFERROR(SUM('Data Sheet'!F23:F24),0) -> 10101 | H18: =IFERROR(SUM('Data Sheet'!G23:G24),0) -> 10523 | I18: =IFERROR(SUM('Data Sheet'!H23:H24),0) -> 11052 | J18: =IFERROR(SUM('Data Sheet'!I23:I24),0) -> 13586 | ... L18: =IFERROR(SUM('Data Sheet'!K23:K24),0) -> 13795 | M18: =IFERROR(SUM('Data Sheet'!H43:K43),0) -> 50108
B19: SG&A % Sales | C19: =IFERROR(C18/C6,0) -> 0.24603462 | D19: =IFERROR(D18/D6,0) -> 0.24566043 | E19: =IFERROR(E18/E6,0) -> 0.23782752 | F19: =IFERROR(F18/F6,0) -> 0.23396928 | G19: =IFERROR(G18/G6,0) -> 0.21478694 | H19: =IFERROR(H18/H6,0) -> 0.20064447 | I19: =IFERROR(I18/I6,0) -> 0.18243645 | J19: =IFERROR(J18/J6,0) -> 0.21949722 | ... M19: =IFERROR(M18/M6,0) -> 0.76823304
B21: EBITDA | C21: =IFERROR(C12-SUM(C15,C18),0) -> 6616 | D21: =IFERROR(D12-SUM(D15,D18),0) -> 7355 | E21: =IFERROR(E12-SUM(E15,E18),0) -> 8904 | F21: =IFERROR(F12-SUM(F15,F18),0) -> 9645 | G21: =IFERROR(G12-SUM(G15,G18),0) -> 10816 | H21: =IFERROR(H12-SUM(H15,H18),0) -> 12813 | I21: =IFERROR(I12-SUM(I15,I18),0) -> 13997 | J21: =IFERROR(J12-SUM(J15,J18),0) -> 14637 | ... M21: =IFERROR(M12-SUM(M15,M18),0) -> 15117
B22: EBITDA % Sales | C22: =IFERROR(C21/C6,0) -> 0.19950546 | D22: =IFERROR(D21/D6,0) -> 0.2069208 | E22: =IFERROR(E21/E6,0) -> 0.22650725 | F22: =IFERROR(F21/F6,0) -> 0.24244024 | G22: =IFERROR(G21/G6,0) -> 0.22999064 | H22: =IFERROR(H21/H6,0) -> 0.24430843 | I22: =IFERROR(I21/I6,0) -> 0.23104985 | J22: =IFERROR(J21/J6,0) -> 0.23647732 | ... M22: =IFERROR(M21/M6,0) -> 0.23176696
B24: Interest | C24: =IFERROR(('Data Sheet'!B27),0) -> 35 | D24: =IFERROR(('Data Sheet'!C27),0) -> 26 | E24: =IFERROR(('Data Sheet'!D27),0) -> 33 | F24: =IFERROR(('Data Sheet'!E27),0) -> 118 | G24: =IFERROR(('Data Sheet'!F27),0) -> 117 | H24: =IFERROR(('Data Sheet'!G27),0) -> 106 | I24: =IFERROR(('Data Sheet'!H27),0) -> 114 | J24: =IFERROR(('Data Sheet'!I27),0) -> 334 | ... L24: =IFERROR(('Data Sheet'!K27),0) -> 410 | M24: =IFERROR(SUM('Data Sheet'!H46:K46),0) -> 415
B25: Interest % Sales | C25: =C24/C6 -> 0.0010554249 | D25: =D24/D6 -> 0.00073146715 | E25: =E24/E6 -> 0.00083948105 | F25: =F24/F6 -> 0.002966091 | G25: =G24/G6 -> 0.0024878796 | H25: =H24/H6 -> 0.0020211265 | I25: =I24/I6 -> 0.0018818092 | J25: =J24/J6 -> 0.0053961484 | ... M25: =M24/M6 -> 0.006362591
B27: Depreciation | C27: =IFERROR(('Data Sheet'!B26),0) -> 432 | D27: =IFERROR(('Data Sheet'!C26),0) -> 520 | E27: =IFERROR(('Data Sheet'!D26),0) -> 565 | F27: =IFERROR(('Data Sheet'!E26),0) -> 1002 | G27: =IFERROR(('Data Sheet'!F26),0) -> 1074 | H27: =IFERROR(('Data Sheet'!G26),0) -> 1091 | I27: =IFERROR(('Data Sheet'!H26),0) -> 1137 | J27: =IFERROR(('Data Sheet'!I26),0) -> 1216 | ... L27: =IFERROR(('Data Sheet'!K26),0) -> 1333 | M27: =IFERROR(SUM('Data Sheet'!H45:K45),0) -> 1368
B28: Depreciation % Sales | C28: =C27/C6 -> 0.013026959 | D28: =D27/D6 -> 0.014629343 | E28: =E27/E6 -> 0.014372933 | F28: =F27/F6 -> 0.025186638 | G28: =G27/G6 -> 0.022837459 | H28: =H27/H6 -> 0.020802349 | I28: =I27/I6 -> 0.01876857 | J28: =J27/J6 -> 0.019645858 | ... M28: =M27/M6 -> 0.020973553
B30: Other Income | C30: =IFERROR('Data Sheet'!B25,0) -> 606 | D30: =IFERROR('Data Sheet'!C25,0) -> 353 | E30: =IFERROR('Data Sheet'!D25,0) -> 322 | F30: =IFERROR('Data Sheet'!E25,0) -> 424 | G30: =IFERROR('Data Sheet'!F25,0) -> 170 | H30: =IFERROR('Data Sheet'!G25,0) -> 219 | I30: =IFERROR('Data Sheet'!H25,0) -> 448 | J30: =IFERROR('Data Sheet'!I25,0) -> 817 | ... L30: =IFERROR('Data Sheet'!K25,0) -> 4923 | M30: =IFERROR(SUM('Data Sheet'!H44:K44),0) -> 4894
B31: Other Income% sales | C31: =IFERROR(C30/C6,0) -> 0.018273928 | D31: =IFERROR(D30/D6,0) -> 0.0099310733 | E31: =IFERROR(E30/E6,0) -> 0.0081912999 | F31: =IFERROR(F30/F6,0) -> 0.010657819 | G31: =IFERROR(G30/G6,0) -> 0.0036148677 | H31: =IFERROR(H30/H6,0) -> 0.0041757236 | I31: =IFERROR(I30/I6,0) -> 0.0073951799 | J31: =IFERROR(J30/J6,0) -> 0.013199561 | ... M31: =IFERROR(M30/M6,0) -> 0.07503258
B33: Earnings Before Tax | C33: =IFERROR(C21-C24-C27+C30,0) -> 6755 | D33: =IFERROR(D21-D24-D27+D30,0) -> 7162 | E33: =IFERROR(E21-E24-E27+E30,0) -> 8628 | F33: =IFERROR(F21-F24-F27+F30,0) -> 8949 | G33: =IFERROR(G21-G24-G27+G30,0) -> 9795 | H33: =IFERROR(H21-H24-H27+H30,0) -> 11835 | I33: =IFERROR(I21-I24-I27+I30,0) -> 13194 | J33: =IFERROR(J21-J24-J27+J30,0) -> 13904 | ... M33: =IFERROR(M21-M24-M27+M30,0) -> 18228
B34: EBT % Sales | C34: =IFERROR(C33/C6,0) -> 0.203697 | D34: =IFERROR(D33/D6,0) -> 0.20149107 | E34: =IFERROR(E33/E6,0) -> 0.21948614 | F34: =IFERROR(F33/F6,0) -> 0.22494533 | G34: =IFERROR(G33/G6,0) -> 0.20828017 | H34: =IFERROR(H33/H6,0) -> 0.22566068 | I34: =IFERROR(I33/I6,0) -> 0.21779465 | J34: =IFERROR(J33/J6,0) -> 0.22463487 | ... M34: =IFERROR(M33/M6,0) -> 0.2794634
B36: Tax | C36: =IFERROR('Data Sheet'!B29,0) -> 1977 | D36: =IFERROR('Data Sheet'!C29,0) -> 2079 | E36: =IFERROR('Data Sheet'!D29,0) -> 2544 | F36: =IFERROR('Data Sheet'!E29,0) -> 2409 | G36: =IFERROR('Data Sheet'!F29,0) -> 2606 | H36: =IFERROR('Data Sheet'!G29,0) -> 2987 | I36: =IFERROR('Data Sheet'!H29,0) -> 3201 | J36: =IFERROR('Data Sheet'!I29,0) -> 3644 | ... L36: =IFERROR('Data Sheet'!K29,0) -> 3160 | M36: =IFERROR(SUM('Data Sheet'!H48:K48),0) -> 3169
B37: Effective Tax rate | C37: =IFERROR(C36/C33,0) -> 0.29267209 | D37: =IFERROR(D36/D33,0) -> 0.29028204 | E37: =IFERROR(E36/E33,0) -> 0.29485396 | F37: =IFERROR(F36/F33,0) -> 0.26919209 | G37: =IFERROR(G36/G33,0) -> 0.26605411 | H37: =IFERROR(H36/H33,0) -> 0.25238699 | I37: =IFERROR(I36/I33,0) -> 0.24261028 | J37: =IFERROR(J36/J33,0) -> 0.26208285 | ... M37: =IFERROR(M36/M33,0) -> 0.17385341
B39: Net Profit | C39: =IFERROR((C33-C36),0) -> 4778 | D39: =IFERROR((D33-D36),0) -> 5083 | E39: =IFERROR((E33-E36),0) -> 6084 | F39: =IFERROR((F33-F36),0) -> 6540 | G39: =IFERROR((G33-G36),0) -> 7189 | H39: =IFERROR((H33-H36),0) -> 8848 | I39: =IFERROR((I33-I36),0) -> 9993 | J39: =IFERROR((J33-J36),0) -> 10260 | ... M39: =IFERROR((M33-M36),0) -> 15059
B40: Net Margin | C40: =IFERROR(C39/C6,0) -> 0.14408057 | D40: =IFERROR(D39/D6,0) -> 0.14300183 | E40: =IFERROR(E39/E6,0) -> 0.15476978 | F40: =IFERROR(F39/F6,0) -> 0.16439183 | G40: =IFERROR(G39/G6,0) -> 0.15286638 | H40: =IFERROR(H39/H6,0) -> 0.16870686 | I40: =IFERROR(I39/I6,0) -> 0.16495543 | J40: =IFERROR(J39/J6,0) -> 0.16576192 | ... M40: =IFERROR(M39/M6,0) -> 0.23087773
B42: No. of Equity Shares O/S | C42: =IFERROR('Data Sheet'!B93,0) -> 216.43 | D42: =IFERROR('Data Sheet'!C93,0) -> 216.45 | E42: =IFERROR('Data Sheet'!D93,0) -> 216.47 | F42: =IFERROR('Data Sheet'!E93,0) -> 216.48 | G42: =IFERROR('Data Sheet'!F93,0) -> 234.96 | H42: =IFERROR('Data Sheet'!G93,0) -> 234.96 | I42: =IFERROR('Data Sheet'!H93,0) -> 234.96 | J42: =IFERROR('Data Sheet'!I93,0) -> 234.96 | ... L42: =IFERROR('Data Sheet'!K93,0) -> 234.96 | M42: =L42 -> 234.96
B44: Earnings Per Share | C44: =IFERROR(C39/C42,0) -> 22.076422 | D44: =IFERROR(D39/D42,0) -> 23.483483 | E44: =IFERROR(E39/E42,0) -> 28.105511 | F44: =IFERROR(F39/F42,0) -> 30.210643 | G44: =IFERROR(G39/G42,0) -> 30.596697 | H44: =IFERROR(H39/H42,0) -> 37.657474 | I44: =IFERROR(I39/I42,0) -> 42.530644 | J44: =IFERROR(J39/J42,0) -> 43.667007 | ... M44: =IFERROR(M39/M42,0) -> 64.09176
B45: EPS growth % | D45: =IFERROR((D44/C44-1),0) -> 0.063735942 | E45: =IFERROR((E44/D44-1),0) -> 0.19682036 | F45: =IFERROR((F44/E44-1),0) -> 0.074901034 | G45: =IFERROR((G44/F44-1),0) -> 0.012778751 | H45: =IFERROR((H44/G44-1),0) -> 0.23076923 | I45: =IFERROR((I44/H44-1),0) -> 0.12940778 | J45: =IFERROR((J44/I44-1),0) -> 0.026718703 | K45: =IFERROR((K44/J44-1),0) -> 0.015692008 | ... M45: =IFERROR((M44/L44-1),0) -> 0.06041828
B47: Dividends Per Share | C47: =IFERROR(('Data Sheet'!B31/C42),0) -> 16.966225 | D47: =IFERROR(('Data Sheet'!C31/D42),0) -> 19.95842 | E47: =IFERROR(('Data Sheet'!D31/E42),0) -> 21.952234 | F47: =IFERROR(('Data Sheet'!E31/F42),0) -> 24.944568 | G47: =IFERROR(('Data Sheet'!F31/G42),0) -> 40.506895 | H47: =IFERROR(('Data Sheet'!G31/H42),0) -> 34.005788 | I47: =IFERROR(('Data Sheet'!H31/I42),0) -> 39.006639 | J47: =IFERROR(('Data Sheet'!I31/J42),0) -> 42.00715 | ... M47: =IFERROR(('Data Sheet'!L31/M42),0) -> 0
B48: Dividend Payout Ratio | C48: =IFERROR((C47/C44),0) -> 0.76852239 | D48: =IFERROR((D47/D44),0) -> 0.8498918 | E48: =IFERROR((E47/E44),0) -> 0.78106509 | F48: =IFERROR((F47/F44),0) -> 0.82568807 | G48: =IFERROR((G47/G44),0) -> 1.3238976 | H48: =IFERROR((H47/H44),0) -> 0.90302893 | I48: =IFERROR((I47/I44),0) -> 0.917142 | J48: =IFERROR((J47/J44),0) -> 0.9619883 | ... M48: =IFERROR((M47/M44),0) -> 0
B50: Retained Earnings | C50: =IFERROR(IF(C44>C47,1-C48,0),0) -> 0.23147761 | D50: =IFERROR(IF(D44>D47,1-D48,0),0) -> 0.1501082 | E50: =IFERROR(IF(E44>E47,1-E48,0),0) -> 0.21893491 | F50: =IFERROR(IF(F44>F47,1-F48,0),0) -> 0.17431193 | G50: =IFERROR(IF(G44>G47,1-G48,0),0) -> 0 | H50: =IFERROR(IF(H44>H47,1-H48,0),0) -> 0.096971067 | I50: =IFERROR(IF(I44>I47,1-I48,0),0) -> 0.082858001 | J50: =IFERROR(IF(J44>J47,1-J48,0),0) -> 0.038011696 | ... M50: =IFERROR(IF(M44>M47,1-M48,0),0) -> 1
A52: # | B52: Balance Sheet
B54: Equity Share Capital | C54: =IFERROR('Data Sheet'!B57,0) -> 216 | D54: =IFERROR('Data Sheet'!C57,0) -> 216 | E54: =IFERROR('Data Sheet'!D57,0) -> 216 | F54: =IFERROR('Data Sheet'!E57,0) -> 216 | G54: =IFERROR('Data Sheet'!F57,0) -> 235 | H54: =IFERROR('Data Sheet'!G57,0) -> 235 | I54: =IFERROR('Data Sheet'!H57,0) -> 235 | J54: =IFERROR('Data Sheet'!I57,0) -> 235 | ... L54: =IFERROR('Data Sheet'!K57,0) -> 235
B55: Reserves | C55: =IFERROR('Data Sheet'!B58,0) -> 6528 | D55: =IFERROR('Data Sheet'!C58,0) -> 7065 | E55: =IFERROR('Data Sheet'!D58,0) -> 7651 | F55: =IFERROR('Data Sheet'!E58,0) -> 8013 | G55: =IFERROR('Data Sheet'!F58,0) -> 47439 | H55: =IFERROR('Data Sheet'!G58,0) -> 48826 | I55: =IFERROR('Data Sheet'!H58,0) -> 50069 | J55: =IFERROR('Data Sheet'!I58,0) -> 50983 | ... L55: =IFERROR('Data Sheet'!K58,0) -> 48504
B56: Borrowings | C56: =IFERROR('Data Sheet'!B59,0) -> 277 | D56: =IFERROR('Data Sheet'!C59,0) -> 0 | E56: =IFERROR('Data Sheet'!D59,0) -> 99 | F56: =IFERROR('Data Sheet'!E59,0) -> 0 | G56: =IFERROR('Data Sheet'!F59,0) -> 0 | H56: =IFERROR('Data Sheet'!G59,0) -> 1043 | I56: =IFERROR('Data Sheet'!H59,0) -> 1219 | J56: =IFERROR('Data Sheet'!I59,0) -> 1484 | ... L56: =IFERROR('Data Sheet'!K59,0) -> 1478
B57: Other Liabilities | C57: =IFERROR('Data Sheet'!B60,0) -> 8685 | D57: =IFERROR('Data Sheet'!C60,0) -> 10581 | E57: =IFERROR('Data Sheet'!D60,0) -> 10663 | F57: =IFERROR('Data Sheet'!E60,0) -> 11924 | G57: =IFERROR('Data Sheet'!F60,0) -> 21066 | H57: =IFERROR('Data Sheet'!G60,0) -> 20402 | I57: =IFERROR('Data Sheet'!H60,0) -> 21554 | J57: =IFERROR('Data Sheet'!I60,0) -> 25787 | ... L57: =IFERROR('Data Sheet'!K60,0) -> 29521
B58: Total Liabilities | C58: =IFERROR('Data Sheet'!B61,0) -> 15706 | D58: =IFERROR('Data Sheet'!C61,0) -> 17862 | E58: =IFERROR('Data Sheet'!D61,0) -> 18629 | F58: =IFERROR('Data Sheet'!E61,0) -> 20153 | G58: =IFERROR('Data Sheet'!F61,0) -> 68740 | H58: =IFERROR('Data Sheet'!G61,0) -> 70506 | I58: =IFERROR('Data Sheet'!H61,0) -> 73077 | J58: =IFERROR('Data Sheet'!I61,0) -> 78489 | ... L58: =IFERROR('Data Sheet'!K61,0) -> 79738
B60: Fixed Assets Net Block | C60: =IFERROR('Data Sheet'!B62,0) -> 4419 | D60: =IFERROR('Data Sheet'!C62,0) -> 4528 | E60: =IFERROR('Data Sheet'!D62,0) -> 4715 | F60: =IFERROR('Data Sheet'!E62,0) -> 5479 | G60: =IFERROR('Data Sheet'!F62,0) -> 51443 | H60: =IFERROR('Data Sheet'!G62,0) -> 51473 | I60: =IFERROR('Data Sheet'!H62,0) -> 52678 | J60: =IFERROR('Data Sheet'!I62,0) -> 53744 | ... L60: =IFERROR('Data Sheet'!K62,0) -> 57428
B61: Capital Work in Progress | C61: =IFERROR('Data Sheet'!B63,0) -> 229 | D61: =IFERROR('Data Sheet'!C63,0) -> 461 | E61: =IFERROR('Data Sheet'!D63,0) -> 406 | F61: =IFERROR('Data Sheet'!E63,0) -> 597 | G61: =IFERROR('Data Sheet'!F63,0) -> 745 | H61: =IFERROR('Data Sheet'!G63,0) -> 1313 | I61: =IFERROR('Data Sheet'!H63,0) -> 1132 | J61: =IFERROR('Data Sheet'!I63,0) -> 1025 | ... L61: =IFERROR('Data Sheet'!K63,0) -> 880
B62: Investments | C62: =IFERROR('Data Sheet'!B64,0) -> 3794 | D62: =IFERROR('Data Sheet'!C64,0) -> 2873 | E62: =IFERROR('Data Sheet'!D64,0) -> 2716 | F62: =IFERROR('Data Sheet'!E64,0) -> 1255 | G62: =IFERROR('Data Sheet'!F64,0) -> 2709 | H62: =IFERROR('Data Sheet'!G64,0) -> 3521 | I62: =IFERROR('Data Sheet'!H64,0) -> 2882 | J62: =IFERROR('Data Sheet'!I64,0) -> 4625 | ... L62: =IFERROR('Data Sheet'!K64,0) -> 4359
B63: Other Assets | C63: =IFERROR('Data Sheet'!B65-SUM('Data Sheet'!B67:B69),0) -> 1810 | D63: =IFERROR('Data Sheet'!C65-SUM('Data Sheet'!C67:C69),0) -> 2692 | E63: =IFERROR('Data Sheet'!D65-SUM('Data Sheet'!D67:D69),0) -> 2645 | F63: =IFERROR('Data Sheet'!E65-SUM('Data Sheet'!E67:E69),0) -> 3793 | G63: =IFERROR('Data Sheet'!F65-SUM('Data Sheet'!F67:F69),0) -> 4035 | H63: =IFERROR('Data Sheet'!G65-SUM('Data Sheet'!G67:G69),0) -> 4021 | I63: =IFERROR('Data Sheet'!H65-SUM('Data Sheet'!H67:H69),0) -> 4377 | J63: =IFERROR('Data Sheet'!I65-SUM('Data Sheet'!I67:I69),0) -> 4517 | ... L63: =IFERROR('Data Sheet'!K65-SUM('Data Sheet'!K67:K69),0) -> 5655
B64: Total Non Current Asset | C64: =IFERROR(SUM(C60:C63),0) -> 10252 | D64: =IFERROR(SUM(D60:D63),0) -> 10554 | E64: =IFERROR(SUM(E60:E63),0) -> 10482 | F64: =IFERROR(SUM(F60:F63),0) -> 11124 | G64: =IFERROR(SUM(G60:G63),0) -> 58932 | H64: =IFERROR(SUM(H60:H63),0) -> 60328 | I64: =IFERROR(SUM(I60:I63),0) -> 61069 | J64: =IFERROR(SUM(J60:J63),0) -> 63911 | ... L64: =IFERROR(SUM(L60:L63),0) -> 68322
B66: Receivables | C66: =IFERROR('Data Sheet'!B67,0) -> 1085 | D66: =IFERROR('Data Sheet'!C67,0) -> 1310 | E66: =IFERROR('Data Sheet'!D67,0) -> 1816 | F66: =IFERROR('Data Sheet'!E67,0) -> 1149 | G66: =IFERROR('Data Sheet'!F67,0) -> 1758 | H66: =IFERROR('Data Sheet'!G67,0) -> 2236 | I66: =IFERROR('Data Sheet'!H67,0) -> 3079 | J66: =IFERROR('Data Sheet'!I67,0) -> 2997 | ... L66: =IFERROR('Data Sheet'!K67,0) -> 3379
B67: Inventory | C67: =IFERROR('Data Sheet'!B68,0) -> 2541 | D67: =IFERROR('Data Sheet'!C68,0) -> 2513 | E67: =IFERROR('Data Sheet'!D68,0) -> 2574 | F67: =IFERROR('Data Sheet'!E68,0) -> 2767 | G67: =IFERROR('Data Sheet'!F68,0) -> 3579 | H67: =IFERROR('Data Sheet'!G68,0) -> 4096 | I67: =IFERROR('Data Sheet'!H68,0) -> 4251 | J67: =IFERROR('Data Sheet'!I68,0) -> 4022 | ... L67: =IFERROR('Data Sheet'!K68,0) -> 4789
B68: Cash & Bank | C68: =IFERROR('Data Sheet'!B69,0) -> 1828 | D68: =IFERROR('Data Sheet'!C69,0) -> 3485 | E68: =IFERROR('Data Sheet'!D69,0) -> 3757 | F68: =IFERROR('Data Sheet'!E69,0) -> 5113 | G68: =IFERROR('Data Sheet'!F69,0) -> 4471 | H68: =IFERROR('Data Sheet'!G69,0) -> 3846 | I68: =IFERROR('Data Sheet'!H69,0) -> 4678 | J68: =IFERROR('Data Sheet'!I69,0) -> 7559 | ... L68: =IFERROR('Data Sheet'!K69,0) -> 3248
B69: Total Current Asset | C69: =IFERROR(SUM(C66:C68),0) -> 5454 | D69: =IFERROR(SUM(D66:D68),0) -> 7308 | E69: =IFERROR(SUM(E66:E68),0) -> 8147 | F69: =IFERROR(SUM(F66:F68),0) -> 9029 | G69: =IFERROR(SUM(G66:G68),0) -> 9808 | H69: =IFERROR(SUM(H66:H68),0) -> 10178 | I69: =IFERROR(SUM(I66:I68),0) -> 12008 | J69: =IFERROR(SUM(J66:J68),0) -> 14578 | ... L69: =IFERROR(SUM(L66:L68),0) -> 11416
B71: Total Asset | C71: =IFERROR((C69+C64),0) -> 15706 | D71: =IFERROR((D69+D64),0) -> 17862 | E71: =IFERROR((E69+E64),0) -> 18629 | F71: =IFERROR((F69+F64),0) -> 20153 | G71: =IFERROR((G69+G64),0) -> 68740 | H71: =IFERROR((H69+H64),0) -> 70506 | I71: =IFERROR((I69+I64),0) -> 73077 | J71: =IFERROR((J69+J64),0) -> 78489 | ... L71: =IFERROR((L69+L64),0) -> 79738
B73: CHECK | C73: =C71=C58 -> TRUE | D73: =D71=D58 -> TRUE | E73: =E71=E58 -> TRUE | F73: =F71=F58 -> TRUE | G73: =G71=G58 -> TRUE | H73: =H71=H58 -> TRUE | I73: =I71=I58 -> TRUE | J73: =J71=J58 -> TRUE | ... L73: =L71=L58 -> TRUE
A75: # | B75: Cash Flow Statement
B76: Operating Activities
B77: Profit from operations | C77: =IFERROR('Cash Flow Data'!E4,0) -> 6219 | D77: =IFERROR('Cash Flow Data'!F4,0) -> 7237 | E77: =IFERROR('Cash Flow Data'!G4,0) -> 8674 | F77: =IFERROR('Cash Flow Data'!H4,0) -> 9473 | G77: =IFERROR('Cash Flow Data'!I4,0) -> 11380 | H77: =IFERROR('Cash Flow Data'!J4,0) -> 12473 | I77: =IFERROR('Cash Flow Data'!K4,0) -> 13557 | J77: =IFERROR('Cash Flow Data'!L4,0) -> 14043 | ... L77: =IFERROR('Cash Flow Data'!N4,0) -> 14538
B78: Receivables | C78: =IFERROR('Cash Flow Data'!E5,0) -> 131 | D78: =IFERROR('Cash Flow Data'!F5,0) -> 0 | E78: =IFERROR('Cash Flow Data'!G5,0) -> 0 | F78: =IFERROR('Cash Flow Data'!H5,0) -> 0 | G78: =IFERROR('Cash Flow Data'!I5,0) -> 0 | H78: =IFERROR('Cash Flow Data'!J5,0) -> 0 | I78: =IFERROR('Cash Flow Data'!K5,0) -> 0 | J78: =IFERROR('Cash Flow Data'!L5,0) -> 0 | ... L78: =IFERROR('Cash Flow Data'!N5,0) -> 0
B79: Inventory | C79: =IFERROR('Cash Flow Data'!E6,0) -> 38 | D79: =IFERROR('Cash Flow Data'!F6,0) -> -162 | E79: =IFERROR('Cash Flow Data'!G6,0) -> -195 | F79: =IFERROR('Cash Flow Data'!H6,0) -> -369 | G79: =IFERROR('Cash Flow Data'!I6,0) -> -472 | H79: =IFERROR('Cash Flow Data'!J6,0) -> -737 | I79: =IFERROR('Cash Flow Data'!K6,0) -> -332 | J79: =IFERROR('Cash Flow Data'!L6,0) -> 77 | ... L79: =IFERROR('Cash Flow Data'!N6,0) -> -630
B80: Payables | C80: =IFERROR('Cash Flow Data'!E7,0) -> 508 | D80: =IFERROR('Cash Flow Data'!F7,0) -> 0 | E80: =IFERROR('Cash Flow Data'!G7,0) -> 0 | F80: =IFERROR('Cash Flow Data'!H7,0) -> 0 | G80: =IFERROR('Cash Flow Data'!I7,0) -> 0 | H80: =IFERROR('Cash Flow Data'!J7,0) -> 0 | I80: =IFERROR('Cash Flow Data'!K7,0) -> 0 | J80: =IFERROR('Cash Flow Data'!L7,0) -> 0 | ... L80: =IFERROR('Cash Flow Data'!N7,0) -> 0
B81: Loans Advances | C81: =IFERROR('Cash Flow Data'!E8,0) -> -46 | D81: =IFERROR('Cash Flow Data'!F8,0) -> 0 | E81: =IFERROR('Cash Flow Data'!G8,0) -> 0 | F81: =IFERROR('Cash Flow Data'!H8,0) -> 0 | G81: =IFERROR('Cash Flow Data'!I8,0) -> 0 | H81: =IFERROR('Cash Flow Data'!J8,0) -> 0 | I81: =IFERROR('Cash Flow Data'!K8,0) -> 0 | J81: =IFERROR('Cash Flow Data'!L8,0) -> 0 | ... L81: =IFERROR('Cash Flow Data'!N8,0) -> 0
B82: Other WC items | C82: =IFERROR('Cash Flow Data'!E9,0) -> -93 | D82: =IFERROR('Cash Flow Data'!F9,0) -> 1026 | E82: =IFERROR('Cash Flow Data'!G9,0) -> -66 | F82: =IFERROR('Cash Flow Data'!H9,0) -> 666 | G82: =IFERROR('Cash Flow Data'!I9,0) -> 416 | H82: =IFERROR('Cash Flow Data'!J9,0) -> -52 | I82: =IFERROR('Cash Flow Data'!K9,0) -> -531 | J82: =IFERROR('Cash Flow Data'!L9,0) -> 1059 | ... L82: =IFERROR('Cash Flow Data'!N9,0) -> 1314
B83: Working capital changes | C83: =IFERROR('Cash Flow Data'!E10,0) -> 538 | D83: =IFERROR('Cash Flow Data'!F10,0) -> 864 | E83: =IFERROR('Cash Flow Data'!G10,0) -> -261 | F83: =IFERROR('Cash Flow Data'!H10,0) -> 297 | G83: =IFERROR('Cash Flow Data'!I10,0) -> -56 | H83: =IFERROR('Cash Flow Data'!J10,0) -> -789 | I83: =IFERROR('Cash Flow Data'!K10,0) -> -863 | J83: =IFERROR('Cash Flow Data'!L10,0) -> 1136 | ... L83: =IFERROR('Cash Flow Data'!N10,0) -> 684
B84: Direct taxes | C84: =IFERROR('Cash Flow Data'!E11,0) -> -1783 | D84: =IFERROR('Cash Flow Data'!F11,0) -> -2188 | E84: =IFERROR('Cash Flow Data'!G11,0) -> -2685 | F84: =IFERROR('Cash Flow Data'!H11,0) -> -2465 | G84: =IFERROR('Cash Flow Data'!I11,0) -> -2367 | H84: =IFERROR('Cash Flow Data'!J11,0) -> -2720 | I84: =IFERROR('Cash Flow Data'!K11,0) -> -3068 | J84: =IFERROR('Cash Flow Data'!L11,0) -> -295 | ... L84: =IFERROR('Cash Flow Data'!N11,0) -> -4726
B85: Other operating items | C85: =IFERROR('Cash Flow Data'!E12,0) -> -21 | D85: =IFERROR('Cash Flow Data'!F12,0) -> 0 | E85: =IFERROR('Cash Flow Data'!G12,0) -> 0 | F85: =IFERROR('Cash Flow Data'!H12,0) -> 0 | G85: =IFERROR('Cash Flow Data'!I12,0) -> 0 | H85: =IFERROR('Cash Flow Data'!J12,0) -> 0 | I85: =IFERROR('Cash Flow Data'!K12,0) -> 0 | J85: =IFERROR('Cash Flow Data'!L12,0) -> 0 | ... L85: =IFERROR('Cash Flow Data'!N12,0) -> 0
B86: Cash from Operating Activities | C86: =IFERROR(SUM(C77,C83,C84,C85),0) -> 4953 | D86: =IFERROR(SUM(D77,D83,D84,D85),0) -> 5913 | E86: =IFERROR(SUM(E77,E83,E84,E85),0) -> 5728 | F86: =IFERROR(SUM(F77,F83,F84,F85),0) -> 7305 | G86: =IFERROR(SUM(G77,G83,G84,G85),0) -> 8957 | H86: =IFERROR(SUM(H77,H83,H84,H85),0) -> 8964 | I86: =IFERROR(SUM(I77,I83,I84,I85),0) -> 9626 | J86: =IFERROR(SUM(J77,J83,J84,J85),0) -> 14884 | ... L86: =IFERROR(SUM(L77,L83,L84,L85),0) -> 10496
B88: Investing Activities
B89: Fixed assets purchased | C89: =IFERROR('Cash Flow Data'!E14,0) -> -1024 | D89: =IFERROR('Cash Flow Data'!F14,0) -> -853 | E89: =IFERROR('Cash Flow Data'!G14,0) -> -728 | F89: =IFERROR('Cash Flow Data'!H14,0) -> -765 | G89: =IFERROR('Cash Flow Data'!I14,0) -> -4051 | H89: =IFERROR('Cash Flow Data'!J14,0) -> -919 | I89: =IFERROR('Cash Flow Data'!K14,0) -> -1041 | J89: =IFERROR('Cash Flow Data'!L14,0) -> -1318 | ... L89: =IFERROR('Cash Flow Data'!N14,0) -> -1274
B90: Fixed assets sold | C90: =IFERROR('Cash Flow Data'!E15,0) -> 172 | D90: =IFERROR('Cash Flow Data'!F15,0) -> 26 | E90: =IFERROR('Cash Flow Data'!G15,0) -> 4 | F90: =IFERROR('Cash Flow Data'!H15,0) -> 52 | G90: =IFERROR('Cash Flow Data'!I15,0) -> 97 | H90: =IFERROR('Cash Flow Data'!J15,0) -> 175 | I90: =IFERROR('Cash Flow Data'!K15,0) -> 180 | J90: =IFERROR('Cash Flow Data'!L15,0) -> 20 | ... L90: =IFERROR('Cash Flow Data'!N15,0) -> 29
B91: Investments purchased | C91: =IFERROR('Cash Flow Data'!E16,0) -> -26230 | D91: =IFERROR('Cash Flow Data'!F16,0) -> -47755 | E91: =IFERROR('Cash Flow Data'!G16,0) -> -70434 | F91: =IFERROR('Cash Flow Data'!H16,0) -> -34074 | G91: =IFERROR('Cash Flow Data'!I16,0) -> -38450 | H91: =IFERROR('Cash Flow Data'!J16,0) -> -47928 | I91: =IFERROR('Cash Flow Data'!K16,0) -> -22631 | J91: =IFERROR('Cash Flow Data'!L16,0) -> -21198 | ... L91: =IFERROR('Cash Flow Data'!N16,0) -> -23058
B92: Investments sold | C92: =IFERROR('Cash Flow Data'!E17,0) -> 25260 | D92: =IFERROR('Cash Flow Data'!F17,0) -> 48534 | E92: =IFERROR('Cash Flow Data'!G17,0) -> 70761 | F92: =IFERROR('Cash Flow Data'!H17,0) -> 35656 | G92: =IFERROR('Cash Flow Data'!I17,0) -> 37076 | H92: =IFERROR('Cash Flow Data'!J17,0) -> 47173 | I92: =IFERROR('Cash Flow Data'!K17,0) -> 23363 | J92: =IFERROR('Cash Flow Data'!L17,0) -> 19752 | ... L92: =IFERROR('Cash Flow Data'!N17,0) -> 22609
B93: Interest received | C93: =IFERROR('Cash Flow Data'!E18,0) -> 266 | D93: =IFERROR('Cash Flow Data'!F18,0) -> 229 | E93: =IFERROR('Cash Flow Data'!G18,0) -> 308 | F93: =IFERROR('Cash Flow Data'!H18,0) -> 359 | G93: =IFERROR('Cash Flow Data'!I18,0) -> 285 | H93: =IFERROR('Cash Flow Data'!J18,0) -> 171 | I93: =IFERROR('Cash Flow Data'!K18,0) -> 273 | J93: =IFERROR('Cash Flow Data'!L18,0) -> 417 | ... L93: =IFERROR('Cash Flow Data'!N18,0) -> 431
B94: Dividends received | C94: =IFERROR('Cash Flow Data'!E19,0) -> 178 | D94: =IFERROR('Cash Flow Data'!F19,0) -> 190 | E94: =IFERROR('Cash Flow Data'!G19,0) -> 103 | F94: =IFERROR('Cash Flow Data'!H19,0) -> 96 | G94: =IFERROR('Cash Flow Data'!I19,0) -> 102 | H94: =IFERROR('Cash Flow Data'!J19,0) -> 131 | I94: =IFERROR('Cash Flow Data'!K19,0) -> 118 | J94: =IFERROR('Cash Flow Data'!L19,0) -> 176 | ... L94: =IFERROR('Cash Flow Data'!N19,0) -> 230
B95: Invest in subsidiaries | C95: =IFERROR('Cash Flow Data'!E20,0) -> 0 | D95: =IFERROR('Cash Flow Data'!F20,0) -> 0 | E95: =IFERROR('Cash Flow Data'!G20,0) -> 0 | F95: =IFERROR('Cash Flow Data'!H20,0) -> 0 | G95: =IFERROR('Cash Flow Data'!I20,0) -> -60 | H95: =IFERROR('Cash Flow Data'!J20,0) -> -300 | I95: =IFERROR('Cash Flow Data'!K20,0) -> -264 | J95: =IFERROR('Cash Flow Data'!L20,0) -> 0 | ... L95: =IFERROR('Cash Flow Data'!N20,0) -> -3530
B96: Loans to subsidiaries | C96: =IFERROR('Cash Flow Data'!E21,0) -> -84 | D96: =IFERROR('Cash Flow Data'!F21,0) -> -183 | E96: =IFERROR('Cash Flow Data'!G21,0) -> -248 | F96: =IFERROR('Cash Flow Data'!H21,0) -> -292 | G96: =IFERROR('Cash Flow Data'!I21,0) -> -180 | H96: =IFERROR('Cash Flow Data'!J21,0) -> -436 | I96: =IFERROR('Cash Flow Data'!K21,0) -> -493 | J96: =IFERROR('Cash Flow Data'!L21,0) -> -431 | ... L96: =IFERROR('Cash Flow Data'!N21,0) -> -171
B97: Redemp n Canc of Shares | C97: =IFERROR('Cash Flow Data'!E22,0) -> 20 | D97: =IFERROR('Cash Flow Data'!F22,0) -> 73 | E97: =IFERROR('Cash Flow Data'!G22,0) -> 0 | F97: =IFERROR('Cash Flow Data'!H22,0) -> 0 | G97: =IFERROR('Cash Flow Data'!I22,0) -> 0 | H97: =IFERROR('Cash Flow Data'!J22,0) -> 0 | I97: =IFERROR('Cash Flow Data'!K22,0) -> 0 | J97: =IFERROR('Cash Flow Data'!L22,0) -> 0 | ... L97: =IFERROR('Cash Flow Data'!N22,0) -> 298
B98: Acquisition of companies | C98: =IFERROR('Cash Flow Data'!E23,0) -> 0 | D98: =IFERROR('Cash Flow Data'!F23,0) -> 0 | E98: =IFERROR('Cash Flow Data'!G23,0) -> 0 | F98: =IFERROR('Cash Flow Data'!H23,0) -> 0 | G98: =IFERROR('Cash Flow Data'!I23,0) -> 0 | H98: =IFERROR('Cash Flow Data'!J23,0) -> 0 | I98: =IFERROR('Cash Flow Data'!K23,0) -> 0 | J98: =IFERROR('Cash Flow Data'!L23,0) -> 0 | ... L98: =IFERROR('Cash Flow Data'!N23,0) -> 0
B99: Other investing items | C99: =IFERROR('Cash Flow Data'!E24,0) -> 690 | D99: =IFERROR('Cash Flow Data'!F24,0) -> -1522 | E99: =IFERROR('Cash Flow Data'!G24,0) -> -30 | F99: =IFERROR('Cash Flow Data'!H24,0) -> 894 | G99: =IFERROR('Cash Flow Data'!I24,0) -> 4114 | H99: =IFERROR('Cash Flow Data'!J24,0) -> 201 | I99: =IFERROR('Cash Flow Data'!K24,0) -> -567 | J99: =IFERROR('Cash Flow Data'!L24,0) -> -2389 | ... L99: =IFERROR('Cash Flow Data'!N24,0) -> 963
B100: Cash from Investing Activities | C100: =IFERROR(SUM(C89:C99),0) -> -752 | D100: =IFERROR(SUM(D89:D99),0) -> -1261 | E100: =IFERROR(SUM(E89:E99),0) -> -264 | F100: =IFERROR(SUM(F89:F99),0) -> 1926 | G100: =IFERROR(SUM(G89:G99),0) -> -1067 | H100: =IFERROR(SUM(H89:H99),0) -> -1732 | I100: =IFERROR(SUM(I89:I99),0) -> -1062 | J100: =IFERROR(SUM(J89:J99),0) -> -4971 | ... L100: =IFERROR(SUM(L89:L99),0) -> -3473
B102: Financing Activities
B103: Proceeds from shares | C103: =IFERROR('Cash Flow Data'!E26,0) -> 0 | D103: =IFERROR('Cash Flow Data'!F26,0) -> 0 | E103: =IFERROR('Cash Flow Data'!G26,0) -> 0 | F103: =IFERROR('Cash Flow Data'!H26,0) -> 0 | G103: =IFERROR('Cash Flow Data'!I26,0) -> 0 | H103: =IFERROR('Cash Flow Data'!J26,0) -> 0 | I103: =IFERROR('Cash Flow Data'!K26,0) -> 0 | J103: =IFERROR('Cash Flow Data'!L26,0) -> 0 | ... L103: =IFERROR('Cash Flow Data'!N26,0) -> 0
B104: Proceeds from borrowings | C104: 0 | D104: 0 | E104: 0 | F104: 0 | G104: 0 | H104: 0 | I104: 0 | J104: 0 | K104: 0 | L104: 0
B105: Repayment of borrowings | C105: 0 | D105: 0 | E105: 0 | F105: 0 | G105: 0 | H105: 0 | I105: 0 | J105: 0 | K105: 0 | L105: 0
B106: Proceeds from deposits | C106: 0 | D106: 0 | E106: 0 | F106: 0 | G106: 0 | H106: 0 | I106: 0 | J106: 0 | K106: 0 | L106: 0
B107: Interest paid fin | C107: =IFERROR('Cash Flow Data'!E27,0) -> 0 | D107: =IFERROR('Cash Flow Data'!F27,0) -> 0 | E107: =IFERROR('Cash Flow Data'!G27,0) -> -3 | F107: =IFERROR('Cash Flow Data'!H27,0) -> -80 | G107: =IFERROR('Cash Flow Data'!I27,0) -> -86 | H107: =IFERROR('Cash Flow Data'!J27,0) -> -77 | I107: =IFERROR('Cash Flow Data'!K27,0) -> -76 | J107: =IFERROR('Cash Flow Data'!L27,0) -> -98 | ... L107: =IFERROR('Cash Flow Data'!N27,0) -> -117
B108: Dividends paid | C108: =IFERROR('Cash Flow Data'!E28,0) -> -3561 | D108: =IFERROR('Cash Flow Data'!F28,0) -> -3896 | E108: =IFERROR('Cash Flow Data'!G28,0) -> -4546 | F108: =IFERROR('Cash Flow Data'!H28,0) -> -5196 | G108: =IFERROR('Cash Flow Data'!I28,0) -> -8811 | H108: =IFERROR('Cash Flow Data'!J28,0) -> -7519 | I108: =IFERROR('Cash Flow Data'!K28,0) -> -8459 | J108: =IFERROR('Cash Flow Data'!L28,0) -> -9398 | ... L108: =IFERROR('Cash Flow Data'!N28,0) -> -10103
B109: Financial liabilities | C109: =IFERROR('Cash Flow Data'!E29,0) -> 0 | D109: =IFERROR('Cash Flow Data'!F29,0) -> 0 | E109: =IFERROR('Cash Flow Data'!G29,0) -> 0 | F109: =IFERROR('Cash Flow Data'!H29,0) -> -352 | G109: =IFERROR('Cash Flow Data'!I29,0) -> -383 | H109: =IFERROR('Cash Flow Data'!J29,0) -> -388 | I109: =IFERROR('Cash Flow Data'!K29,0) -> -431 | J109: =IFERROR('Cash Flow Data'!L29,0) -> -394 | ... L109: =IFERROR('Cash Flow Data'!N29,0) -> -464
B110: Application money refund | C110: 0 | D110: 0 | E110: 0 | F110: 0 | G110: 0 | H110: 0 | I110: 0 | J110: 0 | K110: 0 | L110: 0
B111: Other financing items | C111: =IFERROR('Cash Flow Data'!E30,0) -> -703 | D111: =IFERROR('Cash Flow Data'!F30,0) -> -755 | E111: =IFERROR('Cash Flow Data'!G30,0) -> -913 | F111: =IFERROR('Cash Flow Data'!H30,0) -> -1048 | G111: =IFERROR('Cash Flow Data'!I30,0) -> 0 | H111: =IFERROR('Cash Flow Data'!J30,0) -> 0 | I111: =IFERROR('Cash Flow Data'!K30,0) -> 0 | J111: =IFERROR('Cash Flow Data'!L30,0) -> 0 | ... L111: =IFERROR('Cash Flow Data'!N30,0) -> 0
B112: Cash from Financing Activities | C112: =IFERROR(SUM(C103:C111),0) -> -4264 | D112: =IFERROR(SUM(D103:D111),0) -> -4651 | E112: =IFERROR(SUM(E103:E111),0) -> -5462 | F112: =IFERROR(SUM(F103:F111),0) -> -6676 | G112: =IFERROR(SUM(G103:G111),0) -> -9280 | H112: =IFERROR(SUM(H103:H111),0) -> -7984 | I112: =IFERROR(SUM(I103:I111),0) -> -8966 | J112: =IFERROR(SUM(J103:J111),0) -> -9890 | ... L112: =IFERROR(SUM(L103:L111),0) -> -10684
B114: Net Cash Flow | C114: =IFERROR(SUM(C112,C100,C86),0) -> -63 | D114: =IFERROR(SUM(D112,D100,D86),0) -> 1 | E114: =IFERROR(SUM(E112,E100,E86),0) -> 2 | F114: =IFERROR(SUM(F112,F100,F86),0) -> 2555 | G114: =IFERROR(SUM(G112,G100,G86),0) -> -1390 | H114: =IFERROR(SUM(H112,H100,H86),0) -> -752 | I114: =IFERROR(SUM(I112,I100,I86),0) -> -402 | J114: =IFERROR(SUM(J112,J100,J86),0) -> 23 | ... L114: =IFERROR(SUM(L112,L100,L86),0) -> -3661

Sheet Ratio Analysis
B2: ="Ratio Analysis - " & 'Data Sheet'!B1 -> Ratio Analysis - HINDUSTAN UNILEVER LTD
B3: Years | C3: =IFERROR('Data Sheet'!B16,0) -> 42825 | D3: =IFERROR('Data Sheet'!C16,0) -> 43190 | E3: =IFERROR('Data Sheet'!D16,0) -> 43555 | F3: =IFERROR('Data Sheet'!E16,0) -> 43921 | G3: =IFERROR('Data Sheet'!F16,0) -> 44286 | H3: =IFERROR('Data Sheet'!G16,0) -> 44651 | I3: =IFERROR('Data Sheet'!H16,0) -> 45016 | J3: =IFERROR('Data Sheet'!I16,0) -> 45382 | ... L3: =IFERROR('Data Sheet'!K16,0) -> 46112 | M3: LTM | N3: Trend | O3: Mean | P3: Median
B5: Sales growth | D5: =IFERROR(HistoricalFS!D7,0) -> 0.071859357 | E5: =IFERROR(HistoricalFS!E7,0) -> 0.10592207 | F5: =IFERROR(HistoricalFS!F7,0) -> 0.012032562 | G5: =IFERROR(HistoricalFS!G7,0) -> 0.18211296 | H5: =IFERROR(HistoricalFS!H7,0) -> 0.11520796 | I5: =IFERROR(HistoricalFS!I7,0) -> 0.15509286 | J5: =IFERROR(HistoricalFS!J7,0) -> 0.021723341 | K5: =IFERROR(HistoricalFS!K7,0) -> -0.0091766835 | L5: =IFERROR(HistoricalFS!L7,0) -> 0.051200104 | O5: =IFERROR(AVERAGE(D5:L5),0) -> 0.078441615 | P5: =IFERROR(MEDIAN(C5:L5),0) -> 0.071859357
B6: EBITDA growth | D6: =IFERROR(HistoricalFS!D21/HistoricalFS!C21-1,0) -> 0.11169891 | E6: =IFERROR(HistoricalFS!E21/HistoricalFS!D21-1,0) -> 0.21060503 | F6: =IFERROR(HistoricalFS!F21/HistoricalFS!E21-1,0) -> 0.083221024 | G6: =IFERROR(HistoricalFS!G21/HistoricalFS!F21-1,0) -> 0.12141006 | H6: =IFERROR(HistoricalFS!H21/HistoricalFS!G21-1,0) -> 0.18463388 | I6: =IFERROR(HistoricalFS!I21/HistoricalFS!H21-1,0) -> 0.09240615 | J6: =IFERROR(HistoricalFS!J21/HistoricalFS!I21-1,0) -> 0.045724084 | K6: =IFERROR(HistoricalFS!K21/HistoricalFS!J21-1,0) -> -0.012912482 | L6: =IFERROR(HistoricalFS!L21/HistoricalFS!K21-1,0) -> -0.018480066 | O6: =IFERROR(AVERAGE(D6:L6),0) -> 0.090922954 | P6: =IFERROR(MEDIAN(C6:L6),0) -> 0.09240615
B7: EBIT growth | D7: =IFERROR((HistoricalFS!D21-HistoricalFS!D27)/(HistoricalFS!C21-HistoricalFS!C27)-1,0) -> 0.10527167 | E7: =IFERROR((HistoricalFS!E21-HistoricalFS!E27)/(HistoricalFS!D21-HistoricalFS!D27)-1,0) -> 0.22004389 | F7: =IFERROR((HistoricalFS!F21-HistoricalFS!F27)/(HistoricalFS!E21-HistoricalFS!E27)-1,0) -> 0.03645521 | G7: =IFERROR((HistoricalFS!G21-HistoricalFS!G27)/(HistoricalFS!F21-HistoricalFS!F27)-1,0) -> 0.12715492 | H7: =IFERROR((HistoricalFS!H21-HistoricalFS!H27)/(HistoricalFS!G21-HistoricalFS!G27)-1,0) -> 0.20324369 | I7: =IFERROR((HistoricalFS!I21-HistoricalFS!I27)/(HistoricalFS!H21-HistoricalFS!H27)-1,0) -> 0.097082409 | J7: =IFERROR((HistoricalFS!J21-HistoricalFS!J27)/(HistoricalFS!I21-HistoricalFS!I27)-1,0) -> 0.043623639 | K7: =IFERROR((HistoricalFS!K21-HistoricalFS!K27)/(HistoricalFS!J21-HistoricalFS!J27)-1,0) -> -0.016839282 | L7: =IFERROR((HistoricalFS!L21-HistoricalFS!L27)/(HistoricalFS!K21-HistoricalFS!K27)-1,0) -> -0.02629784 | O7: =IFERROR(AVERAGE(D7:L7),0) -> 0.087748701 | P7: =IFERROR(MEDIAN(C7:L7),0) -> 0.097082409
B8: Net profit growth | D8: =IFERROR(HistoricalFS!D39/HistoricalFS!C39-1,0) -> 0.06383424 | E8: =IFERROR(HistoricalFS!E39/HistoricalFS!D39-1,0) -> 0.19693095 | F8: =IFERROR(HistoricalFS!F39/HistoricalFS!E39-1,0) -> 0.07495069 | G8: =IFERROR(HistoricalFS!G39/HistoricalFS!F39-1,0) -> 0.099235474 | H8: =IFERROR(HistoricalFS!H39/HistoricalFS!G39-1,0) -> 0.23076923 | I8: =IFERROR(HistoricalFS!I39/HistoricalFS!H39-1,0) -> 0.12940778 | J8: =IFERROR(HistoricalFS!J39/HistoricalFS!I39-1,0) -> 0.026718703 | K8: =IFERROR(HistoricalFS!K39/HistoricalFS!J39-1,0) -> 0.015692008 | L8: =IFERROR(HistoricalFS!L39/HistoricalFS!K39-1,0) -> 0.3627291 | O8: =IFERROR(AVERAGE(D8:L8),0) -> 0.13336313 | P8: =IFERROR(MEDIAN(C8:L8),0) -> 0.099235474
B9: Dividend growth | D9: =IFERROR(HistoricalFS!D47/HistoricalFS!C47-1,0) -> 0.17636188 | E9: =IFERROR(HistoricalFS!E47/HistoricalFS!D47-1,0) -> 0.099898369 | F9: =IFERROR(HistoricalFS!F47/HistoricalFS!E47-1,0) -> 0.13631114 | G9: =IFERROR(HistoricalFS!G47/HistoricalFS!F47-1,0) -> 0.6238764 | H9: =IFERROR(HistoricalFS!H47/HistoricalFS!G47-1,0) -> -0.16049383 | I9: =IFERROR(HistoricalFS!I47/HistoricalFS!H47-1,0) -> 0.14705882 | J9: =IFERROR(HistoricalFS!J47/HistoricalFS!I47-1,0) -> 0.076923077 | K9: =IFERROR(HistoricalFS!K47/HistoricalFS!J47-1,0) -> 0.26190476 | L9: =IFERROR(HistoricalFS!L47/HistoricalFS!K47-1,0) -> -0.22641509 | O9: =IFERROR(AVERAGE(D9:L9),0) -> 0.12615839 | P9: =IFERROR(MEDIAN(C9:L9),0) -> 0.13631114
B11: Gross margin | C11: =IFERROR(HistoricalFS!C13,0) -> 0.49810024 | D11: =IFERROR(HistoricalFS!D13,0) -> 0.50490927 | E11: =IFERROR(HistoricalFS!E13,0) -> 0.51203256 | F11: =IFERROR(HistoricalFS!F13,0) -> 0.52215771 | G11: =IFERROR(HistoricalFS!G13,0) -> 0.49491792 | H11: =IFERROR(HistoricalFS!H13,0) -> 0.49347901 | I11: =IFERROR(HistoricalFS!I13,0) -> 0.46059756 | J11: =IFERROR(HistoricalFS!J13,0) -> 0.50458834 | ... L11: =IFERROR(HistoricalFS!L13,0) -> 0.48320097 | O11: =IFERROR(AVERAGE(C11:L11),0) -> 0.49714888 | P11: =IFERROR(MEDIAN(C11:L11),0) -> 0.49780273
B12: EBITDA margin | C12: =IFERROR(HistoricalFS!C22,0) -> 0.19950546 | D12: =IFERROR(HistoricalFS!D22,0) -> 0.2069208 | E12: =IFERROR(HistoricalFS!E22,0) -> 0.22650725 | F12: =IFERROR(HistoricalFS!F22,0) -> 0.24244024 | G12: =IFERROR(HistoricalFS!G22,0) -> 0.22999064 | H12: =IFERROR(HistoricalFS!H22,0) -> 0.24430843 | I12: =IFERROR(HistoricalFS!I22,0) -> 0.23104985 | J12: =IFERROR(HistoricalFS!J22,0) -> 0.23647732 | ... L12: =IFERROR(HistoricalFS!L22,0) -> 0.2199696 | O12: =IFERROR(AVERAGE(C12:L12),0) -> 0.22727553 | P12: =IFERROR(MEDIAN(C12:L12),0) -> 0.23052025
B13: EBIT margin | C13: =IFERROR((HistoricalFS!C21-HistoricalFS!C27)/HistoricalFS!C6,0) -> 0.1864785 | D13: =IFERROR((HistoricalFS!D21-HistoricalFS!D27)/HistoricalFS!D6,0) -> 0.19229146 | E13: =IFERROR((HistoricalFS!E21-HistoricalFS!E27)/HistoricalFS!E6,0) -> 0.21213432 | F13: =IFERROR((HistoricalFS!F21-HistoricalFS!F27)/HistoricalFS!F6,0) -> 0.2172536 | G13: =IFERROR((HistoricalFS!G21-HistoricalFS!G27)/HistoricalFS!G6,0) -> 0.20715319 | H13: =IFERROR((HistoricalFS!H21-HistoricalFS!H27)/HistoricalFS!H6,0) -> 0.22350608 | I13: =IFERROR((HistoricalFS!I21-HistoricalFS!I27)/HistoricalFS!I6,0) -> 0.21228128 | J13: =IFERROR((HistoricalFS!J21-HistoricalFS!J27)/HistoricalFS!J6,0) -> 0.21683146 | ... L13: =IFERROR((HistoricalFS!L21-HistoricalFS!L27)/HistoricalFS!L6,0) -> 0.19929267 | O13: =IFERROR(AVERAGE(C13:L13),0) -> 0.20823771 | P13: =IFERROR(MEDIAN(C13:L13),0) -> 0.2122078
B14: EBT margin | C14: =IFERROR(HistoricalFS!C34,0) -> 0.203697 | D14: =IFERROR(HistoricalFS!D34,0) -> 0.20149107 | E14: =IFERROR(HistoricalFS!E34,0) -> 0.21948614 | F14: =IFERROR(HistoricalFS!F34,0) -> 0.22494533 | G14: =IFERROR(HistoricalFS!G34,0) -> 0.20828017 | H14: =IFERROR(HistoricalFS!H34,0) -> 0.22566068 | I14: =IFERROR(HistoricalFS!I34,0) -> 0.21779465 | J14: =IFERROR(HistoricalFS!J34,0) -> 0.22463487 | ... L14: =IFERROR(HistoricalFS!L34,0) -> 0.2692964 | O14: =IFERROR(AVERAGE(C14:L14),0) -> 0.22263227 | P14: =IFERROR(MEDIAN(C14:L14),0) -> 0.2220605
B15: Net Profit margin | C15: =IFERROR(HistoricalFS!C40,0) -> 0.14408057 | D15: =IFERROR(HistoricalFS!D40,0) -> 0.14300183 | E15: =IFERROR(HistoricalFS!E40,0) -> 0.15476978 | F15: =IFERROR(HistoricalFS!F40,0) -> 0.16439183 | G15: =IFERROR(HistoricalFS!G40,0) -> 0.15286638 | H15: =IFERROR(HistoricalFS!H40,0) -> 0.16870686 | I15: =IFERROR(HistoricalFS!I40,0) -> 0.16495543 | J15: =IFERROR(HistoricalFS!J40,0) -> 0.16576192 | ... L15: =IFERROR(HistoricalFS!L40,0) -> 0.22027983 | O15: =IFERROR(AVERAGE(C15:L15),0) -> 0.16487368 | P15: =IFERROR(MEDIAN(C15:L15),0) -> 0.16467363
B17: SalesExpenses%sales | C17: =IFERROR(HistoricalFS!C19,0) -> 0.24603462 | D17: =IFERROR(HistoricalFS!D19,0) -> 0.24566043 | E17: =IFERROR(HistoricalFS!E19,0) -> 0.23782752 | F17: =IFERROR(HistoricalFS!F19,0) -> 0.23396928 | G17: =IFERROR(HistoricalFS!G19,0) -> 0.21478694 | H17: =IFERROR(HistoricalFS!H19,0) -> 0.20064447 | I17: =IFERROR(HistoricalFS!I19,0) -> 0.18243645 | J17: =IFERROR(HistoricalFS!J19,0) -> 0.21949722 | ... L17: =IFERROR(HistoricalFS!L19,0) -> 0.21398213 | O17: =IFERROR(AVERAGE(C17:L17),0) -> 0.2208624 | P17: =IFERROR(MEDIAN(C17:L17),0) -> 0.21714208
B18: Depreciation%sales | C18: =IFERROR(HistoricalFS!C28,0) -> 0.013026959 | D18: =IFERROR(HistoricalFS!D28,0) -> 0.014629343 | E18: =IFERROR(HistoricalFS!E28,0) -> 0.014372933 | F18: =IFERROR(HistoricalFS!F28,0) -> 0.025186638 | G18: =IFERROR(HistoricalFS!G28,0) -> 0.022837459 | H18: =IFERROR(HistoricalFS!H28,0) -> 0.020802349 | I18: =IFERROR(HistoricalFS!I28,0) -> 0.01876857 | J18: =IFERROR(HistoricalFS!J28,0) -> 0.019645858 | ... L18: =IFERROR(HistoricalFS!L28,0) -> 0.020676925 | O18: =IFERROR(AVERAGE(C18:L18),0) -> 0.019037816 | P18: =IFERROR(MEDIAN(C18:L18),0) -> 0.020038491
B19: OperatingIncome%sales | C19: =C13 -> 0.1864785 | D19: =D13 -> 0.19229146 | E19: =E13 -> 0.21213432 | F19: =F13 -> 0.2172536 | G19: =G13 -> 0.20715319 | H19: =H13 -> 0.22350608 | I19: =I13 -> 0.21228128 | J19: =J13 -> 0.21683146 | ... L19: =L13 -> 0.19929267 | O19: =IFERROR(AVERAGE(C19:L19),0) -> 0.20823771 | P19: =IFERROR(MEDIAN(C19:L19),0) -> 0.2122078
B21: Return on Capital Employed | C21: =IFERROR((HistoricalFS!C21-HistoricalFS!C27)/(SUM(HistoricalFS!C54:C56)),0) -> 0.88078621 | D21: =IFERROR((HistoricalFS!D21-HistoricalFS!D27)/(SUM(HistoricalFS!D54:D56)),0) -> 0.93874468 | E21: =IFERROR((HistoricalFS!E21-HistoricalFS!E27)/(SUM(HistoricalFS!E54:E56)),0) -> 1.046824 | F21: =IFERROR((HistoricalFS!F21-HistoricalFS!F27)/(SUM(HistoricalFS!F54:F56)),0) -> 1.0503099 | G21: =IFERROR((HistoricalFS!G21-HistoricalFS!G27)/(SUM(HistoricalFS!G54:G56)),0) -> 0.20434618 | H21: =IFERROR((HistoricalFS!H21-HistoricalFS!H27)/(SUM(HistoricalFS!H54:H56)),0) -> 0.23395338 | I21: =IFERROR((HistoricalFS!I21-HistoricalFS!I27)/(SUM(HistoricalFS!I54:I56)),0) -> 0.24959727 | J21: =IFERROR((HistoricalFS!J21-HistoricalFS!J27)/(SUM(HistoricalFS!J54:J56)),0) -> 0.25465827 | ... L21: =IFERROR((HistoricalFS!L21-HistoricalFS!L27)/(SUM(HistoricalFS!L54:L56)),0) -> 0.25584961 | O21: =IFERROR(AVERAGE(C21:L21),0) -> 0.53735416 | P21: =IFERROR(MEDIAN(C21:L21),0) -> 0.25716085
B22: Retained earnings % | C22: =HistoricalFS!C50 -> 0.23147761 | D22: =HistoricalFS!D50 -> 0.1501082 | E22: =HistoricalFS!E50 -> 0.21893491 | F22: =HistoricalFS!F50 -> 0.17431193 | G22: =HistoricalFS!G50 -> 0 | H22: =HistoricalFS!H50 -> 0.096971067 | I22: =HistoricalFS!I50 -> 0.082858001 | J22: =HistoricalFS!J50 -> 0.038011696 | ... L22: =HistoricalFS!L50 -> 0.32152665 | O22: =IFERROR(AVERAGE(C22:L22),0) -> 0.13142001 | P22: =IFERROR(MEDIAN(C22:L22),0) -> 0.12353964
B23: Return on equity % | C23: =IFERROR(HistoricalFS!C39/SUM(HistoricalFS!C54:C55),0) -> 0.70848161 | D23: =IFERROR(HistoricalFS!D39/SUM(HistoricalFS!D54:D55),0) -> 0.69811839 | E23: =IFERROR(HistoricalFS!E39/SUM(HistoricalFS!E54:E55),0) -> 0.77335706 | F23: =IFERROR(HistoricalFS!F39/SUM(HistoricalFS!F54:F55),0) -> 0.79475027 | G23: =IFERROR(HistoricalFS!G39/SUM(HistoricalFS!G54:G55),0) -> 0.15079498 | H23: =IFERROR(HistoricalFS!H39/SUM(HistoricalFS!H54:H55),0) -> 0.18034692 | I23: =IFERROR(HistoricalFS!I39/SUM(HistoricalFS!I54:I55),0) -> 0.19865219 | J23: =IFERROR(HistoricalFS!J39/SUM(HistoricalFS!J54:J55),0) -> 0.2003202 | ... L23: =IFERROR(HistoricalFS!L39/SUM(HistoricalFS!L54:L55),0) -> 0.29136831 | O23: =IFERROR(AVERAGE(C23:L23),0) -> 0.42071328 | P23: =IFERROR(MEDIAN(C23:L23),0) -> 0.25115559
B24: Self sustained growth rate | C24: =IFERROR(C22*C23,0) -> 0.16399763 | D24: =IFERROR(D22*D23,0) -> 0.1047933 | E24: =IFERROR(E22*E23,0) -> 0.16931486 | F24: =IFERROR(F22*F23,0) -> 0.13853445 | G24: =IFERROR(G22*G23,0) -> 0 | H24: =IFERROR(H22*H23,0) -> 0.017488433 | I24: =IFERROR(I22*I23,0) -> 0.016459924 | J24: =IFERROR(J22*J23,0) -> 0.0076145105 | ... L24: =IFERROR(L22*L23,0) -> 0.093682677 | O24: =IFERROR(AVERAGE(C24:L24),0) -> 0.071188578 | P24: =IFERROR(MEDIAN(C24:L24),0) -> 0.055585555
B25: Interest Coverage ratio | C25: =IFERROR((HistoricalFS!C21-HistoricalFS!C27)/HistoricalFS!C24,0) -> 176.68571 | D25: =IFERROR((HistoricalFS!D21-HistoricalFS!D27)/HistoricalFS!D24,0) -> 262.88462 | E25: =IFERROR((HistoricalFS!E21-HistoricalFS!E27)/HistoricalFS!E24,0) -> 252.69697 | F25: =IFERROR((HistoricalFS!F21-HistoricalFS!F27)/HistoricalFS!F24,0) -> 73.245763 | G25: =IFERROR((HistoricalFS!G21-HistoricalFS!G27)/HistoricalFS!G24,0) -> 83.264957 | H25: =IFERROR((HistoricalFS!H21-HistoricalFS!H27)/HistoricalFS!H24,0) -> 110.58491 | I25: =IFERROR((HistoricalFS!I21-HistoricalFS!I27)/HistoricalFS!I24,0) -> 112.80702 | J25: =IFERROR((HistoricalFS!J21-HistoricalFS!J27)/HistoricalFS!J24,0) -> 40.182635 | ... L25: =IFERROR((HistoricalFS!L21-HistoricalFS!L27)/HistoricalFS!L24,0) -> 31.336585 | O25: =IFERROR(AVERAGE(C25:L25),0) -> 117.83217 | P25: =IFERROR(MEDIAN(C25:L25),0) -> 96.924931
B27: Debtor Turnover ratio | C27: =IFERROR(HistoricalFS!C6/HistoricalFS!C66,0) -> 30.564055 | D27: =IFERROR(HistoricalFS!D6/HistoricalFS!D66,0) -> 27.133588 | E27: =IFERROR(HistoricalFS!E6/HistoricalFS!E66,0) -> 21.646476 | F27: =IFERROR(HistoricalFS!F6/HistoricalFS!F66,0) -> 34.624021 | G27: =IFERROR(HistoricalFS!G6/HistoricalFS!G66,0) -> 26.750853 | H27: =IFERROR(HistoricalFS!H6/HistoricalFS!H66,0) -> 23.455277 | I27: =IFERROR(HistoricalFS!I6/HistoricalFS!I66,0) -> 19.675219 | J27: =IFERROR(HistoricalFS!J6/HistoricalFS!J66,0) -> 20.652653 | ... L27: =IFERROR(HistoricalFS!L6/HistoricalFS!L66,0) -> 19.079017 | O27: =IFERROR(AVERAGE(C27:L27),0) -> 23.963981 | P27: =IFERROR(MEDIAN(C27:L27),0) -> 22.550877
B28: Creditor Turnover ratio | C28: =IFERROR(HistoricalFS!C9/HistoricalFS!C57,0) -> 1.9164076 | D28: =IFERROR(HistoricalFS!D9/HistoricalFS!D57,0) -> 1.6631698 | E28: =IFERROR(HistoricalFS!E9/HistoricalFS!E57,0) -> 1.7989309 | F28: =IFERROR(HistoricalFS!F9/HistoricalFS!F57,0) -> 1.5942637 | G28: =IFERROR(HistoricalFS!G9/HistoricalFS!G57,0) -> 1.1275515 | H28: =IFERROR(HistoricalFS!H9/HistoricalFS!H57,0) -> 1.3020782 | I28: =IFERROR(HistoricalFS!I9/HistoricalFS!I57,0) -> 1.5160527 | J28: =IFERROR(HistoricalFS!J9/HistoricalFS!J57,0) -> 1.1891263 | ... L28: =IFERROR(HistoricalFS!L9/HistoricalFS!L57,0) -> 1.1285864 | O28: =IFERROR(AVERAGE(C28:L28),0) -> 1.4305719 | P28: =IFERROR(MEDIAN(C28:L28),0) -> 1.4090655
B29: Inventory Turnover ratio | C29: =IFERROR(HistoricalFS!C9/HistoricalFS!C67,0) -> 6.5501771 | D29: =IFERROR(HistoricalFS!D9/HistoricalFS!D67,0) -> 7.0027855 | E29: =IFERROR(HistoricalFS!E9/HistoricalFS!E67,0) -> 7.4522145 | F29: =IFERROR(HistoricalFS!F9/HistoricalFS!F67,0) -> 6.8702566 | G29: =IFERROR(HistoricalFS!G9/HistoricalFS!G67,0) -> 6.63677 | H29: =IFERROR(HistoricalFS!H9/HistoricalFS!H67,0) -> 6.4855957 | I29: =IFERROR(HistoricalFS!I9/HistoricalFS!I67,0) -> 7.6868972 | J29: =IFERROR(HistoricalFS!J9/HistoricalFS!J67,0) -> 7.6240676 | ... L29: =IFERROR(HistoricalFS!L9/HistoricalFS!L67,0) -> 6.9569848 | O29: =IFERROR(AVERAGE(C29:L29),0) -> 7.0245817 | P29: =IFERROR(MEDIAN(C29:L29),0) -> 6.9685264
B30: Fixed Asset Turnover ratio | C30: =IFERROR(HistoricalFS!C6/HistoricalFS!C60,0) -> 7.5044128 | D30: =IFERROR(HistoricalFS!D6/AVERAGE(HistoricalFS!C60:D60),0) -> 7.9456801 | E30: =IFERROR(HistoricalFS!E6/AVERAGE(HistoricalFS!D60:E60),0) -> 8.5058964 | F30: =IFERROR(HistoricalFS!F6/AVERAGE(HistoricalFS!E60:F60),0) -> 7.8051795 | G30: =IFERROR(HistoricalFS!G6/AVERAGE(HistoricalFS!F60:G60),0) -> 1.6523664 | H30: =IFERROR(HistoricalFS!H6/AVERAGE(HistoricalFS!G60:H60),0) -> 1.0192001 | I30: =IFERROR(HistoricalFS!I6/AVERAGE(HistoricalFS!H60:I60),0) -> 1.163311 | J30: =IFERROR(HistoricalFS!J6/AVERAGE(HistoricalFS!I60:J60),0) -> 1.1632181 | K30: =IFERROR(HistoricalFS!K6/AVERAGE(HistoricalFS!J60:K60),0) -> 1.1348736 | L30: =IFERROR(HistoricalFS!L6/AVERAGE(HistoricalFS!K60:L60),0) -> 1.1536555 | O30: =IFERROR(AVERAGE(C30:L30),0) -> 3.9047793 | P30: =IFERROR(MEDIAN(C30:L30),0) -> 1.4078387
B31: Capital Turnover ratio | C31: =IFERROR(HistoricalFS!C6/SUM(HistoricalFS!C54:C55),0) -> 4.9172598 | D31: =IFERROR(HistoricalFS!D6/SUM(HistoricalFS!D54:D55),0) -> 4.8818844 | E31: =IFERROR(HistoricalFS!E6/SUM(HistoricalFS!E54:E55),0) -> 4.9968222 | F31: =IFERROR(HistoricalFS!F6/SUM(HistoricalFS!F54:F55),0) -> 4.8344878 | G31: =IFERROR(HistoricalFS!G6/SUM(HistoricalFS!G54:G55),0) -> 0.98644964 | H31: =IFERROR(HistoricalFS!H6/SUM(HistoricalFS!H54:H55),0) -> 1.0689957 | I31: =IFERROR(HistoricalFS!I6/SUM(HistoricalFS!I54:I55),0) -> 1.204278 | J31: =IFERROR(HistoricalFS!J6/SUM(HistoricalFS!J54:J55),0) -> 1.2084814 | ... L31: =IFERROR(HistoricalFS!L6/SUM(HistoricalFS!L54:L55),0) -> 1.322719 | O31: =IFERROR(AVERAGE(C31:L31),0) -> 2.6662785 | P31: =IFERROR(MEDIAN(C31:L31),0) -> 1.2820631
B33: (in days)
B34: Debtors days | C34: =IFERROR(365/C27,0) -> 11.942133 | D34: =IFERROR(365/D27,0) -> 13.451962 | E34: =IFERROR(365/E27,0) -> 16.861867 | F34: =IFERROR(365/F27,0) -> 10.541814 | G34: =IFERROR(365/G27,0) -> 13.644425 | H34: =IFERROR(365/H27,0) -> 15.56153 | I34: =IFERROR(365/I27,0) -> 18.551255 | J34: =IFERROR(365/J27,0) -> 17.673275 | ... L34: =IFERROR(365/L27,0) -> 19.130964 | O34: =IFERROR(AVERAGE(C34:L34),0) -> 16.00884 | P34: =IFERROR(MEDIAN(C34:L34),0) -> 16.211699
B35: Payable days | C35: =IFERROR(365/C28,0) -> 190.46053 | D35: =IFERROR(365/D28,0) -> 219.46045 | E35: =IFERROR(365/E28,0) -> 202.89829 | F35: =IFERROR(365/F28,0) -> 228.94582 | G35: =IFERROR(365/G28,0) -> 323.71027 | H35: =IFERROR(365/H28,0) -> 280.3211 | I35: =IFERROR(365/I28,0) -> 240.7568 | J35: =IFERROR(365/J28,0) -> 306.94805 | ... L35: =IFERROR(365/L28,0) -> 323.41342 | O35: =IFERROR(AVERAGE(C35:L35),0) -> 265.81791 | P35: =IFERROR(MEDIAN(C35:L35),0) -> 260.53895
B36: Inventory days | C36: =IFERROR(365/C29,0) -> 55.723684 | D36: =IFERROR(365/D29,0) -> 52.122116 | E36: =IFERROR(365/E29,0) -> 48.97873 | F36: =IFERROR(365/F29,0) -> 53.127564 | G36: =IFERROR(365/G29,0) -> 54.996632 | H36: =IFERROR(365/H29,0) -> 56.278562 | I36: =IFERROR(365/I29,0) -> 47.483398 | J36: =IFERROR(365/J29,0) -> 47.874706 | ... L36: =IFERROR(365/L29,0) -> 52.465258 | O36: =IFERROR(AVERAGE(C36:L36),0) -> 52.134241 | P36: =IFERROR(MEDIAN(C36:L36),0) -> 52.378506
B37: Cash Conversion Cycle | C37: =IFERROR(SUM(C36,C34)-C35,0) -> -122.79471 | D37: =IFERROR(SUM(D36,D34)-D35,0) -> -153.88637 | E37: =IFERROR(SUM(E36,E34)-E35,0) -> -137.05769 | F37: =IFERROR(SUM(F36,F34)-F35,0) -> -165.27644 | G37: =IFERROR(SUM(G36,G34)-G35,0) -> -255.06921 | H37: =IFERROR(SUM(H36,H34)-H35,0) -> -208.48101 | I37: =IFERROR(SUM(I36,I34)-I35,0) -> -174.72215 | J37: =IFERROR(SUM(J36,J34)-J35,0) -> -241.40007 | ... L37: =IFERROR(SUM(L36,L34)-L35,0) -> -251.8172 | O37: =IFERROR(AVERAGE(C37:L37),0) -> -197.67483 | P37: =IFERROR(MEDIAN(C37:L37),0) -> -191.60158
B39: CFO/Sales | C39: =IFERROR(HistoricalFS!C86/HistoricalFS!C6,0) -> 0.1493577 | D39: =IFERROR(HistoricalFS!D86/HistoricalFS!D6,0) -> 0.16635251 | E39: =IFERROR(HistoricalFS!E86/HistoricalFS!E6,0) -> 0.14571356 | F39: =IFERROR(HistoricalFS!F86/HistoricalFS!F6,0) -> 0.18362114 | G39: =IFERROR(HistoricalFS!G86/HistoricalFS!G6,0) -> 0.190461 | H39: =IFERROR(HistoricalFS!H86/HistoricalFS!H6,0) -> 0.17091866 | I39: =IFERROR(HistoricalFS!I86/HistoricalFS!I6,0) -> 0.15889733 | J39: =IFERROR(HistoricalFS!J86/HistoricalFS!J6,0) -> 0.24046788 | ... L39: =IFERROR(HistoricalFS!L86/HistoricalFS!L6,0) -> 0.16280946 | O39: =IFERROR(AVERAGE(C39:L39),0) -> 0.1757844 | P39: =IFERROR(MEDIAN(C39:L39),0) -> 0.16863559
B40: CFO/Total Assets | C40: =IFERROR(HistoricalFS!C86/HistoricalFS!C71,0) -> 0.31535719 | D40: =IFERROR(HistoricalFS!D86/HistoricalFS!D71,0) -> 0.33103796 | E40: =IFERROR(HistoricalFS!E86/HistoricalFS!E71,0) -> 0.30747759 | F40: =IFERROR(HistoricalFS!F86/HistoricalFS!F71,0) -> 0.36247705 | G40: =IFERROR(HistoricalFS!G86/HistoricalFS!G71,0) -> 0.13030259 | H40: =IFERROR(HistoricalFS!H86/HistoricalFS!H71,0) -> 0.12713812 | I40: =IFERROR(HistoricalFS!I86/HistoricalFS!I71,0) -> 0.13172407 | J40: =IFERROR(HistoricalFS!J86/HistoricalFS!J71,0) -> 0.18963167 | ... L40: =IFERROR(HistoricalFS!L86/HistoricalFS!L71,0) -> 0.13163109 | O40: =IFERROR(AVERAGE(C40:L40),0) -> 0.21721012 | P40: =IFERROR(MEDIAN(C40:L40),0) -> 0.16747777
B41: CFO/Total Debt | C41: =IFERROR(HistoricalFS!C86/HistoricalFS!C56,0) -> 17.880866 | D41: =IFERROR(HistoricalFS!D86/HistoricalFS!D56,0) -> 0 | E41: =IFERROR(HistoricalFS!E86/HistoricalFS!E56,0) -> 57.858586 | F41: =IFERROR(HistoricalFS!F86/HistoricalFS!F56,0) -> 0 | G41: =IFERROR(HistoricalFS!G86/HistoricalFS!G56,0) -> 0 | H41: =IFERROR(HistoricalFS!H86/HistoricalFS!H56,0) -> 8.5944391 | I41: =IFERROR(HistoricalFS!I86/HistoricalFS!I56,0) -> 7.8966366 | J41: =IFERROR(HistoricalFS!J86/HistoricalFS!J56,0) -> 10.02965 | ... L41: =IFERROR(HistoricalFS!L86/HistoricalFS!L56,0) -> 7.1014885 | O41: =IFERROR(AVERAGE(C41:L41),0) -> 11.640414 | P41: =IFERROR(MEDIAN(C41:L41),0) -> 7.4990625

Sheet Forecasting 
B3: ='Data Sheet'!B1& " - "& 'Data Sheet'!A17&" Forecasting " -> HINDUSTAN UNILEVER LTD - Sales Forecasting | G3: ='Data Sheet'!B1&" - "& HistoricalFS!B21&" Forecasting " -> HINDUSTAN UNILEVER LTD - EBITDA Forecasting | L3: ='Data Sheet'!B1& " - "&HistoricalFS!B44& " Forecasting " -> HINDUSTAN UNILEVER LTD - Earnings Per Share Forecasting
B4: Year Weight | C4: Year | D4: Sales | E4: Sales Growth | G4: Year Weight | H4: Year | I4: EBITDA | J4: EBITDA Growth | L4: Year Weight | M4: Year | N4: EPS | O4: EPS Growth
B5: 1 | C5: ='Data Sheet'!$B$16 -> 42825 | D5: {=TRANSPOSE('Data Sheet'!B17:K17)} -> 33162 | G5: 1 | H5: ='Data Sheet'!B16 -> 42825 | I5: {=TRANSPOSE(HistoricalFS!C21:L21)} -> 6616 | L5: 1 | M5: ='Data Sheet'!B16 -> 42825 | N5: {=IFERROR(TRANSPOSE(HistoricalFS!C44:L44),0)} -> 22.076422
B6: =B5+1 -> 2 | C6: =C5+365 -> 43190 | D6: 1365.06 | E6: =IFERROR(D6/D5-1,0) -> -0.95883662 | G6: =G5+1 -> 2 | H6: =H5+365 -> 43190 | I6: 7355 | J6: =IFERROR(I6/I5-1,0) -> 0.11169891 | L6: =L5+1 -> 2 | M6: =M5+365 -> 43190 | N6: 23.483483 | O6: =IFERROR(N6/N5-1,0) -> 0.063735942
B7: =B6+1 -> 3 | C7: =C6+365 -> 43555 | D7: 1430.59 | E7: =IFERROR(D7/D6-1,0) -> 0.048005216 | G7: =G6+1 -> 3 | H7: =H6+365 -> 43555 | I7: 8904 | J7: =IFERROR(I7/I6-1,0) -> 0.21060503 | L7: =L6+1 -> 3 | M7: =M6+365 -> 43555 | N7: 28.105511 | O7: =IFERROR(N7/N6-1,0) -> 0.19682036
B8: =B7+1 -> 4 | C8: =C7+365 -> 43920 | D8: 1437.57 | E8: =IFERROR(D8/D7-1,0) -> 0.0048791058 | G8: =G7+1 -> 4 | H8: =H7+365 -> 43920 | I8: 9645 | J8: =IFERROR(I8/I7-1,0) -> 0.083221024 | L8: =L7+1 -> 4 | M8: =M7+365 -> 43920 | N8: 30.210643 | O8: =IFERROR(N8/N7-1,0) -> 0.074901034
B9: =B8+1 -> 5 | C9: =C8+365 -> 44285 | D9: 1564.49 | E9: =IFERROR(D9/D8-1,0) -> 0.088287875 | G9: =G8+1 -> 5 | H9: =H8+365 -> 44285 | I9: 10816 | J9: =IFERROR(I9/I8-1,0) -> 0.12141006 | L9: =L8+1 -> 5 | M9: =M8+365 -> 44285 | N9: 30.596697 | O9: =IFERROR(N9/N8-1,0) -> 0.012778751
B10: =B9+1 -> 6 | C10: =C9+365 -> 44650 | D10: 2160.35 | E10: =IFERROR(D10/D9-1,0) -> 0.38086533 | G10: =G9+1 -> 6 | H10: =H9+365 -> 44650 | I10: 12813 | J10: =IFERROR(I10/I9-1,0) -> 0.18463388 | L10: =L9+1 -> 6 | M10: =M9+365 -> 44650 | N10: 37.657474 | O10: =IFERROR(N10/N9-1,0) -> 0.23076923
B11: =B10+1 -> 7 | C11: =C10+365 -> 45015 | D11: 2647.9 | E11: =IFERROR(D11/D10-1,0) -> 0.22568102 | G11: =G10+1 -> 7 | H11: =H10+365 -> 45015 | I11: 13997 | J11: =IFERROR(I11/I10-1,0) -> 0.09240615 | L11: =L10+1 -> 7 | M11: =M10+365 -> 45015 | N11: 42.530644 | O11: =IFERROR(N11/N10-1,0) -> 0.12940778
B12: =B11+1 -> 8 | C12: =C11+365 -> 45380 | D12: 2925.54 | E12: =IFERROR(D12/D11-1,0) -> 0.1048529 | G12: =G11+1 -> 8 | H12: =H11+365 -> 45380 | I12: 14637 | J12: =IFERROR(I12/I11-1,0) -> 0.045724084 | L12: =L11+1 -> 8 | M12: =M11+365 -> 45380 | N12: 43.667007 | O12: =IFERROR(N12/N11-1,0) -> 0.026718703
B13: =B12+1 -> 9 | C13: =C12+365 -> 45745 | D13: 3365.87 | E13: =IFERROR(D13/D12-1,0) -> 0.15051238 | G13: =G12+1 -> 9 | H13: =H12+365 -> 45745 | I13: 14448 | J13: =IFERROR(I13/I12-1,0) -> -0.012912482 | L13: =L12+1 -> 9 | M13: =M12+365 -> 45745 | N13: 44.35223 | O13: =IFERROR(N13/N12-1,0) -> 0.015692008
B14: =B13+1 -> 10 | C14: =C13+365 -> 46110 | D14: 4117.03 | E14: =IFERROR(D14/D13-1,0) -> 0.22316964 | G14: =G13+1 -> 10 | H14: =H13+365 -> 46110 | I14: 14181 | J14: =IFERROR(I14/I13-1,0) -> -0.018480066 | L14: =L13+1 -> 10 | M14: =M13+365 -> 46110 | N14: 60.440075 | O14: =IFERROR(N14/N13-1,0) -> 0.3627291
B15: =B14+1 -> 11 | C15: =C14+365 -> 46475 | D15: =IFERROR(FORECAST(B15,$D$5:$D$14,$B$5:$B$14),0) -> -2438.942 | E15: =IFERROR(D15/D14-1,0) -> -1.5924033 | G15: =G14+1 -> 11 | H15: =H14+365 -> 46475 | I15: =IFERROR(FORECAST(G15,$I$5:$I$14,$G$5:$G$14),0) -> 16723 | J15: =IFERROR(I15/I14-1,0) -> 0.17925393 | L15: =L14+1 -> 11 | M15: =M14+365 -> 46475 | N15: =IFERROR(FORECAST(L15,$N$5:$N$14,$L$5:$L$14),0) -> 56.751431 | O15: =IFERROR(N15/N14-1,0) -> -0.061029776
B16: =B15+1 -> 12 | C16: =C15+365 -> 46840 | D16: =IFERROR(FORECAST(B16,$D$5:$D$14,$B$5:$B$14),0) -> -3867.4115 | E16: =IFERROR(D16/D15-1,0) -> 0.58569226 | G16: =G15+1 -> 12 | H16: =H15+365 -> 46840 | I16: =IFERROR(FORECAST(G16,$I$5:$I$14,$G$5:$G$14),0) -> 17701.509 | J16: =IFERROR(I16/I15-1,0) -> 0.058512772 | L16: =L15+1 -> 12 | M16: =M15+365 -> 46840 | N16: =IFERROR(FORECAST(L16,$N$5:$N$14,$L$5:$L$14),0) -> 60.467687 | O16: =IFERROR(N16/N15-1,0) -> 0.065483049
B17: =B16+1 -> 13 | C17: =C16+365 -> 47205 | D17: =IFERROR(FORECAST(B17,$D$5:$D$14,$B$5:$B$14),0) -> -5295.8809 | E17: =IFERROR(D17/D16-1,0) -> 0.36936061 | G17: =G16+1 -> 13 | H17: =H16+365 -> 47205 | I17: =IFERROR(FORECAST(G17,$I$5:$I$14,$G$5:$G$14),0) -> 18680.018 | J17: =IFERROR(I17/I16-1,0) -> 0.055278286 | L17: =L16+1 -> 13 | M17: =M16+365 -> 47205 | N17: =IFERROR(FORECAST(L17,$N$5:$N$14,$L$5:$L$14),0) -> 64.183944 | O17: =IFERROR(N17/N16-1,0) -> 0.061458556
B18: =B17+1 -> 14 | C18: =C17+365 -> 47570 | D18: =IFERROR(FORECAST(B18,$D$5:$D$14,$B$5:$B$14),0) -> -6724.3504 | E18: =IFERROR(D18/D17-1,0) -> 0.26973217 | G18: =G17+1 -> 14 | H18: =H17+365 -> 47570 | I18: =IFERROR(FORECAST(G18,$I$5:$I$14,$G$5:$G$14),0) -> 19658.527 | J18: =IFERROR(I18/I17-1,0) -> 0.052382663 | L18: =L17+1 -> 14 | M18: =M17+365 -> 47570 | N18: =IFERROR(FORECAST(L18,$N$5:$N$14,$L$5:$L$14),0) -> 67.900201 | O18: =IFERROR(N18/N17-1,0) -> 0.057900099
B19: =B18+1 -> 15 | C19: =C18+365 -> 47935 | D19: =IFERROR(FORECAST(B19,$D$5:$D$14,$B$5:$B$14),0) -> -8152.8198 | E19: =IFERROR(D19/D18-1,0) -> 0.21243234 | G19: =G18+1 -> 15 | H19: =H18+365 -> 47935 | I19: =IFERROR(FORECAST(G19,$I$5:$I$14,$G$5:$G$14),0) -> 20637.036 | J19: =IFERROR(I19/I18-1,0) -> 0.0497753 | L19: =L18+1 -> 15 | M19: =M18+365 -> 47935 | N19: =IFERROR(FORECAST(L19,$N$5:$N$14,$L$5:$L$14),0) -> 71.616458 | O19: =IFERROR(N19/N18-1,0) -> 0.05473116

Sheet Common Size Income Statement
B2: ="Common Size Income Statement"&" - " &'Data Sheet'!$B$1 -> Common Size Income Statement - HINDUSTAN UNILEVER LTD
B4: Particulars | C4: ='Data Sheet'!B$16 -> 42825 | D4: ='Data Sheet'!C$16 -> 43190 | E4: ='Data Sheet'!D$16 -> 43555 | F4: ='Data Sheet'!E$16 -> 43921 | G4: ='Data Sheet'!F$16 -> 44286 | H4: ='Data Sheet'!G$16 -> 44651 | I4: ='Data Sheet'!H$16 -> 45016 | J4: ='Data Sheet'!I$16 -> 45382 | ... L4: ='Data Sheet'!K$16 -> 46112
B6: ='Data Sheet'!A17 -> Sales | C6: ='Data Sheet'!B17/'Data Sheet'!B$17 -> 1 | D6: ='Data Sheet'!C17/'Data Sheet'!C$17 -> 1 | E6: ='Data Sheet'!D17/'Data Sheet'!D$17 -> 1 | F6: ='Data Sheet'!E17/'Data Sheet'!E$17 -> 1 | G6: ='Data Sheet'!F17/'Data Sheet'!F$17 -> 1 | H6: ='Data Sheet'!G17/'Data Sheet'!G$17 -> 1 | I6: ='Data Sheet'!H17/'Data Sheet'!H$17 -> 1 | J6: ='Data Sheet'!I17/'Data Sheet'!I$17 -> 1 | ... L6: ='Data Sheet'!K17/'Data Sheet'!K$17 -> 1
B7: ='Data Sheet'!A18 -> Raw Material Cost | C7: ='Data Sheet'!B18/'Data Sheet'!B$17 -> 0.41028888 | D7: ='Data Sheet'!C18/'Data Sheet'!C$17 -> 0.400422 | E7: ='Data Sheet'!D18/'Data Sheet'!D$17 -> 0.4030781 | F7: ='Data Sheet'!E18/'Data Sheet'!E$17 -> 0.39456552 | G7: ='Data Sheet'!F18/'Data Sheet'!F$17 -> 0.42827677 | H7: ='Data Sheet'!G18/'Data Sheet'!G$17 -> 0.43608664 | I7: ='Data Sheet'!H18/'Data Sheet'!H$17 -> 0.46924728 | J7: ='Data Sheet'!I18/'Data Sheet'!I$17 -> 0.4333398 | ... L7: ='Data Sheet'!K18/'Data Sheet'!K$17 -> 0.45228641
B8: ='Data Sheet'!A19 -> Change in Inventory | C8: ='Data Sheet'!B19/'Data Sheet'!B$17 -> -0.0043423195 | D8: ='Data Sheet'!C19/'Data Sheet'!C$17 -> 0.0020256014 | E8: ='Data Sheet'!D19/'Data Sheet'!D$17 -> -0.00030526584 | F8: ='Data Sheet'!E19/'Data Sheet'!E$17 -> 0.0027147274 | G8: ='Data Sheet'!F19/'Data Sheet'!F$17 -> 0.0086118908 | H8: ='Data Sheet'!G19/'Data Sheet'!G$17 -> 0.00041947908 | I8: ='Data Sheet'!H19/'Data Sheet'!H$17 -> 0.0012380324 | J8: ='Data Sheet'!I19/'Data Sheet'!I$17 -> 0.00017771746 | ... L8: ='Data Sheet'!K19/'Data Sheet'!K$17 -> 0.0066544642
B9: ='Data Sheet'!A20 -> Power and Fuel | C9: ='Data Sheet'!B20/'Data Sheet'!B$17 -> 0.008895724 | D9: ='Data Sheet'!C20/'Data Sheet'!C$17 -> 0.0082993389 | E9: ='Data Sheet'!D20/'Data Sheet'!D$17 -> 0.0078351564 | F9: ='Data Sheet'!E20/'Data Sheet'!E$17 -> 0.0075157731 | G9: ='Data Sheet'!F20/'Data Sheet'!F$17 -> 0.0072084715 | H9: ='Data Sheet'!G20/'Data Sheet'!G$17 -> 0.0060633795 | I9: ='Data Sheet'!H20/'Data Sheet'!H$17 -> 0.0063387257 | J9: ='Data Sheet'!I20/'Data Sheet'!I$17 -> 0.0072056353 | ... L9: ='Data Sheet'!K20/'Data Sheet'!K$17 -> 0.0066079295
B10: ='Data Sheet'!A21 -> Other Mfr. Exp | C10: ='Data Sheet'!B21/'Data Sheet'!B$17 -> 0.087057475 | D10: ='Data Sheet'!C21/'Data Sheet'!C$17 -> 0.08434379 | E10: ='Data Sheet'!D21/'Data Sheet'!D$17 -> 0.077359451 | F10: ='Data Sheet'!E21/'Data Sheet'!E$17 -> 0.073046276 | G10: ='Data Sheet'!F21/'Data Sheet'!F$17 -> 0.060984945 | H10: ='Data Sheet'!G21/'Data Sheet'!G$17 -> 0.063951493 | I10: ='Data Sheet'!H21/'Data Sheet'!H$17 -> 0.062578409 | J10: ='Data Sheet'!I21/'Data Sheet'!I$17 -> 0.05468851 | ... L10: ='Data Sheet'!K21/'Data Sheet'!K$17 -> 0.051250233
B11: ='Data Sheet'!A22 -> Employee Cost | C11: ='Data Sheet'!B22/'Data Sheet'!B$17 -> 0.052560159 | D11: ='Data Sheet'!C22/'Data Sheet'!C$17 -> 0.052328035 | E11: ='Data Sheet'!D22/'Data Sheet'!D$17 -> 0.047697787 | F11: ='Data Sheet'!E22/'Data Sheet'!E$17 -> 0.045748184 | G11: ='Data Sheet'!F22/'Data Sheet'!F$17 -> 0.050140342 | H11: ='Data Sheet'!G22/'Data Sheet'!G$17 -> 0.048526103 | I11: ='Data Sheet'!H22/'Data Sheet'!H$17 -> 0.047111258 | J11: ='Data Sheet'!I22/'Data Sheet'!I$17 -> 0.048613804 | ... L11: ='Data Sheet'!K22/'Data Sheet'!K$17 -> 0.04924924
B12: ='Data Sheet'!A23 -> Selling and admin | C12: ='Data Sheet'!B23/'Data Sheet'!B$17 -> 0.20170677 | D12: ='Data Sheet'!C23/'Data Sheet'!C$17 -> 0.20402307 | E12: ='Data Sheet'!D23/'Data Sheet'!D$17 -> 0.19832104 | F12: ='Data Sheet'!E23/'Data Sheet'!E$17 -> 0.1915391 | G12: ='Data Sheet'!F23/'Data Sheet'!F$17 -> 0.16811261 | H12: ='Data Sheet'!G23/'Data Sheet'!G$17 -> 0.15566487 | I12: ='Data Sheet'!H23/'Data Sheet'!H$17 -> 0.14501486 | J12: ='Data Sheet'!I23/'Data Sheet'!I$17 -> 0.17416311 | ... L12: ='Data Sheet'!K23/'Data Sheet'!K$17 -> 0.16665633
B13: ='Data Sheet'!A24 -> Other Expenses | C13: ='Data Sheet'!B24/'Data Sheet'!B$17 -> 0.044327845 | D13: ='Data Sheet'!C24/'Data Sheet'!C$17 -> 0.041637361 | E13: ='Data Sheet'!D24/'Data Sheet'!D$17 -> 0.039506487 | F13: ='Data Sheet'!E24/'Data Sheet'!E$17 -> 0.042430184 | G13: ='Data Sheet'!F24/'Data Sheet'!F$17 -> 0.046674322 | H13: ='Data Sheet'!G24/'Data Sheet'!G$17 -> 0.044979598 | I13: ='Data Sheet'!H24/'Data Sheet'!H$17 -> 0.037421591 | J13: ='Data Sheet'!I24/'Data Sheet'!I$17 -> 0.045334109 | ... L13: ='Data Sheet'!K24/'Data Sheet'!K$17 -> 0.047325805
B14: ='Data Sheet'!A25 -> Other Income | C14: ='Data Sheet'!B25/'Data Sheet'!B$17 -> 0.018273928 | D14: ='Data Sheet'!C25/'Data Sheet'!C$17 -> 0.0099310733 | E14: ='Data Sheet'!D25/'Data Sheet'!D$17 -> 0.0081912999 | F14: ='Data Sheet'!E25/'Data Sheet'!E$17 -> 0.010657819 | G14: ='Data Sheet'!F25/'Data Sheet'!F$17 -> 0.0036148677 | H14: ='Data Sheet'!G25/'Data Sheet'!G$17 -> 0.0041757236 | I14: ='Data Sheet'!H25/'Data Sheet'!H$17 -> 0.0073951799 | J14: ='Data Sheet'!I25/'Data Sheet'!I$17 -> 0.013199561 | ... L14: ='Data Sheet'!K25/'Data Sheet'!K$17 -> 0.076363467
B15: ='Data Sheet'!A26 -> Depreciation | C15: ='Data Sheet'!B26/'Data Sheet'!B$17 -> 0.013026959 | D15: ='Data Sheet'!C26/'Data Sheet'!C$17 -> 0.014629343 | E15: ='Data Sheet'!D26/'Data Sheet'!D$17 -> 0.014372933 | F15: ='Data Sheet'!E26/'Data Sheet'!E$17 -> 0.025186638 | G15: ='Data Sheet'!F26/'Data Sheet'!F$17 -> 0.022837459 | H15: ='Data Sheet'!G26/'Data Sheet'!G$17 -> 0.020802349 | I15: ='Data Sheet'!H26/'Data Sheet'!H$17 -> 0.01876857 | J15: ='Data Sheet'!I26/'Data Sheet'!I$17 -> 0.019645858 | ... L15: ='Data Sheet'!K26/'Data Sheet'!K$17 -> 0.020676925
B16: ='Data Sheet'!A27 -> Interest | C16: ='Data Sheet'!B27/'Data Sheet'!B$17 -> 0.0010554249 | D16: ='Data Sheet'!C27/'Data Sheet'!C$17 -> 0.00073146715 | E16: ='Data Sheet'!D27/'Data Sheet'!D$17 -> 0.00083948105 | F16: ='Data Sheet'!E27/'Data Sheet'!E$17 -> 0.002966091 | G16: ='Data Sheet'!F27/'Data Sheet'!F$17 -> 0.0024878796 | H16: ='Data Sheet'!G27/'Data Sheet'!G$17 -> 0.0020211265 | I16: ='Data Sheet'!H27/'Data Sheet'!H$17 -> 0.0018818092 | J16: ='Data Sheet'!I27/'Data Sheet'!I$17 -> 0.0053961484 | ... L16: ='Data Sheet'!K27/'Data Sheet'!K$17 -> 0.0063597444
B17: ='Data Sheet'!A28 -> Profit before tax | C17: ='Data Sheet'!B28/'Data Sheet'!B$17 -> 0.19501236 | D17: ='Data Sheet'!C28/'Data Sheet'!C$17 -> 0.20554227 | E17: ='Data Sheet'!D28/'Data Sheet'!D$17 -> 0.2188756 | F17: ='Data Sheet'!E28/'Data Sheet'!E$17 -> 0.23037478 | G17: ='Data Sheet'!F28/'Data Sheet'!F$17 -> 0.22550396 | H17: ='Data Sheet'!G28/'Data Sheet'!G$17 -> 0.22649964 | I17: ='Data Sheet'!H28/'Data Sheet'!H$17 -> 0.22027072 | J17: ='Data Sheet'!I28/'Data Sheet'!I$17 -> 0.22499031 | ... L17: ='Data Sheet'!K28/'Data Sheet'!K$17 -> 0.28260532
... B21: ='Data Sheet'!A32 -> EBITDA | C21: ='Data Sheet'!B32/'Data Sheet'!B$17 -> 0.20909475 | D21: ='Data Sheet'!C32/'Data Sheet'!C$17 -> 0.22090308 | E21: ='Data Sheet'!D32/'Data Sheet'!D$17 -> 0.23408802 | F21: ='Data Sheet'!E32/'Data Sheet'!E$17 -> 0.25852751 | G21: ='Data Sheet'!F32/'Data Sheet'!F$17 -> 0.25082929 | H21: ='Data Sheet'!G32/'Data Sheet'!G$17 -> 0.24932311 | I21: ='Data Sheet'!H32/'Data Sheet'!H$17 -> 0.2409211 | J21: ='Data Sheet'!I32/'Data Sheet'!I$17 -> 0.25003231 | ... L21: ='Data Sheet'!K32/'Data Sheet'!K$17 -> 0.30964199
B23: ="Common Size Balance Sheet"&" - " &'Data Sheet'!$B$1 -> Common Size Balance Sheet - HINDUSTAN UNILEVER LTD
B25: Particulars | C25: ='Data Sheet'!B$16 -> 42825 | D25: ='Data Sheet'!C$16 -> 43190 | E25: ='Data Sheet'!D$16 -> 43555 | F25: ='Data Sheet'!E$16 -> 43921 | G25: ='Data Sheet'!F$16 -> 44286 | H25: ='Data Sheet'!G$16 -> 44651 | I25: ='Data Sheet'!H$16 -> 45016 | J25: ='Data Sheet'!I$16 -> 45382 | ... L25: ='Data Sheet'!K$16 -> 46112
B27: Total Liabilities | C27: ='Data Sheet'!B61/'Data Sheet'!B$61 -> 1 | D27: ='Data Sheet'!C61/'Data Sheet'!C$61 -> 1 | E27: ='Data Sheet'!D61/'Data Sheet'!D$61 -> 1 | F27: ='Data Sheet'!E61/'Data Sheet'!E$61 -> 1 | G27: ='Data Sheet'!F61/'Data Sheet'!F$61 -> 1 | H27: ='Data Sheet'!G61/'Data Sheet'!G$61 -> 1 | I27: ='Data Sheet'!H61/'Data Sheet'!H$61 -> 1 | J27: ='Data Sheet'!I61/'Data Sheet'!I$61 -> 1 | ... L27: ='Data Sheet'!K61/'Data Sheet'!K$61 -> 1
B28: ='Data Sheet'!A57 -> Equity Share Capital | C28: ='Data Sheet'!B57/'Data Sheet'!B$61 -> 0.013752706 | D28: ='Data Sheet'!C57/'Data Sheet'!C$61 -> 0.012092711 | E28: ='Data Sheet'!D57/'Data Sheet'!D$61 -> 0.011594825 | F28: ='Data Sheet'!E57/'Data Sheet'!E$61 -> 0.010718007 | G28: ='Data Sheet'!F57/'Data Sheet'!F$61 -> 0.0034186791 | H28: ='Data Sheet'!G57/'Data Sheet'!G$61 -> 0.0033330497 | I28: ='Data Sheet'!H57/'Data Sheet'!H$61 -> 0.0032157861 | J28: ='Data Sheet'!I57/'Data Sheet'!I$61 -> 0.0029940501 | ... L28: ='Data Sheet'!K57/'Data Sheet'!K$61 -> 0.0029471519
B29: ='Data Sheet'!A58 -> Reserves | C29: ='Data Sheet'!B58/'Data Sheet'!B$61 -> 0.41563734 | D29: ='Data Sheet'!C58/'Data Sheet'!C$61 -> 0.39553242 | E29: ='Data Sheet'!D58/'Data Sheet'!D$61 -> 0.41070374 | F29: ='Data Sheet'!E58/'Data Sheet'!E$61 -> 0.3976083 | G29: ='Data Sheet'!F58/'Data Sheet'!F$61 -> 0.6901222 | H29: ='Data Sheet'!G58/'Data Sheet'!G$61 -> 0.69250844 | I29: ='Data Sheet'!H58/'Data Sheet'!H$61 -> 0.68515402 | J29: ='Data Sheet'!I58/'Data Sheet'!I$61 -> 0.64955599 | ... L29: ='Data Sheet'!K58/'Data Sheet'!K$61 -> 0.60829216
B30: ='Data Sheet'!A59 -> Borrowings | C30: ='Data Sheet'!B59/'Data Sheet'!B$61 -> 0.017636572 | D30: ='Data Sheet'!C59/'Data Sheet'!C$61 -> 0 | E30: ='Data Sheet'!D59/'Data Sheet'!D$61 -> 0.0053142949 | F30: ='Data Sheet'!E59/'Data Sheet'!E$61 -> 0 | G30: ='Data Sheet'!F59/'Data Sheet'!F$61 -> 0 | H30: ='Data Sheet'!G59/'Data Sheet'!G$61 -> 0.014793067 | I30: ='Data Sheet'!H59/'Data Sheet'!H$61 -> 0.016681035 | J30: ='Data Sheet'!I59/'Data Sheet'!I$61 -> 0.018907108 | ... L30: ='Data Sheet'!K59/'Data Sheet'!K$61 -> 0.018535704
B31: ='Data Sheet'!A60 -> Other Liabilities | C31: ='Data Sheet'!B60/'Data Sheet'!B$61 -> 0.55297339 | D31: ='Data Sheet'!C60/'Data Sheet'!C$61 -> 0.59237487 | E31: ='Data Sheet'!D60/'Data Sheet'!D$61 -> 0.57238714 | F31: ='Data Sheet'!E60/'Data Sheet'!E$61 -> 0.5916737 | G31: ='Data Sheet'!F60/'Data Sheet'!F$61 -> 0.30645912 | H31: ='Data Sheet'!G60/'Data Sheet'!G$61 -> 0.28936544 | I31: ='Data Sheet'!H60/'Data Sheet'!H$61 -> 0.29494916 | J31: ='Data Sheet'!I60/'Data Sheet'!I$61 -> 0.32854285 | ... L31: ='Data Sheet'!K60/'Data Sheet'!K$61 -> 0.37022499
B33: Total Assets | C33: ='Data Sheet'!B66/'Data Sheet'!B$66 -> 1 | D33: ='Data Sheet'!C66/'Data Sheet'!C$66 -> 1 | E33: ='Data Sheet'!D66/'Data Sheet'!D$66 -> 1 | F33: ='Data Sheet'!E66/'Data Sheet'!E$66 -> 1 | G33: ='Data Sheet'!F66/'Data Sheet'!F$66 -> 1 | H33: ='Data Sheet'!G66/'Data Sheet'!G$66 -> 1 | I33: ='Data Sheet'!H66/'Data Sheet'!H$66 -> 1 | J33: ='Data Sheet'!I66/'Data Sheet'!I$66 -> 1 | ... L33: ='Data Sheet'!K66/'Data Sheet'!K$66 -> 1
B34: ='Data Sheet'!A62 -> Net Block | C34: ='Data Sheet'!B62/'Data Sheet'!B$66 -> 0.28135744 | D34: ='Data Sheet'!C62/'Data Sheet'!C$66 -> 0.25349905 | E34: ='Data Sheet'!D62/'Data Sheet'!D$66 -> 0.25310001 | F34: ='Data Sheet'!E62/'Data Sheet'!E$66 -> 0.27187019 | G34: ='Data Sheet'!F62/'Data Sheet'!F$66 -> 0.74837067 | H34: ='Data Sheet'!G62/'Data Sheet'!G$66 -> 0.73005134 | I34: ='Data Sheet'!H62/'Data Sheet'!H$66 -> 0.72085608 | J34: ='Data Sheet'!I62/'Data Sheet'!I$66 -> 0.68473289 | ... L34: ='Data Sheet'!K62/'Data Sheet'!K$66 -> 0.72020868
B35: ='Data Sheet'!A63 -> Capital Work in Progress | C35: ='Data Sheet'!B63/'Data Sheet'!B$66 -> 0.014580415 | D35: ='Data Sheet'!C63/'Data Sheet'!C$66 -> 0.02580898 | E35: ='Data Sheet'!D63/'Data Sheet'!D$66 -> 0.021793977 | F35: ='Data Sheet'!E63/'Data Sheet'!E$66 -> 0.029623381 | G35: ='Data Sheet'!F63/'Data Sheet'!F$66 -> 0.01083794 | H35: ='Data Sheet'!G63/'Data Sheet'!G$66 -> 0.018622529 | I35: ='Data Sheet'!H63/'Data Sheet'!H$66 -> 0.01549051 | J35: ='Data Sheet'!I63/'Data Sheet'!I$66 -> 0.013059155 | ... L35: ='Data Sheet'!K63/'Data Sheet'!K$66 -> 0.011036143
B36: ='Data Sheet'!A64 -> Investments | C36: ='Data Sheet'!B64/'Data Sheet'!B$66 -> 0.24156373 | D36: ='Data Sheet'!C64/'Data Sheet'!C$66 -> 0.16084425 | E36: ='Data Sheet'!D64/'Data Sheet'!D$66 -> 0.14579419 | F36: ='Data Sheet'!E64/'Data Sheet'!E$66 -> 0.062273607 | G36: ='Data Sheet'!F64/'Data Sheet'!F$66 -> 0.039409369 | H36: ='Data Sheet'!G64/'Data Sheet'!G$66 -> 0.049939012 | I36: ='Data Sheet'!H64/'Data Sheet'!H$66 -> 0.039437853 | J36: ='Data Sheet'!I64/'Data Sheet'!I$66 -> 0.058925455 | ... L36: ='Data Sheet'!K64/'Data Sheet'!K$66 -> 0.054666533
B37: ='Data Sheet'!A65 -> Other Assets | C37: ='Data Sheet'!B74/'Data Sheet'!B$66 -> 0.11524258 | D37: ='Data Sheet'!C74/'Data Sheet'!C$66 -> 0.15071101 | E37: ='Data Sheet'!D74/'Data Sheet'!D$66 -> 0.14198293 | F37: ='Data Sheet'!E74/'Data Sheet'!E$66 -> 0.18821019 | G37: ='Data Sheet'!F74/'Data Sheet'!F$66 -> 0.058699447 | H37: ='Data Sheet'!G74/'Data Sheet'!G$66 -> 0.057030607 | I37: ='Data Sheet'!H74/'Data Sheet'!H$66 -> 0.059895726 | J37: ='Data Sheet'!I74/'Data Sheet'!I$66 -> 0.057549466 | ... L37: ='Data Sheet'!K74/'Data Sheet'!K$66 -> 0.070919762
B38: ='Data Sheet'!A67 -> Receivables | C38: ='Data Sheet'!B67/'Data Sheet'!B$66 -> 0.06908188 | D38: ='Data Sheet'!C67/'Data Sheet'!C$66 -> 0.073340052 | E38: ='Data Sheet'!D67/'Data Sheet'!D$66 -> 0.09748242 | F38: ='Data Sheet'!E67/'Data Sheet'!E$66 -> 0.057013844 | G38: ='Data Sheet'!F67/'Data Sheet'!F$66 -> 0.025574629 | H38: ='Data Sheet'!G67/'Data Sheet'!G$66 -> 0.031713613 | I38: ='Data Sheet'!H67/'Data Sheet'!H$66 -> 0.04213364 | J38: ='Data Sheet'!I67/'Data Sheet'!I$66 -> 0.038183695 | ... L38: ='Data Sheet'!K67/'Data Sheet'!K$66 -> 0.042376282
B39: ='Data Sheet'!A68 -> Inventory | C39: ='Data Sheet'!B68/'Data Sheet'!B$66 -> 0.1617853 | D39: ='Data Sheet'!C68/'Data Sheet'!C$66 -> 0.14068973 | E39: ='Data Sheet'!D68/'Data Sheet'!D$66 -> 0.13817167 | F39: ='Data Sheet'!E68/'Data Sheet'!E$66 -> 0.13729966 | G39: ='Data Sheet'!F68/'Data Sheet'!F$66 -> 0.052065755 | H39: ='Data Sheet'!G68/'Data Sheet'!G$66 -> 0.058094347 | I39: ='Data Sheet'!H68/'Data Sheet'!H$66 -> 0.058171518 | J39: ='Data Sheet'!I68/'Data Sheet'!I$66 -> 0.051242849 | ... L39: ='Data Sheet'!K68/'Data Sheet'!K$66 -> 0.060059194
B40: ='Data Sheet'!A69 -> Cash & Bank | C40: ='Data Sheet'!B69/'Data Sheet'!B$66 -> 0.11638864 | D40: ='Data Sheet'!C69/'Data Sheet'!C$66 -> 0.19510693 | E40: ='Data Sheet'!D69/'Data Sheet'!D$66 -> 0.20167481 | F40: ='Data Sheet'!E69/'Data Sheet'!E$66 -> 0.25370913 | G40: ='Data Sheet'!F69/'Data Sheet'!F$66 -> 0.065042188 | H40: ='Data Sheet'!G69/'Data Sheet'!G$66 -> 0.054548549 | I40: ='Data Sheet'!H69/'Data Sheet'!H$66 -> 0.064014669 | J40: ='Data Sheet'!I69/'Data Sheet'!I$66 -> 0.096306489 | ... L40: ='Data Sheet'!K69/'Data Sheet'!K$66 -> 0.040733402

Sheet Data Sheet
A1: COMPANY NAME | B1: HINDUSTAN UNILEVER LTD | E1: =IF(B2<>B3, "A NEW VERSION OF THE WORKSHEET IS AVAILABLE", "")
A2: LATEST VERSION | B2: 2.1 | E2: PLEASE DO NOT MAKE ANY CHANGES TO THIS SHEET
A3: CURRENT VERSION | B3: 2.1
A5: META
A6: Number of shares | B6: =IF(B9>0, B9/B8, 0) -> 234.98652
A7: Face Value | B7: 1
A8: Current Price | B8: 2174.6
A9: Market Capitalization | B9: 511001.68
A15: PROFIT & LOSS
A16: Report Date | B16: 42825 | C16: 43190 | D16: 43555 | E16: 43921 | F16: 44286 | G16: 44651 | H16: 45016 | I16: 45382 | J16: 45747 | K16: 46112
A17: Sales | B17: 33162 | C17: 35545 | D17: 39310 | E17: 39783 | F17: 47028 | G17: 52446 | H17: 60580 | I17: 61896 | J17: 61328 | K17: 64468
A18: Raw Material Cost | B18: 13606 | C18: 14233 | D18: 15845 | E18: 15697 | F18: 20141 | G18: 22871 | H18: 28427 | I18: 26822 | J18: 26602 | K18: 29158
A19: Change in Inventory | B19: -144 | C19: 72 | D19: -12 | E19: 108 | F19: 405 | G19: 22 | H19: 75 | I19: 11 | J19: 125 | K19: 429
A20: Power and Fuel | B20: 295 | C20: 295 | D20: 308 | E20: 299 | F20: 339 | G20: 318 | H20: 384 | I20: 446 | J20: 403 | K20: 426
A21: Other Mfr. Exp | B21: 2887 | C21: 2998 | D21: 3041 | E21: 2906 | F21: 2868 | G21: 3354 | H21: 3791 | I21: 3385 | J21: 3687 | K21: 3304
A22: Employee Cost | B22: 1743 | C22: 1860 | D22: 1875 | E22: 1820 | F22: 2358 | G22: 2545 | H22: 2854 | I22: 3009 | J22: 2952 | K22: 3175
A23: Selling and admin | B23: 6689 | C23: 7252 | D23: 7796 | E23: 7620 | F23: 7906 | G23: 8164 | H23: 8785 | I23: 10780 | J23: 10145 | K23: 10744
A24: Other Expenses | B24: 1470 | C24: 1480 | D24: 1553 | E24: 1688 | F24: 2195 | G24: 2359 | H24: 2267 | I24: 2806 | J24: 2966 | K24: 3051
A25: Other Income | B25: 606 | C25: 353 | D25: 322 | E25: 424 | F25: 170 | G25: 219 | H25: 448 | I25: 817 | J25: 1355 | K25: 4923
A26: Depreciation | B26: 432 | C26: 520 | D26: 565 | E26: 1002 | F26: 1074 | G26: 1091 | H26: 1137 | I26: 1216 | J26: 1253 | K26: 1333
A27: Interest | B27: 35 | C27: 26 | D27: 33 | E27: 118 | F27: 117 | G27: 106 | H27: 114 | I27: 334 | J27: 381 | K27: 410
... A31: Dividend Amount | B31: 3672 | C31: 4320 | D31: 4752 | E31: 5400 | F31: 9517.5 | G31: 7990 | H31: 9165 | I31: 9870 | J31: 12455 | K31: 9635
A32: EBITDA | B32: =B28+B27+B26 -> 6934 | C32: =C28+C27+C26 -> 7852 | D32: =D28+D27+D26 -> 9202 | E32: =E28+E27+E26 -> 10285 | F32: =F28+F27+F26 -> 11796 | G32: =G28+G27+G26 -> 13076 | H32: =H28+H27+H26 -> 14595 | I32: =I28+I27+I26 -> 15476 | ... K32: =K28+K27+K26 -> 19962
A40: Quarters
A41: Report Date | B41: 45291 | C41: 45382 | D41: 45473 | E41: 45565 | F41: 45657 | G41: 45747 | H41: 45838 | I41: 45930 | J41: 46022 | K41: 46112
A42: Sales | B42: 15567 | C42: 15210 | D42: 15707 | E42: 15926 | F42: 15556 | G42: 15190 | H42: 16514 | I42: 15919 | J42: 16441 | K42: 16351
A43: Expenses | B43: 11902 | C43: 11675 | D43: 11965 | E43: 12139 | F43: 11867 | G43: 11572 | H43: 12797 | I43: 12137 | J43: 12660 | K43: 12514
A44: Other Income | B44: 184 | C44: 309 | D44: 209 | E44: 203 | F44: 733 | G44: 149 | H44: 74 | I44: 269 | J44: 4048 | K44: 503
A45: Depreciation | B45: 313 | C45: 320 | D45: 329 | E45: 338 | F45: 318 | G45: 318 | H45: 361 | I45: 322 | J45: 337 | K45: 348
A46: Interest | B46: 91 | C46: 105 | D46: 93 | E46: 110 | F46: 109 | G46: 77 | H46: 127 | I46: 124 | J46: 88 | K46: 76
A47: Profit before tax | B47: 3445 | C47: 3419 | D47: 3529 | E47: 3542 | F47: 3995 | G47: 3372 | H47: 3303 | I47: 3605 | J47: 7404 | K47: 3916
A48: Tax | B48: 937 | C48: 858 | D48: 917 | E48: 947 | F48: 1006 | G48: 897 | H48: 535 | I48: 911 | J48: 801 | K48: 922
A49: Net profit | B49: 2509 | C49: 2558 | D49: 2610 | E49: 2591 | F49: 2984 | G49: 2464 | H49: 2756 | I49: 2685 | J49: 6607 | K49: 2992
A50: Operating Profit | B50: 3665 | C50: 3535 | D50: 3742 | E50: 3787 | F50: 3689 | G50: 3618 | H50: 3717 | I50: 3782 | J50: 3781 | K50: 3837
A55: BALANCE SHEET
A56: Report Date | B56: 42825 | C56: 43190 | D56: 43555 | E56: 43921 | F56: 44286 | G56: 44651 | H56: 45016 | I56: 45382 | J56: 45747 | K56: 46112
A57: Equity Share Capital | B57: 216 | C57: 216 | D57: 216 | E57: 216 | F57: 235 | G57: 235 | H57: 235 | I57: 235 | J57: 235 | K57: 235
A58: Reserves | B58: 6528 | C58: 7065 | D58: 7651 | E58: 8013 | F58: 47439 | G58: 48826 | H58: 50069 | I58: 50983 | J58: 49167 | K58: 48504
A59: Borrowings | B59: 277 | D59: 99 | G59: 1043 | H59: 1219 | I59: 1484 | J59: 1648 | K59: 1478
A60: Other Liabilities | B60: 8685 | C60: 10581 | D60: 10663 | E60: 11924 | F60: 21066 | G60: 20402 | H60: 21554 | I60: 25787 | J60: 28813 | K60: 29521
A61: Total | B61: 15706 | C61: 17862 | D61: 18629 | E61: 20153 | F61: 68740 | G61: 70506 | H61: 73077 | I61: 78489 | J61: 79863 | K61: 79738
A62: Net Block | B62: 4419 | C62: 4528 | D62: 4715 | E62: 5479 | F62: 51443 | G62: 51473 | H62: 52678 | I62: 53744 | J62: 54335 | K62: 57428
A63: Capital Work in Progress | B63: 229 | C63: 461 | D63: 406 | E63: 597 | F63: 745 | G63: 1313 | H63: 1132 | I63: 1025 | J63: 1009 | K63: 880
A64: Investments | B64: 3794 | C64: 2873 | D64: 2716 | E64: 1255 | F64: 2709 | G64: 3521 | H64: 2882 | I64: 4625 | J64: 3810 | K64: 4359
A65: Other Assets | B65: 7264 | C65: 10000 | D65: 10792 | E65: 12822 | F65: 13843 | G65: 14199 | H65: 16385 | I65: 19095 | J65: 20709 | K65: 17071
A66: Total | B66: 15706 | C66: 17862 | D66: 18629 | E66: 20153 | F66: 68740 | G66: 70506 | H66: 73077 | I66: 78489 | J66: 79863 | K66: 79738
A67: Receivables | B67: 1085 | C67: 1310 | D67: 1816 | E67: 1149 | F67: 1758 | G67: 2236 | H67: 3079 | I67: 2997 | J67: 3819 | K67: 3379
A68: Inventory | B68: 2541 | C68: 2513 | D68: 2574 | E68: 2767 | F68: 3579 | G68: 4096 | H68: 4251 | I68: 4022 | J68: 4415 | K68: 4789
A69: Cash & Bank | B69: 1828 | C69: 3485 | D69: 3757 | E69: 5113 | F69: 4471 | G69: 3846 | H69: 4678 | I69: 7559 | J69: 7554 | K69: 3248
A70: No. of Equity Shares | B70: 2164349639 | C70: 2164528777 | D70: 2164704405 | E70: 2164704405 | F70: 2349567819 | G70: 2349591262 | H70: 2349591262 | I70: 2349591262 | J70: 2349591262 | K70: 2349591262
A71: New Bonus Shares
A72: Face value | B72: 1 | C72: 1 | D72: 1 | E72: 1 | F72: 1 | G72: 1 | H72: 1 | I72: 1 | J72: 1 | K72: 1
A74: Other Assets | B74: =B65-SUM(B67:B69) -> 1810 | C74: =C65-SUM(C67:C69) -> 2692 | D74: =D65-SUM(D67:D69) -> 2645 | E74: =E65-SUM(E67:E69) -> 3793 | F74: =F65-SUM(F67:F69) -> 4035 | G74: =G65-SUM(G67:G69) -> 4021 | H74: =H65-SUM(H67:H69) -> 4377 | I74: =I65-SUM(I67:I69) -> 4517 | ... K74: =K65-SUM(K67:K69) -> 5655
A80: CASH FLOW:
A81: Report Date | B81: 42825 | C81: 43190 | D81: 43555 | E81: 43921 | F81: 44286 | G81: 44651 | H81: 45016 | I81: 45382 | J81: 45747 | K81: 46112
A82: Cash from Operating Activity | B82: 5185 | C82: 6059 | D82: 5800 | E82: 7623 | F82: 9163 | G82: 9048 | H82: 9991 | I82: 15469 | J82: 11886 | K82: 10999
A83: Cash from Investing Activity | B83: -1173 | C83: -1063 | D83: -438 | E83: 1791 | F83: -1228 | G83: -1728 | H83: -1484 | I83: -5324 | J83: 6473 | K83: -3676
A84: Cash from Financing Activity | B84: -4214 | C84: -4975 | D84: -5390 | E84: -6819 | F84: -9309 | G84: -8015 | H84: -8953 | I84: -10034 | J84: -13101 | K84: -10810
A85: Net Cash Flow | B85: -202 | C85: 21 | D85: -28 | E85: 2595 | F85: -1374 | G85: -695 | H85: -446 | I85: 111 | J85: 5258 | K85: -3487
A90: PRICE: | B90: 872.61 | C90: 1276.11 | D90: 1633.53 | E90: 2199.83 | F90: 2327.12 | G90: 1960.7 | H90: 2450.44 | I90: 2167.14 | J90: 2161.88 | K90: 2055.2
A92: DERIVED:
A93: Adjusted Equity Shares in Cr | B93: 216.43 | C93: 216.45 | D93: 216.47 | E93: 216.48 | F93: 234.96 | G93: 234.96 | H93: 234.96 | I93: 234.96 | J93: 234.96 | K93: 234.96

Sheet Cash Flow Data
C2: 42064 | D2: 42430 | E2: 42795 | F2: 43160 | G2: 43525 | H2: 43891 | I2: 44256 | J2: 44621 | K2: 44986 | L2: 45352 | M2: 45717 | N2: 46082
B3: Cash from Operating Activity - | C3: 3272 | D3: 3974 | E3: 4953 | F3: 5913 | G3: 5728 | H3: 7305 | I3: 8957 | J3: 8964 | K3: 9626 | L3: 14884 | M3: 11606 | N3: 10496
B4: Profit from operations | C4: 5265 | D4: 5791 | E4: 6219 | F4: 7237 | G4: 8674 | H4: 9473 | I4: 11380 | J4: 12473 | K4: 13557 | L4: 14043 | M4: 14343 | N4: 14538
B5: Receivables | C5: 31 | D5: -279 | E5: 131 | F5: 0 | G5: 0 | H5: 0 | I5: 0 | J5: 0 | K5: 0 | L5: 0 | M5: 0 | N5: 0
B6: Inventory | C6: 145 | D6: 74 | E6: 38 | F6: -162 | G6: -195 | H6: -369 | I6: -472 | J6: -737 | K6: -332 | L6: 77 | M6: -540 | N6: -630
B7: Payables | C7: -373 | D7: 166 | E7: 508 | F7: 0 | G7: 0 | H7: 0 | I7: 0 | J7: 0 | K7: 0 | L7: 0 | M7: 0 | N7: 0
B8: Loans Advances | C8: -100 | D8: 0 | E8: -46 | F8: 0 | G8: 0 | H8: 0 | I8: 0 | J8: 0 | K8: 0 | L8: 0 | M8: 0 | N8: 0
B9: Other WC items | C9: 81 | D9: -74 | E9: -93 | F9: 1026 | G9: -66 | H9: 666 | I9: 416 | J9: -52 | K9: -531 | L9: 1059 | M9: -14 | N9: 1314
B10: Working capital changes | C10: -216 | D10: -113 | E10: 538 | F10: 864 | G10: -261 | H10: 297 | I10: -56 | J10: -789 | K10: -863 | L10: 1136 | M10: -554 | N10: 684
B11: Direct taxes | C11: -1772 | D11: -1696 | E11: -1783 | F11: -2188 | G11: -2685 | H11: -2465 | I11: -2367 | J11: -2720 | K11: -3068 | L11: -295 | M11: -2183 | N11: -4726
B12: Other operating items | C12: -5 | D12: -8 | E12: -21 | F12: 0 | G12: 0 | H12: 0 | I12: 0 | J12: 0 | K12: 0 | L12: 0 | M12: 0 | N12: 0
B13: Cash from Investing Activity - | C13: 280 | D13: -51 | E13: -752 | F13: -1261 | G13: -264 | H13: 1926 | I13: -1067 | J13: -1732 | K13: -1062 | L13: -4971 | M13: 6763 | N13: -3473
B14: Fixed assets purchased | C14: -527 | D14: -756 | E14: -1024 | F14: -853 | G14: -728 | H14: -765 | I14: -4051 | J14: -919 | K14: -1041 | L14: -1318 | M14: -1149 | N14: -1274
... B33: CFO/OP | C33: 0.97 | D33: 0.99 | E33: 1.11 | F33: 1.11 | G33: 0.97 | H33: 1.02 | I33: 1 | J33: 0.93 | K33: 0.93 | L33: 1.07 | M33: 0.97 | N33: 1.05
